Workbook
Name ProjFCFs: 'Master Data'!$K$21:$K$26
Name Slicer_Year: #N/A
Name t: 'Master Data'!$S$21:$S$26

Sheet Cover Page
A1: Stryker Corporation DCF Evaluation
A2: Harris Waseem
A3: BUS 341W & CSCI 48
A4: Luc Marest, Matthew Fried, Shu Yuan Wu | E4: Table of Contents
A5: March - May 9th, 2026 | D5: 1 | E5: =HYPERLINK("#'DCF Dashboard'!A2", "DCF Dashboard") -> DCF Dashboard
D6: 2 | E6: =HYPERLINK("#'WACC Dashboard'!A1", "WACC Dashboard") -> WACC Dashboard
D7: 3 | E7: =HYPERLINK("#'WACC PivotTable'!A1", "Stock Price Movement") -> Stock Price Movement
D8: 4 | E8: =HYPERLINK("#'Master Data'!A1", "Master Data") -> Master Data
D9: 5 | E9: =HYPERLINK("#'SYK'!A1", "Stryker Corporation Overview") -> Stryker Corporation Overview
E10: Competitors
D11: 6 | E11: =HYPERLINK("#'JNJ'!A1", "Johnson & Johnson OV") -> Johnson & Johnson OV
D12: 7 | E12: =HYPERLINK("#'ABBOTT'!A1","Abbott Laboratories OV") -> Abbott Laboratories OV
D13: 8 | E13: =HYPERLINK("#'BSX'!A1","Boston Scientific Corporation OV") -> Boston Scientific Corporation OV
D14: 9 | E14: =HYPERLINK("#'EDW'!A1","Edwards Lifesciences Corporation OV") -> Edwards Lifesciences Corporation OV

Sheet DCF Dashboard
A1: Simple Current Snapshot (2026 - 2027) | D1: Red Circle = Trading Hours are over | G1: =TODAY() -> 46160 | H1: =NOW()-TODAY() -> 0.63022176 | K1: Select below:
A2: In Millions USD | B2: Enterprise Value | C2: Net Debt | D2: Equity Value | E2: Diluted Shares | F2: Imp. Share Price | G2: Current Share Price | H2: Valuation | K2: Bloomberg | L2: =K2 & " Revenue & YoY Growth" -> Bloomberg Revenue & YoY Growth
B3: ='BBG Adj Highlights'!I10 -> 146697.27 | C3: ='Master Data'!M9 -> 9193.2857 | D3: ='WACC Dashboard'!B2 -> 134437.3 | E3: =SYK!L176 -> 386.5 | F3: =(B3-C3)/E3 -> 355.76711 | G3: {=IFERROR(_xlfn.STOCKHISTORY("SYK",$G$1,,,0,1),IFERROR(_xlfn.STOCKHISTORY("SYK",$G$1-1,,,0,1),IFERROR(_xlfn.STOCKHISTORY("SYK",$G$1-2,,,0,1),IFERROR(_xlfn.STOCKHISTORY("SYK",$G$1-3,,,0,1),0))))} -> 306.76 | H3: =G3/F3-1 -> -0.13775054 | K3: {=IF($K$2="Bloomberg",'Master Data'!A1:C10,'Master Data'!A13:C26)} -> Year | L3: Revenue Adj ($M) | M3: YoY Growth %
F4: Bloomberg Evaluation Approx. | K4: FY 2019 | L4: 14884 | M4: 0.094331
K5: FY 2020 | L5: 14351 | M5: -0.03581
B6: Enterprise Value | C6: Net Debt | D6: Equity Value | E6: Diluted Shares | F6: Imp. Share Price | G6: Current Share Price | H6: Valuation | K6: FY 2021 | L6: 17108 | M6: 0.192112
B7: ='Master Data'!L39 -> 91461.071 | C7: ='Master Data'!M21 -> 9193.2857 | D7: ='Master Data'!N39 -> 82267.785 | E7: 386.5 | F7: =(B7-C7)/E7 -> 212.85326 | G7: {=IFERROR(_xlfn.STOCKHISTORY("SYK",$G$1,,,0,1),IFERROR(_xlfn.STOCKHISTORY("SYK",$G$1-1,,,0,1),IFERROR(_xlfn.STOCKHISTORY("SYK",$G$1-2,,,0,1),IFERROR(_xlfn.STOCKHISTORY("SYK",$G$1-3,,,0,1),0))))} -> 306.76 | H7: =G7/F7-1 -> 0.44118065 | K7: FY 2022 | L7: 18449 | M7: 0.078384
F8: Quick Personal Evaluation Approx. | K8: FY 2023 | L8: 20498 | M8: 0.111063
A9: Simple Forward Snapshot (2027) | K9: FY 2024 | L9: 22595 | M9: 0.102303
A10: In Millions USD | B10: Enterprise Value | C10: Net Debt | D10: Equity Value | E10: Diluted Shares | F10: Imp. Share Price | G10: Current Share Price | H10: Valuation | K10: FY 2025 | L10: 25116 | M10: 0.111573
B11: ='Master Data'!L40 -> 94204.903 | C11: ='Master Data'!M22 -> 5874.5714 | D11: ='Master Data'!N40 -> 85011.617 | E11: 386.5 | F11: =(B11-C11)/E11 -> 228.53902 | G11: {=IFERROR(_xlfn.STOCKHISTORY("SYK",$G$1,,,0,1),IFERROR(_xlfn.STOCKHISTORY("SYK",$G$1-1,,,0,1),IFERROR(_xlfn.STOCKHISTORY("SYK",$G$1-2,,,0,1),IFERROR(_xlfn.STOCKHISTORY("SYK",$G$1-3,,,0,1),0))))} -> 306.76 | H11: =G11/F11-1 -> 0.34226531 | K11: FY 2026 | L11: 27317.214 | M11: 0.087641913
F12: Quick Personal Future Evaluation Approx. | K12: FY 2027 | L12: 29602.893 | M12: 0.08367173
A15: Advanced Forward Snapshot (2026 - 2031)
A16: In Millions USD | B16: Enterprise Value | C16: Net Debt | D16: Equity Value | E16: Diluted Shares | F16: Imp. Share Price | G16: Current Share Price | H16: Valuation
B17: ='Master Data'!L33 -> 118366.12 | C17: ='Master Data'!M21 -> 9193.2857 | D17: =B17-C17 -> 109172.83 | E17: 386.5 | F17: =(B17-C17)/E17 -> 282.46528 | G17: =INDEX(F2:H17,2,2) -> 306.76 | H17: =G17/F17-1 -> 0.086009583
F18: In-depth Personal Future Evaluation Approx.
A20: Sensitivity Analysis (2026 - 2031)
A21: WACC / Terminal
A22: =F17 -> 282.46528 | B22: 0.02 | C22: 0.025 | D22: 0.03 | E22: 0.035 | F22: 0.04 | G22: 0.045
A23: 0.075 | B23: 243.68155 | C23: 259.86489 | D23: 278.85893 | E23: 301.46551 | F23: 328.82357 | G23: 362.60703
A24: 0.08 | B24: 244.95013 | C24: 261.20939 | D24: 280.29253 | E24: 303.00515 | F24: 330.49155 | G24: 364.43349
A25: 0.085 | B25: 246.21871 | C25: 262.55389 | D25: 281.72613 | E25: 304.5448 | F25: 332.15953 | G25: 366.25995
A26: 0.0876 | B26: 246.87838 | C26: 263.25303 | D26: 282.4716 | E26: 305.34542 | F26: 333.02688 | G26: 367.20971
A27: 0.09 | B27: 247.4873 | C27: 263.89839 | D27: 283.15973 | E27: 306.08445 | F27: 333.82751 | G27: 368.08641
A28: 0.095 | B28: 248.75588 | C28: 265.24289 | D28: 284.59333 | E28: 307.62409 | F28: 335.4955 | G28: 369.91287
A29: 0.1 | B29: 250.02446 | C29: 266.58739 | D29: 286.02693 | E29: 309.16374 | F29: 337.16348 | G29: 371.73933
B31: WACC | C31: 0.087577961
B32: T-G | C32: 0.03

Sheet DCF PivotTable
A3: Row Labels | B3: Average of MedSurg % of Rev | C3: Average of Ortho % of Rev
A4: FY 2019 | B4: 0.44654364 | C4: 0.55345636
A5: FY 2020 | B5: 0.56940339 | C5: 0.43059661
A6: FY 2021 | B6: 0.58149258 | C6: 0.41850742
A7: FY 2022 | B7: 0.55751695 | C7: 0.44248305
A8: FY 2023 | B8: 0.59043851 | C8: 0.40956149
A9: FY 2024 | B9: 0.59337496 | C9: 0.40662504
A10: FY 2025 | B10: 0.59827395 | C10: 0.40172605
A15: Row Labels | B15: Average of EBITDA Margin % | C15: Average of YoY Growth % | D15: Average of CapEx % | E15: Average of NWC %
A16: FY 2019 | B16: 0.29259608 | C16: 0.094331 | D16: 0.04360387 | E16: 0.44732599
A17: FY 2020 | B17: 0.27656609 | C17: -0.03581 | D17: 0.033934917 | E17: 0.32513414
A18: FY 2021 | B18: 0.28559738 | C18: 0.192112 | D18: 0.030687398 | E18: 0.31961655
A19: FY 2022 | B19: 0.26581387 | C19: 0.078384 | D19: 0.031871646 | E19: 0.21529622
A20: FY 2023 | B20: 0.26929457 | C20: 0.111063 | D20: 0.028051517 | E20: 0.22426578
A21: FY 2024 | B21: 0.28023899 | C21: 0.102303 | D21: 0.033414472 | E21: 0.32002655
A22: FY 2025 | B22: 0.2894171 | C22: 0.111573 | D22: 0.030299411 | E22: 0.27715401
A23: FY 2026 | B23: 0.27729002 | C23: 0.087577961 | D23: 0.026896155 | E23: 0.23388512
A24: FY 2027 | B24: 0.28120777 | C24: 0.0837 | D24: 0.02782944 | E24: 0.24466004
A25: FY 2028 | B25: 0.28268081 | C25: 0.07 | D25: 0.027539011 | E25: 0.24526955
A26: FY 2029 | B26: 0.28820306 | C26: 0.06 | D26: 0.026563039 | E26: 0.25529314
A27: FY 2030 | B27: 0.28881887 | C27: 0.05 | D27: 0.025986674 | E27: 0.2514053
A28: FY 2031 | B28: 0.28807985 | C28: 0.03 | D28: 0.024202131 | E28: 0.24598012
A32: Row Labels | B32: Average of Net Debt ($M) | C32: Average of Equity ($M) | D32: Sum of Equity - Debt
A33: FY 2019 | B33: 6665 | C33: 78638.306 | D33: 71973.306
A34: FY 2020 | B34: 10967 | C34: 92184.279 | D34: 81217.279
A35: FY 2021 | B35: 9460 | C35: 100963 | D35: 91503
A36: FY 2022 | B36: 11120 | C36: 92620.452 | D36: 81500.452
A37: FY 2023 | B37: 9942 | C37: 113873.87 | D37: 103931.87
A38: FY 2024 | B38: 9104 | C38: 137323.07 | D38: 128219.07
A39: FY 2025 | B39: 11759 | C39: 134437.27 | D39: 122678.27

Sheet Master Data
A1: Year | B1: Revenue Adj ($M) | C1: YoY Growth % | D1: Gross Margin % | E1: EBITDA Adj ($M) | F1: EBITDA Margin % | G1: EBIT ($M) | H1: NOPAT ($M) | I1: Net Income Adj ($M) | J1: Adj EPS | K1: FCF ($M) | L1: EV ($M) | M1: Net Debt ($M) | N1: Equity ($M) | O1: MedSurg % of Rev | P1: Ortho % of Rev | Q1: Rule of 40
A2: FY 2019 | B2: =_xlfn.XLOOKUP("*"&A2&"*",'BBG Adj Highlights'!$C$4:$L$4,'BBG Adj Highlights'!$C$12:$L$12, , 2) -> 14884 | C2: =_xlfn.XLOOKUP("*"&A2&"*",'BBG Adj Highlights'!$C$4:$L$4,'BBG Adj Highlights'!$C$13:$L$13, , 2)/100 -> 0.094331 | D2: =_xlfn.XLOOKUP("*"&RIGHT(A2,4)&"*", SYK!$E$3:$N$3, SYK!$E$27:$N$27,,2)/100 -> 0.659 | E2: =_xlfn.XLOOKUP("*"&A2&"*",'BBG Adj Highlights'!$C$4:$L$4,'BBG Adj Highlights'!$C$16:$L$16,,2) -> 4355 | F2: =_xlfn.XLOOKUP("*"&A2&"*",'BBG Adj Highlights'!$C$4:$L$4,'BBG Adj Highlights'!$C$17:$L$17,,2) /100 -> 0.29259608 | G2: =_xlfn.XLOOKUP("*"&A2&"*",'BBG Adjusted'!$C$4:$L$4,'BBG Adjusted'!$C$65:$L$65,,2) -> 3444 | I2: =_xlfn.XLOOKUP("*"&A2&"*",'BBG Adj Highlights'!$C$4:$L$4,'BBG Adj Highlights'!$C$18:$L$18,,2) -> 2764 | J2: =_xlfn.XLOOKUP("*"&A2&"*",'BBG Adj Highlights'!$C$4:$L$4,'BBG Adj Highlights'!$C$20:$L$20,,2) -> 7.2726 | K2: =_xlfn.XLOOKUP("*"&A2&"*",'BBG Adj Highlights'!$C$4:$L$4,'BBG Adj Highlights'!$C$25:$L$25,,2) -> 1542 | L2: =_xlfn.XLOOKUP("*"&A2&"*",'BBG Adj Highlights'!$C$4:$L$4,'BBG Adj Highlights'!$C$10:$L$10,,2) -> 85690.306 | M2: =_xlfn.XLOOKUP("*"&RIGHT(A2,4)&"*", SYK!$E$3:$N$3, SYK!$E$31:$N$31,,2) -> 6665 | N2: =_xlfn.XLOOKUP("*"&A2&"*",'BBG Adj Highlights'!$C$4:$L$4,'BBG Adj Highlights'!$C$6:$L$6, , 2) -> 78638.306 | O2: =_xlfn.XLOOKUP("*"&A2&"*",Segments!$E$3:$N$3,Segments!$E$7:$N$7,,2)/100 -> 0.44654364 | P2: =1-O2 -> 0.55345636 | Q2: =SUM(C2,F2) -> 0.38692708
A3: FY 2020 | B3: 14351 | C3: -0.03581 | D3: 0.638 | E3: 3969 | F3: 0.27656609 | G3: 3027 | I3: 2446 | J3: 6.4272 | K3: 2790 | L3: 103585.28 | M3: =_xlfn.XLOOKUP("*"&RIGHT(A3,4)&"*", SYK!$E$3:$N$3, SYK!$E$31:$N$31,,2) -> 10967 | N3: 92184.279 | O3: 0.56940339 | P3: 0.43059661 | Q3: =SUM(C3,F3) -> 0.24075609
A4: FY 2021 | B4: 17108 | C4: 0.192112 | D4: 0.641 | E4: 4886 | F4: 0.28559738 | G4: 3763 | I4: 2985 | J4: 7.8022 | K4: 2738 | L4: 110845 | M4: =_xlfn.XLOOKUP("*"&RIGHT(A4,4)&"*", SYK!$E$3:$N$3, SYK!$E$31:$N$31,,2) -> 9460 | N4: 100963 | O4: 0.58149258 | P4: 0.41850742 | Q4: =SUM(C4,F4) -> 0.47770938
A5: FY 2022 | B5: 18449 | C5: 0.078384 | D5: 0.631 | E5: 4904 | F5: 0.26581387 | G5: 3757 | I5: 3076 | J5: 8.0486 | K5: 2036 | L5: 104218.45 | M5: =_xlfn.XLOOKUP("*"&RIGHT(A5,4)&"*", SYK!$E$3:$N$3, SYK!$E$31:$N$31,,2) -> 11120 | N5: 92620.452 | O5: 0.55751695 | P5: 0.44248305 | Q5: =SUM(C5,F5) -> 0.34419787
A6: FY 2023 | B6: 20498 | C6: 0.111063 | D6: 0.639 | E6: 5520 | F6: 0.26929457 | G6: 4320 | I6: 3563 | J6: 9.2873 | K6: 3136 | L6: 124314.87 | M6: =_xlfn.XLOOKUP("*"&RIGHT(A6,4)&"*", SYK!$E$3:$N$3, SYK!$E$31:$N$31,,2) -> 9942 | N6: 113873.87 | O6: 0.59043851 | P6: 0.40956149 | Q6: =SUM(C6,F6) -> 0.38035757
A7: FY 2024 | B7: 22595 | C7: 0.102303 | D7: 0.64461164 | E7: 6332 | F7: 0.28023899 | G7: 5092 | I7: 4205 | J7: 10.9032 | K7: 3487 | L7: 146950.07 | M7: =_xlfn.XLOOKUP("*"&RIGHT(A7,4)&"*", SYK!$E$3:$N$3, SYK!$E$31:$N$31,,2) -> 9104 | N7: 137323.07 | O7: 0.59337496 | P7: 0.40662504 | Q7: =SUM(C7,F7) -> 0.38254199
A8: FY 2025 | B8: 25116 | C8: 0.111573 | D8: 0.653 | E8: 7269 | F8: 0.2894171 | G8: 5871 | I8: 4686 | J8: 12.1257 | K8: 4283 | L8: 146697.27 | M8: =_xlfn.XLOOKUP("*"&RIGHT(A8,4)&"*", SYK!$E$3:$N$3, SYK!$E$31:$N$31,,2) -> 11759 | N8: 134437.27 | O8: 0.59827395 | P8: 0.40172605 | Q8: =SUM(C8,F8) -> 0.4009901
A9: FY 2026 | B9: =_xlfn.XLOOKUP("*"&A9&"*",'BBG Adj Highlights'!$C$4:$L$4,'BBG Adj Highlights'!$C$12:$L$12, , 2) -> 27317.214 | C9: =_xlfn.XLOOKUP("*"&A9&"*",'BBG Adj Highlights'!$C$4:$L$4,'BBG Adj Highlights'!$C$13:$L$13, , 2)/100 -> 0.087641913 | D9: =_xlfn.XLOOKUP("*"&RIGHT(A9,4)&"*", SYK!$E$3:$N$3, SYK!$E$27:$N$27,,2)/100 -> 0.65211765 | E9: =_xlfn.XLOOKUP("*"&A9&"*",'BBG Adj Highlights'!$C$4:$L$4,'BBG Adj Highlights'!$C$16:$L$16,,2) -> 7838.9167 | F9: =_xlfn.XLOOKUP("*"&A9&"*",'BBG Adj Highlights'!$C$4:$L$4,'BBG Adj Highlights'!$C$17:$L$17,,2) /100 -> 0.28695886 | G9: =_xlfn.XLOOKUP("*"&A9&"*",'BBG Adjusted'!$C$4:$L$4,'BBG Adjusted'!$C$65:$L$65,,2) -> 7296.6923 | I9: =_xlfn.XLOOKUP("*"&A9&"*",'BBG Adj Highlights'!$C$4:$L$4,'BBG Adj Highlights'!$C$18:$L$18,,2) -> 5814.833 | J9: =_xlfn.XLOOKUP("*"&A9&"*",'BBG Adj Highlights'!$C$4:$L$4,'BBG Adj Highlights'!$C$20:$L$20,,2) -> 15.013 | K9: =_xlfn.XLOOKUP("*"&A9&"*",'BBG Adj Highlights'!$C$4:$L$4,'BBG Adj Highlights'!$C$25:$L$25,,2) -> 5415.525 | L9: =_xlfn.XLOOKUP("*"&A9&"*",'BBG Adj Highlights'!$C$4:$L$4,'BBG Adj Highlights'!$C$10:$L$10,,2) -> 0 | M9: =_xlfn.XLOOKUP("*"&RIGHT(A9,4)&"*", SYK!$E$3:$N$3, SYK!$E$31:$N$31,,2) -> 9193.2857 | N9: =_xlfn.XLOOKUP("*"&A9&"*",'BBG Adj Highlights'!$C$4:$L$4,'BBG Adj Highlights'!$C$6:$L$6, , 2) -> 0 | O9: =IFERROR(_xlfn.XLOOKUP("*"&A9&"*",Segments!$E$3:$N$3,Segments!$E$7:$N$7,,2)/100,0) -> 0 | P9: =IFERROR(_xlfn.XLOOKUP("*"&A9&"*",Segments!$E$3:$N$3,Segments!$E$21:$N$21,,2)/100,0) -> 0 | Q9: =SUM(C9,F9) -> 0.37460077
A10: FY 2027 | B10: =_xlfn.XLOOKUP("*"&A10&"*",'BBG Adj Highlights'!$C$4:$L$4,'BBG Adj Highlights'!$C$12:$L$12, , 2) -> 29602.893 | C10: =_xlfn.XLOOKUP("*"&A10&"*",'BBG Adj Highlights'!$C$4:$L$4,'BBG Adj Highlights'!$C$13:$L$13, , 2)/100 -> 0.08367173 | D10: =_xlfn.XLOOKUP("*"&RIGHT(A10,4)&"*", SYK!$E$3:$N$3, SYK!$E$27:$N$27,,2)/100 -> 0.6546326 | E10: =_xlfn.XLOOKUP("*"&A10&"*",'BBG Adj Highlights'!$C$4:$L$4,'BBG Adj Highlights'!$C$16:$L$16,,2) -> 8626.3478 | F10: =_xlfn.XLOOKUP("*"&A10&"*",'BBG Adj Highlights'!$C$4:$L$4,'BBG Adj Highlights'!$C$17:$L$17,,2) /100 -> 0.29140219 | G10: =_xlfn.XLOOKUP("*"&A10&"*",'BBG Adjusted'!$C$4:$L$4,'BBG Adjusted'!$C$65:$L$65,,2) -> 8076.7692 | I10: =_xlfn.XLOOKUP("*"&A10&"*",'BBG Adj Highlights'!$C$4:$L$4,'BBG Adj Highlights'!$C$18:$L$18,,2) -> 6484.64 | J10: =_xlfn.XLOOKUP("*"&A10&"*",'BBG Adj Highlights'!$C$4:$L$4,'BBG Adj Highlights'!$C$20:$L$20,,2) -> 16.746 | K10: =_xlfn.XLOOKUP("*"&A10&"*",'BBG Adj Highlights'!$C$4:$L$4,'BBG Adj Highlights'!$C$25:$L$25,,2) -> 5637.65 | L10: =_xlfn.XLOOKUP("*"&A10&"*",'BBG Adj Highlights'!$C$4:$L$4,'BBG Adj Highlights'!$C$10:$L$10,,2) -> 0 | M10: =_xlfn.XLOOKUP("*"&RIGHT(A10,4)&"*", SYK!$E$3:$N$3, SYK!$E$31:$N$31,,2) -> 5874.5714 | N10: =_xlfn.XLOOKUP("*"&A10&"*",'BBG Adj Highlights'!$C$4:$L$4,'BBG Adj Highlights'!$C$6:$L$6, , 2) -> 0 | O10: =IFERROR(_xlfn.XLOOKUP("*"&A10&"*",Segments!$E$3:$N$3,Segments!$E$7:$N$7,,2)/100,0) -> 0 | P10: =IFERROR(_xlfn.XLOOKUP("*"&A10&"*",Segments!$E$3:$N$3,Segments!$E$21:$N$21,,2)/100,0) -> 0 | Q10: =SUM(C10,F10) -> 0.37507392
M11: Extracted Bloomberg Valuations
A13: Year | B13: Revenue Adj ($M) | C13: YoY Growth % | D13: Gross Margin % | E13: EBITDA Adj ($M) | F13: EBITDA Margin % | G13: EBIT ($M) | H13: NOPAT ($M) | I13: Net Income Adj ($M) | J13: Adj EPS | K13: FCF ($M) | L13: EV ($M) | M13: Net Debt ($M) | N13: Equity ($M) | O13: CapEx % | P13: NWC ($M) | Q13: NWC % | R13: ∆ NWC
A14: FY 2019 | B14: 14884 | C14: 0.094331 | D14: 0.659 | E14: 4355 | F14: 0.29259608 | G14: =_xlfn.XLOOKUP("*"&A14&"*",'BBG Adjusted'!$C$4:$L$4,'BBG Adjusted'!$C$65:$L$65,,2) -> 3444 | I14: 2764 | J14: 7.2726 | K14: 1542 | L14: 85690.306 | M14: 6665 | N14: =_xlfn.XLOOKUP("*"&A14&"*",'BBG Adj Highlights'!$C$4:$L$4,'BBG Adj Highlights'!$C$6:$L$6, , 2) -> 78638.306 | O14: =_xlfn.XLOOKUP("*"&RIGHT(A2,4)&"*",SYK!$E$3:$N$3,SYK!$E$276:$N$276,,2) / 100 -> 0.04360387 | P14: =_xlfn.XLOOKUP("*"&RIGHT(A14,4)&"*", SYK!$E$3:$N$3, SYK!$E$203:$N$203,,2)-_xlfn.XLOOKUP("*"&RIGHT(A14,4)&"*", SYK!$E$3:$N$3, SYK!$E$222:$N$222,,2) -> 6658 | Q14: =P14/B14 -> 0.44732599
A15: FY 2020 | B15: 14351 | C15: -0.03581 | D15: 0.638 | E15: 3969 | F15: 0.27656609 | G15: 3027 | I15: 2446 | J15: 6.4272 | K15: 2790 | L15: 103585.28 | M15: 10967 | N15: =_xlfn.XLOOKUP("*"&A15&"*",'BBG Adj Highlights'!$C$4:$L$4,'BBG Adj Highlights'!$C$6:$L$6, , 2) -> 92184.279 | O15: =_xlfn.XLOOKUP("*"&RIGHT(A3,4)&"*",SYK!$E$3:$N$3,SYK!$E$276:$N$276,,2) / 100 -> 0.033934917 | P15: =_xlfn.XLOOKUP("*"&RIGHT(A15,4)&"*", SYK!$E$3:$N$3, SYK!$E$203:$N$203,,2)-_xlfn.XLOOKUP("*"&RIGHT(A15,4)&"*", SYK!$E$3:$N$3, SYK!$E$222:$N$222,,2) -> 4666 | Q15: =P15/B15 -> 0.32513414 | R15: =P15-P14 -> -1992
A16: FY 2021 | B16: 17108 | C16: 0.192112 | D16: 0.641 | E16: 4886 | F16: 0.28559738 | G16: 3763 | I16: 2985 | J16: 7.8022 | K16: 2738 | L16: 110845 | M16: 9460 | N16: 100963 | O16: =_xlfn.XLOOKUP("*"&RIGHT(A4,4)&"*",SYK!$E$3:$N$3,SYK!$E$276:$N$276,,2) / 100 -> 0.030687398 | P16: =_xlfn.XLOOKUP("*"&RIGHT(A16,4)&"*", SYK!$E$3:$N$3, SYK!$E$203:$N$203,,2)-_xlfn.XLOOKUP("*"&RIGHT(A16,4)&"*", SYK!$E$3:$N$3, SYK!$E$222:$N$222,,2) -> 5468 | Q16: =P16/B16 -> 0.31961655 | R16: =P16-P15 -> 802
A17: FY 2022 | B17: 18449 | C17: 0.078384 | D17: 0.631 | E17: 4904 | F17: 0.26581387 | G17: 3757 | I17: 3076 | J17: 8.0486 | K17: 2036 | L17: 104218.45 | M17: 11120 | N17: 92620.452 | O17: =_xlfn.XLOOKUP("*"&RIGHT(A5,4)&"*",SYK!$E$3:$N$3,SYK!$E$276:$N$276,,2) / 100 -> 0.031871646 | P17: =_xlfn.XLOOKUP("*"&RIGHT(A17,4)&"*", SYK!$E$3:$N$3, SYK!$E$203:$N$203,,2)-_xlfn.XLOOKUP("*"&RIGHT(A17,4)&"*", SYK!$E$3:$N$3, SYK!$E$222:$N$222,,2) -> 3972 | Q17: =P17/B17 -> 0.21529622 | R17: =P17-P16 -> -1496
A18: FY 2023 | B18: 20498 | C18: 0.111063 | D18: 0.639 | E18: 5520 | F18: 0.26929457 | G18: 4320 | I18: 3563 | J18: 9.2873 | K18: 3136 | L18: 124314.87 | M18: 9942 | N18: 113873.87 | O18: =_xlfn.XLOOKUP("*"&RIGHT(A6,4)&"*",SYK!$E$3:$N$3,SYK!$E$276:$N$276,,2) / 100 -> 0.028051517 | P18: =_xlfn.XLOOKUP("*"&RIGHT(A18,4)&"*", SYK!$E$3:$N$3, SYK!$E$203:$N$203,,2)-_xlfn.XLOOKUP("*"&RIGHT(A18,4)&"*", SYK!$E$3:$N$3, SYK!$E$222:$N$222,,2) -> 4597 | Q18: =P18/B18 -> 0.22426578 | R18: =P18-P17 -> 625
A19: FY 2024 | B19: 22595 | C19: 0.102303 | D19: 0.64461164 | E19: 6332 | F19: 0.28023899 | G19: 5092 | I19: 4205 | J19: 10.9032 | K19: 3487 | L19: 146950.07 | M19: 9104 | N19: 137323.07 | O19: =_xlfn.XLOOKUP("*"&RIGHT(A7,4)&"*",SYK!$E$3:$N$3,SYK!$E$276:$N$276,,2) / 100 -> 0.033414472 | P19: =_xlfn.XLOOKUP("*"&RIGHT(A19,4)&"*", SYK!$E$3:$N$3, SYK!$E$203:$N$203,,2)-_xlfn.XLOOKUP("*"&RIGHT(A19,4)&"*", SYK!$E$3:$N$3, SYK!$E$222:$N$222,,2) -> 7231 | Q19: =P19/B19 -> 0.32002655 | R19: =P19-P18 -> 2634
A20: FY 2025 | B20: 25116 | C20: 0.111573 | D20: 0.653 | E20: 7269 | F20: 0.2894171 | G20: 5871 | I20: 4686 | J20: 12.1257 | K20: 4283 | L20: 146697.27 | M20: 11759 | N20: 134437.27 | O20: =_xlfn.XLOOKUP("*"&RIGHT(A8,4)&"*",SYK!$E$3:$N$3,SYK!$E$276:$N$276,,2) / 100 -> 0.030299411 | P20: =_xlfn.XLOOKUP("*"&RIGHT(A20,4)&"*", SYK!$E$3:$N$3, SYK!$E$203:$N$203,,2)-_xlfn.XLOOKUP("*"&RIGHT(A20,4)&"*", SYK!$E$3:$N$3, SYK!$E$222:$N$222,,2) -> 6961 | Q20: =P20/B20 -> 0.27715401 | R20: =P20-P19 -> -270
A21: FY 2026 | B21: =B20*(1+'DCF Dashboard'!C31) -> 27315.608 | C21: ='WACC Dashboard'!B16 -> 0.087577961 | E21: =B21*F21 -> 7574.3455 | F21: {=TREND(F14:F20,(VALUE(RIGHT(A14:A20,4))),VALUE(RIGHT(A21,4)))} -> 0.27729002 | G21: =E21-(B21*0.045) -> 6345.1431 | H21: =G21*(1-15.5%) -> 5361.646 | K21: =H21+(B21*0.045)-(B21*O21)-R21 -> 6428.4492 | M21: 9193.2857 | O21: {=TREND(O14:O20,(VALUE(RIGHT(A14:A20,4))),VALUE(RIGHT(A21,4)))} -> 0.026896155 | P21: {=TREND(P14:P20,(VALUE(RIGHT(A14:A20,4))),VALUE(RIGHT(A21,4)))} -> 6388.7143 | Q21: =P21/B21 -> 0.23388512 | R21: =P21-P20 -> -572.28571 | S21: 1
A22: FY 2027 | B22: =B21*(1+C22) -> 29601.924 | C22: 0.0837 | E22: =B22*F22 -> 8324.2911 | F22: {=TREND(F15:F21,(VALUE(RIGHT(A15:A21,4))),VALUE(RIGHT(A22,4)))} -> 0.28120777 | G22: =E22-(B22*0.045) -> 6992.2045 | H22: =G22*(1-15.5%) -> 5908.4128 | K22: =H22+(B22*0.045)-(B22*O22)-R22 -> 5563.0005 | M22: 5874.5714 | O22: {=TREND(O15:O21,(VALUE(RIGHT(A15:A21,4))),VALUE(RIGHT(A22,4)))} -> 0.02782944 | P22: {=TREND(P15:P21,(VALUE(RIGHT(A15:A21,4))),VALUE(RIGHT(A22,4)))} -> 7242.4082 | Q22: =P22/B22 -> 0.24466004 | R22: =P22-P21 -> 853.69388 | S22: 2
A23: FY 2028 | B23: =B22*(1+C23) -> 31674.059 | C23: 0.07 | E23: =B23*F23 -> 8953.6489 | F23: {=TREND(F16:F22,(VALUE(RIGHT(A16:A22,4))),VALUE(RIGHT(A23,4)))} -> 0.28268081 | G23: =E23-(B23*0.045) -> 7528.3162 | H23: =G23*(1-15.5%) -> 6361.4272 | K23: =H23+(B23*0.045)-(B23*O23)-R23 -> 6388.2135 | O23: {=TREND(O16:O22,(VALUE(RIGHT(A16:A22,4))),VALUE(RIGHT(A23,4)))} -> 0.027539011 | P23: {=TREND(P16:P22,(VALUE(RIGHT(A16:A22,4))),VALUE(RIGHT(A23,4)))} -> 7768.6822 | Q23: =P23/B23 -> 0.24526955 | R23: =P23-P22 -> 526.27405 | S23: 3
A24: FY 2029 | B24: =B23*(1+C24) -> 33574.503 | C24: 0.06 | E24: =B24*F24 -> 9676.2744 | F24: {=TREND(F17:F23,(VALUE(RIGHT(A17:A23,4))),VALUE(RIGHT(A24,4)))} -> 0.28820306 | G24: =E24-(B24*0.045) -> 8165.4218 | H24: =G24*(1-15.5%) -> 6899.7814 | K24: =H24+(B24*0.045)-(B24*O24)-R24 -> 6716.1351 | O24: {=TREND(O17:O23,(VALUE(RIGHT(A17:A23,4))),VALUE(RIGHT(A24,4)))} -> 0.026563039 | P24: {=TREND(P17:P23,(VALUE(RIGHT(A17:A23,4))),VALUE(RIGHT(A24,4)))} -> 8571.3403 | Q24: =P24/B24 -> 0.25529314 | R24: =P24-P23 -> 802.65806 | S24: 4
A25: FY 2030 | B25: =B24*(1+C25) -> 35253.228 | C25: 0.05 | E25: =B25*F25 -> 10181.798 | F25: {=TREND(F18:F24,(VALUE(RIGHT(A18:A24,4))),VALUE(RIGHT(A25,4)))} -> 0.28881887 | G25: =E25-(B25*0.045) -> 8595.4023 | H25: =G25*(1-15.5%) -> 7263.1149 | K25: =H25+(B25*0.045)-(B25*O25)-R25 -> 7641.888 | O25: {=TREND(O18:O24,(VALUE(RIGHT(A18:A24,4))),VALUE(RIGHT(A25,4)))} -> 0.025986674 | P25: {=TREND(P18:P24,(VALUE(RIGHT(A18:A24,4))),VALUE(RIGHT(A25,4)))} -> 8862.8483 | Q25: =P25/B25 -> 0.2514053 | R25: =P25-P24 -> 291.50806 | S25: 5
A26: FY 2031 | B26: =B25*(1+C26) -> 36310.825 | C26: 0.03 | E26: =B26*F26 -> 10460.417 | F26: {=TREND(F19:F25,(VALUE(RIGHT(A19:A25,4))),VALUE(RIGHT(A26,4)))} -> 0.28807985 | G26: =E26-(B26*0.045) -> 8826.43 | H26: =G26*(1-15.5%) -> 7458.3333 | K26: =H26+(B26*0.045)-(B26*O26)-R26 -> 8144.6285 | O26: {=TREND(O19:O25,(VALUE(RIGHT(A19:A25,4))),VALUE(RIGHT(A26,4)))} -> 0.024202131 | P26: {=TREND(P19:P25,(VALUE(RIGHT(A19:A25,4))),VALUE(RIGHT(A26,4)))} -> 8931.741 | Q26: =P26/B26 -> 0.24598012 | R26: =P26-P25 -> 68.89263 | S26: 6
K27: PVs ($M) | L27: EV ($M) | M27: Personal DCF Valuation
J28: FY 2026 | K28: {=ProjFCFs/(1+'WACC Dashboard'!B16)^t} -> 5910.7939
J29: FY 2027 | K29: 4703.1443
J30: FY 2028 | K30: 4965.903
J31: FY 2029 | K31: 4800.4045
J32: FY 2030 | K32: 5022.254
J33: FY 2031 | K33: 4921.6292 | L33: =SUM(K28:K32)+(K34/(1+'WACC Dashboard'!B16)^5) -> 118366.12
J34: TV ($M) | K34: =K26/('WACC Dashboard'!B16-'DCF Dashboard'!C32) -> 141453.92
K38: FCF ($M) | L38: EV ($M) | N38: Equity ($M) | Q38: TVs ($M) | R38: PV(TVs) ($M) | S38: PV(FCF) ($M)
J39: FY 2026 | K39: 5415.525 | L39: =R39+S39 -> 91461.071 | N39: =L39-'DCF Dashboard'!C3 -> 82267.785 | Q39: =K39/('WACC Dashboard'!B16-'Master Data'!O46) -> 94055.52 | R39: =Q39/(1+'WACC Dashboard'!B16) -> 86481.635 | S39: =K39/(1+'WACC Dashboard'!B16) -> 4979.4361
J40: FY 2027 | K40: =K39*(1+O46) -> 5577.9907 | L40: =R40+S40 -> 94204.903 | N40: =L40-'DCF Dashboard'!C3 -> 85011.617 | Q40: =K40/('WACC Dashboard'!B16-'Master Data'!O46) -> 96877.185 | R40: =Q40/(1+'WACC Dashboard'!B16) -> 89076.084 | S40: =K40/(1+'WACC Dashboard'!B16) -> 5128.8192
K41: Manually Calc'd WACC & 3% Terminal Growth
O42: 0.08
O43: 0.07
O44: 0.06
O45: 0.05
O46: 0.03

Sheet Summary Statistics
A1: Year | B1: Revenue Adj ($M) | C1: YoY Growth % | D1: Gross Margin % | E1: EBITDA Adj ($M) | F1: EBITDA Margin % | G1: EBIT ($M) | H1: Net Income Adj ($M) | I1: Adj EPS | J1: FCF ($M) | K1: EV ($M) | L1: Net Debt ($M) | M1: Equity ($M) | N1: MedSurg % of Rev | O1: Ortho % of Rev | P1: Rule of 40 | R1: Advanced Filter | S1: Year | T1: Revenue Adj ($M) | U1: YoY Growth % | V1: EBITDA Adj ($M) | W1: EBITDA Margin % | X1: Adj EPS | Y1: FCF ($M) | Z1: Net Debt ($M) | AA1: Equity ($M)
A2: FY 2019 | B2: =_xlfn.XLOOKUP("*"&A2&"*",'BBG Adj Highlights'!$C$4:$L$4,'BBG Adj Highlights'!$C$12:$L$12, , 2) -> 14884 | C2: =_xlfn.XLOOKUP("*"&A2&"*",'BBG Adj Highlights'!$C$4:$L$4,'BBG Adj Highlights'!$C$13:$L$13, , 2)/100 -> 0.094331 | D2: =_xlfn.XLOOKUP("*"&RIGHT(A2,4)&"*", SYK!$E$3:$N$3, SYK!$E$27:$N$27,,2)/100 -> 0.659 | E2: =_xlfn.XLOOKUP("*"&A2&"*",'BBG Adj Highlights'!$C$4:$L$4,'BBG Adj Highlights'!$C$16:$L$16,,2) -> 4355 | F2: =_xlfn.XLOOKUP("*"&A2&"*",'BBG Adj Highlights'!$C$4:$L$4,'BBG Adj Highlights'!$C$17:$L$17,,2) /100 -> 0.29259608 | G2: =_xlfn.XLOOKUP("*"&A2&"*",'BBG Adjusted'!$C$4:$L$4,'BBG Adjusted'!$C$65:$L$65,,2) -> 3444 | H2: =_xlfn.XLOOKUP("*"&A2&"*",'BBG Adj Highlights'!$C$4:$L$4,'BBG Adj Highlights'!$C$18:$L$18,,2) -> 2764 | I2: =_xlfn.XLOOKUP("*"&A2&"*",'BBG Adj Highlights'!$C$4:$L$4,'BBG Adj Highlights'!$C$20:$L$20,,2) -> 7.2726 | J2: =_xlfn.XLOOKUP("*"&A2&"*",'BBG Adj Highlights'!$C$4:$L$4,'BBG Adj Highlights'!$C$25:$L$25,,2) -> 1542 | K2: =_xlfn.XLOOKUP("*"&A2&"*",'BBG Adj Highlights'!$C$4:$L$4,'BBG Adj Highlights'!$C$10:$L$10,,2) -> 85690.306 | L2: =_xlfn.XLOOKUP("*"&RIGHT(A2,4)&"*", SYK!$E$3:$N$3, SYK!$E$31:$N$31,,2) -> 6665 | M2: =_xlfn.XLOOKUP("*"&A2&"*",'BBG Adj Highlights'!$C$4:$L$4,'BBG Adj Highlights'!$C$6:$L$6, , 2) -> 78638.306 | N2: =_xlfn.XLOOKUP("*"&A2&"*",Segments!$E$3:$N$3,Segments!$E$7:$N$7,,2)/100 -> 0.44654364 | O2: =1-N2 -> 0.55345636 | P2: =SUM(C2,F2) -> 0.38692708 | S2: FY 2019 | T2: 14884 | U2: 0.094331 | V2: 4355 | W2: 0.29259608 | X2: 7.2726 | Y2: 1542 | Z2: 6665 | AA2: 78638.306
A3: FY 2020 | B3: 14351 | C3: -0.03581 | D3: 0.638 | E3: 3969 | F3: 0.27656609 | G3: 3027 | H3: 2446 | I3: 6.4272 | J3: 2790 | K3: 103585.28 | L3: =_xlfn.XLOOKUP("*"&RIGHT(A3,4)&"*", SYK!$E$3:$N$3, SYK!$E$31:$N$31,,2) -> 10967 | M3: 92184.279 | N3: 0.56940339 | O3: 0.43059661 | P3: =SUM(C3,F3) -> 0.24075609 | S3: FY 2020 | T3: 14351 | U3: -0.03581 | V3: 3969 | W3: 0.27656609 | X3: 6.4272 | Y3: 2790 | Z3: 10967 | AA3: 92184.279
A4: FY 2021 | B4: 17108 | C4: 0.192112 | D4: 0.641 | E4: 4886 | F4: 0.28559738 | G4: 3763 | H4: 2985 | I4: 7.8022 | J4: 2738 | K4: 110845 | L4: =_xlfn.XLOOKUP("*"&RIGHT(A4,4)&"*", SYK!$E$3:$N$3, SYK!$E$31:$N$31,,2) -> 9460 | M4: 100963 | N4: 0.58149258 | O4: 0.41850742 | P4: =SUM(C4,F4) -> 0.47770938 | S4: FY 2021 | T4: 17108 | U4: 0.192112 | V4: 4886 | W4: 0.28559738 | X4: 7.8022 | Y4: 2738 | Z4: 9460 | AA4: 100963
A5: FY 2022 | B5: 18449 | C5: 0.078384 | D5: 0.631 | E5: 4904 | F5: 0.26581387 | G5: 3757 | H5: 3076 | I5: 8.0486 | J5: 2036 | K5: 104218.45 | L5: =_xlfn.XLOOKUP("*"&RIGHT(A5,4)&"*", SYK!$E$3:$N$3, SYK!$E$31:$N$31,,2) -> 11120 | M5: 92620.452 | N5: 0.55751695 | O5: 0.44248305 | P5: =SUM(C5,F5) -> 0.34419787 | S5: FY 2022 | T5: 18449 | U5: 0.078384 | V5: 4904 | W5: 0.26581387 | X5: 8.0486 | Y5: 2036 | Z5: 11120 | AA5: 92620.452
A6: FY 2023 | B6: 20498 | C6: 0.111063 | D6: 0.639 | E6: 5520 | F6: 0.26929457 | G6: 4320 | H6: 3563 | I6: 9.2873 | J6: 3136 | K6: 124314.87 | L6: =_xlfn.XLOOKUP("*"&RIGHT(A6,4)&"*", SYK!$E$3:$N$3, SYK!$E$31:$N$31,,2) -> 9942 | M6: 113873.87 | N6: 0.59043851 | O6: 0.40956149 | P6: =SUM(C6,F6) -> 0.38035757 | S6: FY 2023 | T6: 20498 | U6: 0.111063 | V6: 5520 | W6: 0.26929457 | X6: 9.2873 | Y6: 3136 | Z6: 9942 | AA6: 113873.87
A7: FY 2024 | B7: 22595 | C7: 0.102303 | D7: 0.64461164 | E7: 6332 | F7: 0.28023899 | G7: 5092 | H7: 4205 | I7: 10.9032 | J7: 3487 | K7: 146950.07 | L7: =_xlfn.XLOOKUP("*"&RIGHT(A7,4)&"*", SYK!$E$3:$N$3, SYK!$E$31:$N$31,,2) -> 9104 | M7: 137323.07 | N7: 0.59337496 | O7: 0.40662504 | P7: =SUM(C7,F7) -> 0.38254199 | S7: FY 2024 | T7: 22595 | U7: 0.102303 | V7: 6332 | W7: 0.28023899 | X7: 10.9032 | Y7: 3487 | Z7: 9104 | AA7: 137323.07
A8: FY 2025 | B8: 25116 | C8: 0.111573 | D8: 0.653 | E8: 7269 | F8: 0.2894171 | G8: 5871 | H8: 4686 | I8: 12.1257 | J8: 4283 | K8: 146697.27 | L8: =_xlfn.XLOOKUP("*"&RIGHT(A8,4)&"*", SYK!$E$3:$N$3, SYK!$E$31:$N$31,,2) -> 11759 | M8: 134437.27 | N8: 0.59827395 | O8: 0.40172605 | P8: =SUM(C8,F8) -> 0.4009901 | S8: FY 2025 | T8: 25116 | U8: 0.111573 | V8: 7269 | W8: 0.2894171 | X8: 12.1257 | Y8: 4283 | Z8: 11759 | AA8: 134437.27
A9: FY 2026 | B9: =_xlfn.XLOOKUP("*"&A9&"*",'BBG Adj Highlights'!$C$4:$L$4,'BBG Adj Highlights'!$C$12:$L$12, , 2) -> 27317.214 | C9: =_xlfn.XLOOKUP("*"&A9&"*",'BBG Adj Highlights'!$C$4:$L$4,'BBG Adj Highlights'!$C$13:$L$13, , 2)/100 -> 0.087641913 | D9: =_xlfn.XLOOKUP("*"&RIGHT(A9,4)&"*", SYK!$E$3:$N$3, SYK!$E$27:$N$27,,2)/100 -> 0.65211765 | E9: =_xlfn.XLOOKUP("*"&A9&"*",'BBG Adj Highlights'!$C$4:$L$4,'BBG Adj Highlights'!$C$16:$L$16,,2) -> 7838.9167 | F9: =_xlfn.XLOOKUP("*"&A9&"*",'BBG Adj Highlights'!$C$4:$L$4,'BBG Adj Highlights'!$C$17:$L$17,,2) /100 -> 0.28695886 | G9: =_xlfn.XLOOKUP("*"&A9&"*",'BBG Adjusted'!$C$4:$L$4,'BBG Adjusted'!$C$65:$L$65,,2) -> 7296.6923 | H9: =_xlfn.XLOOKUP("*"&A9&"*",'BBG Adj Highlights'!$C$4:$L$4,'BBG Adj Highlights'!$C$18:$L$18,,2) -> 5814.833 | I9: =_xlfn.XLOOKUP("*"&A9&"*",'BBG Adj Highlights'!$C$4:$L$4,'BBG Adj Highlights'!$C$20:$L$20,,2) -> 15.013 | J9: =_xlfn.XLOOKUP("*"&A9&"*",'BBG Adj Highlights'!$C$4:$L$4,'BBG Adj Highlights'!$C$25:$L$25,,2) -> 5415.525 | K9: =_xlfn.XLOOKUP("*"&A9&"*",'BBG Adj Highlights'!$C$4:$L$4,'BBG Adj Highlights'!$C$10:$L$10,,2) -> 0 | L9: =_xlfn.XLOOKUP("*"&RIGHT(A9,4)&"*", SYK!$E$3:$N$3, SYK!$E$31:$N$31,,2) -> 9193.2857 | M9: =_xlfn.XLOOKUP("*"&A9&"*",'BBG Adj Highlights'!$C$4:$L$4,'BBG Adj Highlights'!$C$6:$L$6, , 2) -> 0 | N9: =IFERROR(_xlfn.XLOOKUP("*"&A9&"*",Segments!$E$3:$N$3,Segments!$E$7:$N$7,,2)/100,0) -> 0 | O9: =IFERROR(_xlfn.XLOOKUP("*"&A9&"*",Segments!$E$3:$N$3,Segments!$E$21:$N$21,,2)/100,0) -> 0 | P9: =SUM(C9,F9) -> 0.37460077 | S9: FY 2026 | T9: 27317.214 | U9: 0.087641913 | V9: 7838.9167 | W9: 0.28695886 | X9: 15.013 | Y9: 5415.525 | Z9: 9193.2857 | AA9: 0
A10: FY 2027 | B10: =_xlfn.XLOOKUP("*"&A10&"*",'BBG Adj Highlights'!$C$4:$L$4,'BBG Adj Highlights'!$C$12:$L$12, , 2) -> 29602.893 | C10: =_xlfn.XLOOKUP("*"&A10&"*",'BBG Adj Highlights'!$C$4:$L$4,'BBG Adj Highlights'!$C$13:$L$13, , 2)/100 -> 0.08367173 | D10: =_xlfn.XLOOKUP("*"&RIGHT(A10,4)&"*", SYK!$E$3:$N$3, SYK!$E$27:$N$27,,2)/100 -> 0.6546326 | E10: =_xlfn.XLOOKUP("*"&A10&"*",'BBG Adj Highlights'!$C$4:$L$4,'BBG Adj Highlights'!$C$16:$L$16,,2) -> 8626.3478 | F10: =_xlfn.XLOOKUP("*"&A10&"*",'BBG Adj Highlights'!$C$4:$L$4,'BBG Adj Highlights'!$C$17:$L$17,,2) /100 -> 0.29140219 | G10: =_xlfn.XLOOKUP("*"&A10&"*",'BBG Adjusted'!$C$4:$L$4,'BBG Adjusted'!$C$65:$L$65,,2) -> 8076.7692 | H10: =_xlfn.XLOOKUP("*"&A10&"*",'BBG Adj Highlights'!$C$4:$L$4,'BBG Adj Highlights'!$C$18:$L$18,,2) -> 6484.64 | I10: =_xlfn.XLOOKUP("*"&A10&"*",'BBG Adj Highlights'!$C$4:$L$4,'BBG Adj Highlights'!$C$20:$L$20,,2) -> 16.746 | J10: =_xlfn.XLOOKUP("*"&A10&"*",'BBG Adj Highlights'!$C$4:$L$4,'BBG Adj Highlights'!$C$25:$L$25,,2) -> 5637.65 | K10: =_xlfn.XLOOKUP("*"&A10&"*",'BBG Adj Highlights'!$C$4:$L$4,'BBG Adj Highlights'!$C$10:$L$10,,2) -> 0 | L10: =_xlfn.XLOOKUP("*"&RIGHT(A10,4)&"*", SYK!$E$3:$N$3, SYK!$E$31:$N$31,,2) -> 5874.5714 | M10: =_xlfn.XLOOKUP("*"&A10&"*",'BBG Adj Highlights'!$C$4:$L$4,'BBG Adj Highlights'!$C$6:$L$6, , 2) -> 0 | N10: =IFERROR(_xlfn.XLOOKUP("*"&A10&"*",Segments!$E$3:$N$3,Segments!$E$7:$N$7,,2)/100,0) -> 0 | O10: =IFERROR(_xlfn.XLOOKUP("*"&A10&"*",Segments!$E$3:$N$3,Segments!$E$21:$N$21,,2)/100,0) -> 0 | P10: =SUM(C10,F10) -> 0.37507392 | S10: FY 2027 | T10: 29602.893 | U10: 0.08367173 | V10: 8626.3478 | W10: 0.29140219 | X10: 16.746 | Y10: 5637.65 | Z10: 5874.5714 | AA10: 0
B12: Minimum | R12: Database Function | T12: Revenue Adj ($M) | U12: YoY Growth %
B13: =MIN(B2:B10) -> 14351 | C13: =MIN(C2:C10) -> -0.03581 | D13: =MIN(D2:D10) -> 0.631 | E13: =MIN(E2:E10) -> 3969 | F13: =MIN(F2:F10) -> 0.26581387 | G13: =MIN(G2:G10) -> 3027 | H13: =MIN(H2:H10) -> 2446 | I13: =MIN(I2:I10) -> 6.4272 | ... M13: =MIN(M2:M10) -> 0 | O13: =MIN(O2:O10) -> 0 | P13: =MIN(P2:P10) -> 0.24075609 | T13: >20000 | U13: <10%
B15: Maximum | S15: DAVERAGE EPS for Criteria Above: | T15: =DAVERAGE(Table1[#All],9,T12:U13) -> 15.8795
B16: =MAX(B2:B10) -> 29602.893 | C16: =MAX(C2:C10) -> 0.192112 | D16: =MAX(D2:D10) -> 0.659 | E16: =MAX(E2:E10) -> 8626.3478 | F16: =MAX(F2:F10) -> 0.29259608 | G16: =MAX(G2:G10) -> 8076.7692 | H16: =MAX(H2:H10) -> 6484.64 | I16: =MAX(I2:I10) -> 16.746 | ... M16: =MAX(M2:M10) -> 137323.07 | O16: =MAX(O2:O10) -> 0.55345636 | P16: =MAX(P2:P10) -> 0.47770938 | S16: DCOUNT | T16: =DCOUNTA(Table1[#All],9,T12:U13) -> 2
S17: DMAX | T17: =DMAX(Table1[#All],9,T12:U13) -> 16.746
B18: Average | S18: DMIN | T18: =DMIN(Table1[#All],9,T13:U14) -> 6.4272
B19: =AVERAGE(B2:B10) -> 21102.345 | C19: =AVERAGE(C2:C10) -> 0.091696627 | D19: =AVERAGE(D2:D10) -> 0.64581799 | E19: =AVERAGE(E2:E10) -> 5966.6961 | F19: =AVERAGE(F2:F10) -> 0.28198724 | G19: =AVERAGE(G2:G10) -> 4960.8291 | H19: =AVERAGE(H2:H10) -> 4002.7192 | I19: =AVERAGE(I2:I10) -> 10.402867 | ... M19: =AVERAGE(M2:M10) -> 83337.806 | O19: =AVERAGE(O2:O10) -> 0.34032845 | P19: =AVERAGE(P2:P10) -> 0.37368386 | S19: DSUM | T19: =DSUM(Table1[#All],9,T12:U13) -> 31.759
B21: Median | S21: SUMIFS EPS >20000 | T21: =SUMIFS(Table1[Adj EPS],Table1[Revenue Adj ($M)],">20000") -> 64.0752
B22: =MEDIAN(B2:B10) -> 20498 | C22: =MEDIAN(C2:C10) -> 0.094331 | D22: =MEDIAN(D2:D10) -> 0.64461164 | E22: =MEDIAN(E2:E10) -> 5520 | F22: =MEDIAN(F2:F10) -> 0.28559738 | G22: =MEDIAN(G2:G10) -> 4320 | H22: =MEDIAN(H2:H10) -> 3563 | I22: =MEDIAN(I2:I10) -> 9.2873 | ... M22: =MEDIAN(M2:M10) -> 92620.452 | O22: =MEDIAN(O2:O10) -> 0.40956149 | P22: =MEDIAN(P2:P10) -> 0.38035757 | S22: COUNTIFS | T22: =COUNTIFS(Table1[[#All],[Revenue Adj ($M)]], ">20000") -> 5
S23: AVERAGEIFS | T23: =AVERAGEIFS(Table1[Adj EPS],Table1[Revenue Adj ($M)],">20000") -> 12.81504
B24: Standard Deviation
B25: =_xlfn.STDEV.P(B2:B10) -> 5129.7617 | C25: =_xlfn.STDEV.P(C2:C10) -> 0.055265837 | D25: =_xlfn.STDEV.P(D2:D10) -> 0.008784942 | E25: =_xlfn.STDEV.P(E2:E10) -> 1545.3701 | F25: =_xlfn.STDEV.P(F2:F10) -> 0.0091242593 | G25: =_xlfn.STDEV.P(G2:G10) -> 1678.1631 | H25: =_xlfn.STDEV.P(H2:H10) -> 1333.2163 | I25: =_xlfn.STDEV.P(I2:I10) -> 3.3970932 | ... M25: =_xlfn.STDEV.P(M2:M10) -> 48126.634 | O25: =_xlfn.STDEV.P(O2:O10) -> 0.18700101 | P25: =_xlfn.STDEV.P(P2:P10) -> 0.058125645
B27: Year Count
B28: =SUBTOTAL(3,A2:A10) -> 9
B30: Rank (1st Cell) | C30: Percent Rank (1st Cell) | D30: Quartile (1st Cell) | E30: Frequency | F30: Correl (EBITDA:Gross Margin) | H30: NPVSolver (Set $27,317.21 to $20,498): | J30: =NPV(K30,B9) -> 20498 | K30: 0.33267706
B31: =_xlfn.RANK.AVG(B2,B2:B10,0) -> 8 | C31: =_xlfn.PERCENTRANK.EXC(C2:C10,C2) -> 0.5 | D31: =_xlfn.QUARTILE.EXC(D2:D10,1) -> 0.6385 | E31: {=FREQUENCY(E5:E10,J5:J10)} -> 0 | F31: =CORREL(F2:F7,D2:D7) -> 0.87458374
E32: 0
E33: 0
E34: 0
E35: 1
E36: 1
E37: 4

Sheet WACC Dashboard
A1: (in millions) | B1: SYK | C1: JNJ | D1: ABT | E1: BSX | F1: EW
A2: Equity Value | B2: 134437.3 | C2: 499960.4 | D2: 217578.5 | E2: 141404.1 | F2: 49504.7
A3: Preferred Equity Value | B3: 0 | C3: 0 | D3: 0 | E3: 0 | F3: 0
A4: Short-Term Debt Value | B4: 1153 | C4: 8495 | D4: 3309 | E4: 389 | F4: 24.5
A5: Long-Term Debt Value | B5: 15207 | C5: 40838 | D5: 10827 | E5: 11583 | F5: 680.9
A6: Total Capital | B6: 150797.3 | C6: 549293.4 | D6: 231714.5 | E6: 153376.1 | F6: 50210.1 | H6: % Equity | I6: {=INDEX(B7:F7,$J$9)} -> 0.892
A7: % Equity | B7: 0.892 | C7: 0.91 | D7: 0.939 | E7: 0.922 | F7: 0.986 | H7: %Preferred Equity | I7: {=INDEX(B8:F8,$J$9)} -> 0
A8: %Preferred Equity | B8: 0 | C8: 0 | D8: 0 | E8: 0 | F8: 0 | H8: % Short-Term Debt | I8: {=INDEX(B9:F9,$J$9)} -> 0.008
A9: % Short-Term Debt | B9: 0.008 | C9: 0.015 | D9: 0.014 | E9: 0.003 | F9: 0.0001 | H9: % Long-Term Debt | I9: {=INDEX(B10:F10,$J$9)} -> 0.101 | J9: 1
A10: % Long-Term Debt | B10: 0.101 | C10: 0.074 | D10: 0.047 | E10: 0.076 | F10: 0.014
A11: Beta | B11: =_xlfn.XLOOKUP(B1,'Beta Hand Calculations'!$A67:$A72,'Beta Hand Calculations'!$B67:$B72) -> 0.92827565 | C11: =_xlfn.XLOOKUP(C1,'Beta Hand Calculations'!$A67:$A72,'Beta Hand Calculations'!$B67:$B72) -> 0.32763773 | D11: =_xlfn.XLOOKUP(D1,'Beta Hand Calculations'!$A67:$A72,'Beta Hand Calculations'!$B67:$B72) -> 0.77017981 | E11: =_xlfn.XLOOKUP(E1,'Beta Hand Calculations'!$A67:$A72,'Beta Hand Calculations'!$B67:$B72) -> 0.78314866 | F11: =_xlfn.XLOOKUP(F1,'Beta Hand Calculations'!$A67:$A72,'Beta Hand Calculations'!$B67:$B72) -> 0.93461731
A12: Expected Return of Market | B12: =C13+B18 -> 0.09817
A13: Risk Free Rate | B13: {=(_xlfn.STOCKHISTORY("^TNX",TODAY(),TODAY(),2,0,1)) / 1000} -> 0.04392 | C13: 0.04317
A14: 2026 Tax Rate (%) | B14: 0.155 | C14: 0.18 | D14: 0.1626 | E14: =(BSX!M130/BSX!M123) -> 0.11678751 | F14: 0.1723
A15: Pre-Tax Cost of Debt | B15: 0.039 | C15: 0.042 | D15: 0.041 | E15: 0.048 | F15: 0.045
A16: WACC | B16: =((B2/B6)*($C$13+(B11*$B$18)))+(((B4+B5)/B6)*B15)*(1-B14) -> 0.087577961 | C16: =((C2/C6)*($C$13+(C11*$B$18)))+(((C4+C5)/C6)*C15)*(1-C14) -> 0.058787604 | D16: =((D2/D6)*($C$13+(D11*$B$18)))+(((D4+D5)/D6)*D15)*(1-D14) -> 0.082406591 | E16: =((E2/E6)*($C$13+(E11*$B$18)))+(((E4+E5)/E6)*E15)*(1-E14) -> 0.082820479 | F16: =((F2/F6)*($C$13+(F11*$B$18)))+(((F4+F5)/F6)*F15)*(1-F14) -> 0.093768561
G17: Data compiled as of March 23rd, 2026
A18: Assumed Equity Risk Premium | B18: 0.055

Sheet WACC PivotTable
A3: Row Labels | B3: Average of SYK | C3: Average of JNJ | D3: Average of ABT | E3: Average of BSX | F3: Average of EW
A4: 44197 | B4: 221.01 | C4: 163.13 | D4: 123.59 | E4: 35.44 | F4: 82.58
A5: 44228 | B5: 242.69 | C5: 158.46 | D5: 119.78 | E5: 38.78 | F5: 83.1
A6: 44256 | B6: 243.58 | C6: 164.35 | D6: 119.84 | E6: 38.65 | F6: 83.64
A7: 44287 | B7: 262.63 | C7: 162.73 | D7: 120.08 | E7: 43.6 | F7: 95.52
A8: 44317 | B8: 255.27 | C8: 169.25 | D8: 116.65 | E8: 42.55 | F8: 95.9
A9: 44348 | B9: 259.73 | C9: 164.74 | D9: 115.93 | E9: 42.76 | F9: 103.57
A10: 44378 | B10: 270.94 | C10: 172.2 | D10: 120.98 | E10: 45.6 | F10: 112.27
A11: 44409 | B11: 277.1 | C11: 173.13 | D11: 126.37 | E11: 45.15 | F11: 117.18
A12: 44440 | B12: 263.72 | C12: 161.5 | D12: 118.13 | E12: 43.39 | F12: 113.21
A13: 44470 | B13: 266.07 | C13: 162.88 | D13: 128.89 | E13: 43.13 | F13: 119.82
A14: 44501 | B14: 236.63 | C14: 155.93 | D14: 125.77 | E14: 38.07 | F14: 107.31
A15: 44531 | B15: 267.42 | C15: 171.07 | D15: 140.74 | E15: 42.48 | F15: 129.55
... A66: 46082 | B66: 328.59 | C66: 244.44 | D66: 102.67 | E66: 62.75 | F66: 80.08

Sheet Beta Hand Calculations
A1: Dates (60 Months) | B1: SYK | C1: SYK Returns | D1: JNJ | E1: JNJ Returns | F1: ABT | G1: ABT Returns | H1: BSX | I1: BSX Returns | J1: EW | K1: EW Returns | L1: S&P 500 | M1: S&P Returns
A2: 44197 | B2: {=_xlfn.STOCKHISTORY(B$1,$A$2,$A$64,2,0,1)} -> 221.01 | C2: =B3/B2-1 -> 0.098095109 | D2: {=_xlfn.STOCKHISTORY(D$1,$A$2,$A$64,2,0,1)} -> 163.13 | E2: =D3/D2-1 -> -0.028627475 | F2: {=_xlfn.STOCKHISTORY(F$1,$A$2,$A$64,2,0,1)} -> 123.59 | G2: =F3/F2-1 -> -0.030827737 | H2: {=_xlfn.STOCKHISTORY(H$1,$A$2,$A$64,2,0,1)} -> 35.44 | I2: =H3/H2-1 -> 0.094243792 | J2: {=_xlfn.STOCKHISTORY(J$1,$A$2,$A$64,2,0,1)} -> 82.58 | K2: =J3/J2-1 -> 0.0062969242 | L2: 3714.24 | M2: =L3/L2-1 -> 0.026091475
A3: 44228 | B3: 242.69 | C3: =B4/B3-1 -> 0.0036672298 | D3: 158.46 | E3: =D4/D3-1 -> 0.037170264 | F3: 119.78 | G3: =F4/F3-1 -> 0.00050091835 | H3: 38.78 | I3: =H4/H3-1 -> -0.0033522434 | J3: 83.1 | K3: =J4/J3-1 -> 0.0064981949 | L3: 3811.15 | M3: =L4/L3-1 -> 0.042438634
A4: 44256 | B4: 243.58 | C4: =B5/B4-1 -> 0.078208391 | D4: 164.35 | E4: =D5/D4-1 -> -0.0098570125 | F4: 119.84 | G4: =F5/F4-1 -> 0.0020026702 | H4: 38.65 | I4: =H5/H4-1 -> 0.12807245 | J4: 83.64 | K4: =J5/J4-1 -> 0.1420373 | L4: 3972.89 | M4: =L5/L4-1 -> 0.052425313
A5: 44287 | B5: 262.63 | C5: =B6/B5-1 -> -0.028024217 | D5: 162.73 | E5: =D6/D5-1 -> 0.040066368 | F5: 120.08 | G5: =F6/F5-1 -> -0.02856429 | H5: 43.6 | I5: =H6/H5-1 -> -0.024082569 | J5: 95.52 | K5: =J6/J5-1 -> 0.0039782245 | L5: 4181.17 | M5: =L6/L5-1 -> 0.0054865026
A6: 44317 | B6: 255.27 | C6: =B7/B6-1 -> 0.017471697 | D6: 169.25 | E6: =D7/D6-1 -> -0.026646972 | F6: 116.65 | G6: =F7/F6-1 -> -0.0061723103 | H6: 42.55 | I6: =H7/H6-1 -> 0.0049353702 | J6: 95.9 | K6: =J7/J6-1 -> 0.079979145 | L6: 4204.11 | M6: =L7/L6-1 -> 0.022213976
A7: 44348 | B7: 259.73 | C7: =B8/B7-1 -> 0.043160205 | D7: 164.74 | E7: =D8/D7-1 -> 0.045283477 | F7: 115.93 | G7: =F8/F7-1 -> 0.043560769 | H7: 42.76 | I7: =H8/H7-1 -> 0.066417212 | J7: 103.57 | K7: =J8/J7-1 -> 0.084001159 | L7: 4297.5 | M7: =L8/L7-1 -> 0.022748109
A8: 44378 | B8: 270.94 | C8: =B9/B8-1 -> 0.022735661 | D8: 172.2 | E8: =D9/D8-1 -> 0.0054006969 | F8: 120.98 | G8: =F9/F8-1 -> 0.044552819 | H8: 45.6 | I8: =H9/H8-1 -> -0.0098684211 | J8: 112.27 | K8: =J9/J8-1 -> 0.043733856 | L8: 4395.26 | M8: =L9/L8-1 -> 0.028990321
A9: 44409 | B9: 277.1 | C9: =B10/B9-1 -> -0.048285817 | D9: 173.13 | E9: =D10/D9-1 -> -0.067174955 | F9: 126.37 | G9: =F10/F9-1 -> -0.065205349 | H9: 45.15 | I9: =H10/H9-1 -> -0.038981174 | J9: 117.18 | K9: =J10/J9-1 -> -0.033879502 | L9: 4522.68 | M9: =L10/L9-1 -> -0.04756914
A10: 44440 | B10: 263.72 | C10: =B11/B10-1 -> 0.0089109662 | D10: 161.5 | E10: =D11/D10-1 -> 0.0085448916 | F10: 118.13 | G10: =F11/F10-1 -> 0.091086092 | H10: 43.39 | I10: =H11/H10-1 -> -0.0059921641 | J10: 113.21 | K10: =J11/J10-1 -> 0.058387068 | L10: 4307.54 | M10: =L11/L10-1 -> 0.069143873
A11: 44470 | B11: 266.07 | C11: =B12/B11-1 -> -0.11064757 | D11: 162.88 | E11: =D12/D11-1 -> -0.04266945 | F11: 128.89 | G11: =F12/F11-1 -> -0.024206688 | H11: 43.13 | I11: =H12/H11-1 -> -0.11731973 | J11: 119.82 | K11: =J12/J11-1 -> -0.10440661 | L11: 4605.38 | M11: =L12/L11-1 -> -0.0083337314
A12: 44501 | B12: 236.63 | C12: =B13/B12-1 -> 0.13011875 | D12: 155.93 | E12: =D13/D12-1 -> 0.09709485 | F12: 125.77 | G12: =F13/F12-1 -> 0.11902679 | H12: 38.07 | I12: =H13/H12-1 -> 0.11583924 | J12: 107.31 | K12: =J13/J12-1 -> 0.20725002 | L12: 4567 | M12: =L13/L12-1 -> 0.043612875
A13: 44531 | B13: 267.42 | C13: =B14/B13-1 -> -0.072432877 | D13: 171.07 | E13: =D14/D13-1 -> 0.0071315836 | F13: 140.74 | G13: =F14/F13-1 -> -0.094358391 | H13: 42.48 | I13: =H14/H13-1 -> 0.0098870056 | J13: 129.55 | K13: =J14/J13-1 -> -0.15708221 | L13: 4766.18 | M13: =L14/L13-1 -> -0.052585089
A14: 44562 | B14: 248.05 | C14: =B15/B14-1 -> 0.061681113 | D14: 172.29 | E14: =D15/D14-1 -> -0.044808172 | F14: 127.46 | G14: =F15/F14-1 -> -0.053663895 | H14: 42.9 | I14: =H15/H14-1 -> 0.02960373 | J14: 109.2 | K14: =J15/J14-1 -> 0.029029304 | L14: 4515.55 | M14: =L15/L14-1 -> -0.031360521
... A63: 46054 | B63: 387.46 | C63: =B64/B63-1 -> -0.15193826 | D63: 248.43 | E63: =D64/D63-1 -> -0.016060862 | F63: 116.35 | G63: =F64/F63-1 -> -0.11757628 | H63: 76.85 | I63: =H64/H63-1 -> -0.1834743 | J63: 86.47 | K63: =J64/J63-1 -> -0.073898462 | L63: 6878.88 | M63: =L64/L63-1 -> -0.05413672
A64: 46082 | B64: 328.59 | D64: 244.44 | F64: 102.67 | H64: 62.75 | J64: 80.08 | L64: 6506.48
B66: Beta Vals: | L66: I have to paste S&P values since some European stock keeps populating.
A67: =B1 -> SYK | B67: =SLOPE(C2:C63,$M$2:$M$63) -> 0.92827565
A68: =D1 -> JNJ | B68: =SLOPE(E2:E63,$M$2:$M$63) -> 0.32763773
A69: =F1 -> ABT | B69: =SLOPE(G2:G63,$M$2:$M$63) -> 0.77017981
A70: =H1 -> BSX | B70: =SLOPE(I2:I63,$M$2:$M$63) -> 0.78314866
A71: =J1 -> EW | B71: =SLOPE(K2:K63,$M$2:$M$63) -> 0.93461731
A72: =L1 -> S&P 500 | B72: =SLOPE(M2:M63,$M$2:$M$63) -> 1

Sheet SYK
A1: SYK US Equity- Company Financial (Multiple Periods)
A2: SYK US Equity Periodicity:A Currency:USD Estimate Source:BST Actual Source:Bloomberg
A3: In Millions of USD | E3: 2018 A (Rep) | F3: 2019 A (Rep) | G3: 2020 A (Rep) | H3: 2021 A (Rep) | I3: 2022 A (Rep) | J3: 2023 A (Rep) | K3: 2024 A (Rep) | L3: 2025 A (Rep) | M3: 2026 A (Fwd) | N3: 2027 A (Fwd)
A4: 12 Months Ending | B4: Field Expression | C4: Calcrt Field | D4: Segment Id | E4: 43465 | F4: 43830 | G4: 44196 | H4: 44561 | I4: 44926 | J4: 45291 | K4: 45657 | L4: 46022 | M4: 46387 | N4: 46752
A5: Highlights
A6: Adjusted Diluted EPS | B6: IS_COMP_EPS_ADJUSTED_OLD | C6: IS900 | E6: 7.31 | F6: 8.26 | G6: 7.43 | H6: 9.09 | I6: 9.34 | J6: 10.6 | K6: 12.19 | L6: 13.63 | M6: 15.012333 | N6: 16.776429
A7: Revenue | B7: IS_COMP_SALES | C7: IS902 | E7: 13601 | F7: 14884 | G7: 14351 | H7: 17108 | I7: 18449 | J7: 20498 | K7: 22595 | L7: 25116 | M7: 27330.321 | N7: 29617.036
A8: Organic Growth (%) | B8: IS_ORGANIC_GROWTH_RATE | C8: IS950 | E8: 7.9 | F8: 8.1 | G8: -4.8 | H8: 12.6 | I8: 9.7 | J8: 11.5 | K8: 10.2 | L8: 10.3 | M8: 8.7066022 | N8: 8.2261575
A10: Orthopaedics
A11: Revenue | B11: SALES_REV_TURN | C11: IS010 | D11: SEG0000608032 Segment | F11: 6409 | G11: 6006 | H11: 7570 | I11: 7556 | J11: 8335 | K11: 9077 | L11: 9469 | M11: 10036.826 | N11: 10760.019
A12: Organic Growth (%) | B12: IS_ORGANIC_GROWTH_RATE | C12: IS950 | D12: SEG0000608032 Segment | H12: 12 | I12: 7 | J12: 11.1 | K12: 8.7 | L12: 9.5 | M12: 7.631669 | N12: 7.5633887
A13: Knees | B13: SALES_REV_TURN | C13: IS010 | D13: SEG0000173641 Segment | E13: 1701 | F13: 1815 | G13: 1567 | H13: 1848 | I13: 1997 | J13: 2273 | K13: 2447 | L13: 2656 | M13: 2840.8475 | N13: 3021.1802
A14: Hips | B14: SALES_REV_TURN | C14: IS010 | D14: SEG0000173657 Segment | E14: 1336 | F14: 1383 | G14: 1206 | H14: 1342 | I14: 1413 | J14: 1544 | K14: 1704 | L14: 1865 | M14: 1989.1261 | N14: 2109.3862
A15: Trauma & Extremities | B15: SALES_REV_TURN | C15: IS010 | D15: SEG0000173644 Segment | E15: 1580 | F15: 1639 | G15: 1722 | H15: 2664 | I15: 2807 | J15: 3147 | K15: 3507 | L15: 3948 | M15: 4317.0977 | N15: 4670.8913
A16: Spinal Implants | B16: SALES_REV_TURN | C16: IS010 | D16: SEG4388955483 Segment | I16: 733 | J16: 713 | K16: 707 | L16: 185 | M16: 24
A17: Other | B17: SALES_REV_TURN | C17: IS010 | D17: SEG0000608256 Segment | E17: 374 | F17: 415 | G17: 464 | H17: 549 | I17: 606 | J17: 658 | K17: 712 | L17: 815 | M17: 872.60132 | N17: 937.5209
A18: MedSurg & Neurotechnology
A19: Revenue | B19: SALES_REV_TURN | C19: IS010 | D19: SEG0000608020 Segment | F19: 8475 | G19: 8345 | H19: 9538 | I19: 10893 | J19: 12163 | K19: 13518 | L19: 15647 | M19: 17280.12 | N19: 18817.612
A20: Organic Growth (%) | B20: IS_ORGANIC_GROWTH_RATE | C20: IS950 | D20: SEG0000608020 Segment | H20: 13.1 | I20: 11.8 | J20: 11.8 | K20: 11.2 | L20: 10.7 | M20: 8.902267 | N20: 9.1432523
A21: Instruments | B21: SALES_REV_TURN | C21: IS010 | D21: SEG0000173634 Segment | E21: 1822 | F21: 1959 | G21: 1863 | H21: 2111 | I21: 2245 | J21: 2534 | K21: 2834 | L21: 3183 | M21: 3496.053 | N21: 3793.1494
A22: Endoscopy | B22: SALES_REV_TURN | C22: IS010 | D22: SEG0000173697 Segment | E22: 1846 | F22: 1983 | G22: 1763 | H22: 2141 | I22: 2759 | J22: 3068 | K22: 3389 | L22: 3807 | M22: 4150.364 | N22: 4500.9321
A23: Medical | B23: SALES_REV_TURN | C23: IS010 | D23: SEG0000173720 Segment | E23: 2118 | F23: 2264 | G23: 2524 | H23: 2607 | I23: 3031 | J23: 3459 | K23: 3852 | L23: 4204 | M23: 4604.4725 | N23: 5005.0768
A24: Vascular | B24: SALES_REV_TURN | C24: IS010 | D24: SEG0000608022 Segment | F24: 924 | G24: 973 | H24: 1188 | I24: 1200 | J24: 1226 | K24: 1307 | L24: 1968 | M24: 2273.4045 | N24: 2502.0556
A25: Neuro Cranial | B25: SALES_REV_TURN | C25: IS010 | D25: SEG0000608023 Segment | F25: 1059 | G25: 972 | H25: 1214 | I25: 1658 | J25: 1876 | K25: 2136 | L25: 2485 | M25: 2762.5909 | N25: 3027.7051
A27: Adjusted Gross Margin (%) | B27: IS_COMP_GROSS_MARGIN_PERCENTAGE | C27: IM092 | E27: 66 | F27: 65.9 | G27: 63.8 | H27: 64.1 | I27: 63.1 | J27: 63.9 | K27: 64.461164 | L27: 65.3 | M27: 65.211765 | N27: 65.46326
A28: Adjusted Operating Margin (%) | B28: CB_IS_ADJ_OPERATING_MARGIN | C28: IM731 | E28: 25.9 | F28: 26.3 | G28: 24.4 | H28: 25.6 | I28: 23.8 | J28: 24.2 | K28: 25.3 | L28: 26.3 | M28: 26.520948 | N28: 27.099139
A29: Adjusted Net Income | B29: IS_COMP_NET_INCOME_ADJUST_OLD | C29: IS903 | E29: 2779 | F29: 3139 | G29: 2827 | H29: 3474 | I29: 3571 | J29: 4066 | K29: 4700 | L29: 5267 | M29: 5813.64 | N29: 6498.84
A31: Net Debt | B31: HEADLINE_NET_DEBT | C31: F1708 | E31: 6160 | F31: 6665 | G31: 10967 | H31: 9460 | I31: 11120 | J31: 9942 | K31: 9104 | L31: 11759 | M31: 9193.2857 | N31: 5874.5714
A32: Free Cash Flow | B32: CF_FREE_CASH_FLOW | C32: RR008 | E32: 2038 | F32: 1542 | G32: 2790 | H32: 2738 | I32: 2036 | J32: 3136 | K32: 3487 | L32: 4283 | M32: 5415.5254 | N32: 5637.6501
A34: Company Operating Metrics
A36: Company-Level Industry Statistics
A37: Sales Change - Acquisitions (%) | B37: IS_PCT_SALES_CHANGE_ACQUIS | C37: IM764 | E37: 1.9 | F37: 2.6 | G37: 1.2 | H37: 5.5 | I37: 1.3 | J37: 0.1 | K37: 0.5 | L37: 0.4 | M37: -0.16498594 | N37: 0
A39: Balance Sheet & Cash Flow Metrics
A40: Cash Conversion Cycle | B40: CASH_CONVERSION_CYCLE | C40: RR798 | E40: 232.78489 | F40: 226.59734 | G40: 248.33295 | H40: 204.03155 | I40: 197.86375 | J40: 217.53561 | K40: 206.26117 | L40: 195.44023
A41: Days Sales Outstanding | B41: ACCT_RCV_DAYS | C41: RR159 | E41: 60.784134 | F41: 64.066279 | G41: 71.333148 | H41: 61.05024 | I41: 65.159494 | J41: 65.261245 | K41: 62.78451 | L41: 58.319199 | N41: 62.381673
A43: Business Breakdown
A44: Orthopaedics
A45: Revenue | B45: SALES_REV_TURN | C45: IS010 | D45: SEG0000608032 Segment | F45: 6409 | G45: 6006 | H45: 7570 | I45: 7556 | J45: 8335 | K45: 9077 | L45: 9469 | M45: 10036.826 | N45: 10760.019
A46: Constant Currency Growth (%) | B46: REVENUE_GROWTH_CC_1_YR | C46: M0025 | D46: SEG0000608032 Segment | G46: -6.4 | H46: 24.8 | I46: 7 | J46: 10.9 | K46: 9.4 | L46: 3.8 | M46: 6.2311649 | N46: 7.6879715
A47: Organic Growth (%) | B47: IS_ORGANIC_GROWTH_RATE | C47: IS950 | D47: SEG0000608032 Segment | H47: 12 | I47: 7 | J47: 11.1 | K47: 8.7 | L47: 9.5 | M47: 7.631669 | N47: 7.5633887
A48: Knees | B48: SALES_REV_TURN | C48: IS010 | D48: SEG0000173641 Segment | E48: 1701 | F48: 1815 | G48: 1567 | H48: 1848 | I48: 1997 | J48: 2273 | K48: 2447 | L48: 2656 | M48: 2840.8475 | N48: 3021.1802
A49: Constant Currency Growth (%) | B49: REVENUE_GROWTH_CC_1_YR | C49: M0025 | D49: SEG0000173641 Segment | E49: 6.3 | F49: 8.1 | G49: -13.7 | H49: 16.9 | I49: 11.2 | J49: 14.4 | K49: 8.2 | L49: 8.2 | M49: 6.9176037 | N49: 6.1508638
A50: Hips | B50: SALES_REV_TURN | C50: IS010 | D50: SEG0000173657 Segment | E50: 1336 | F50: 1383 | G50: 1206 | H50: 1342 | I50: 1413 | J50: 1544 | K50: 1704 | L50: 1865 | M50: 1989.1261 | N50: 2109.3862
A51: Constant Currency Growth (%) | B51: REVENUE_GROWTH_CC_1_YR | C51: M0025 | D51: SEG0000173657 Segment | E51: 2.1 | F51: 5.2 | G51: -12.7 | H51: 9.9 | I51: 10.1 | J51: 10.4 | K51: 11.3 | L51: 8.9 | M51: 6.674145 | N51: 6.1965386
A52: Trauma & Extremities | B52: SALES_REV_TURN | C52: IS010 | D52: SEG0000173644 Segment | E52: 1580 | F52: 1639 | G52: 1722 | H52: 2664 | I52: 2807 | J52: 3147 | K52: 3507 | L52: 3948 | M52: 4317.0977 | N52: 4670.8913
A53: Constant Currency Growth (%) | B53: REVENUE_GROWTH_CC_1_YR | C53: M0025 | D53: SEG0000173644 Segment | E53: 6.2 | F53: 5.2 | G53: 4.7 | H53: 53 | I53: 8.7 | J53: 12.2 | K53: 11.6 | L53: 11.8 | M53: 8.8134107 | N53: 8.3396247
A54: Spinal Implants | B54: SALES_REV_TURN | C54: IS010 | D54: SEG4388955483 Segment | I54: 733 | J54: 713 | K54: 707 | L54: 185 | M54: 24
A55: Constant Currency Growth (%) | B55: REVENUE_GROWTH_CC_1_YR | C55: M0025 | D55: SEG4388955483 Segment | J55: -2 | K55: -0.3 | L55: -73.9
A56: Other | B56: SALES_REV_TURN | C56: IS010 | D56: SEG0000608256 Segment | E56: 374 | F56: 415 | G56: 464 | H56: 549 | I56: 606 | J56: 658 | K56: 712 | L56: 815 | M56: 872.60132 | N56: 937.5209
A57: Constant Currency Growth (%) | B57: REVENUE_GROWTH_CC_1_YR | C57: M0025 | D57: SEG0000608256 Segment | E57: 11 | F57: 12 | G57: 11.4 | H57: 18 | I57: -10.3 | J57: 9.5 | K57: 9.6 | L57: 14 | M57: 8.2378766 | N57: 7.8160895
A59: MedSurg & Neurotechnology
A60: Revenue | B60: SALES_REV_TURN | C60: IS010 | D60: SEG0000608020 Segment | F60: 8475 | G60: 8345 | H60: 9538 | I60: 10893 | J60: 12163 | K60: 13518 | L60: 15647 | M60: 17280.12 | N60: 18817.612
A61: Constant Currency Growth (%) | B61: REVENUE_GROWTH_CC_1_YR | C61: M0025 | D61: SEG0000608020 Segment | G61: -1.5 | H61: 13.3 | I61: 14.1 | J61: 12.2 | K61: 11.6 | L61: 15.4 | M61: 10.372364 | N61: 8.8298462
A62: Organic Growth (%) | B62: IS_ORGANIC_GROWTH_RATE | C62: IS950 | D62: SEG0000608020 Segment | H62: 13.1 | I62: 11.8 | J62: 11.8 | K62: 11.2 | L62: 10.7 | M62: 8.902267 | N62: 9.1432523
A63: Instruments | B63: SALES_REV_TURN | C63: IS010 | D63: SEG0000173634 Segment | E63: 1822 | F63: 1959 | G63: 1863 | H63: 2111 | I63: 2245 | J63: 2534 | K63: 2834 | L63: 3183 | M63: 3496.053 | N63: 3793.1494
A64: Constant Currency Growth (%) | B64: REVENUE_GROWTH_CC_1_YR | C64: M0025 | D64: SEG0000173634 Segment | E64: 8.4 | F64: 13.1 | G64: -5 | H64: 12.5 | I64: 10.4 | J64: 13 | K64: 12.1 | L64: 11.9 | M64: 9.5434233 | N64: 8.5851084
A65: Endoscopy | B65: SALES_REV_TURN | C65: IS010 | D65: SEG0000173697 Segment | E65: 1846 | F65: 1983 | G65: 1763 | H65: 2141 | I65: 2759 | J65: 3068 | K65: 3389 | L65: 3807 | M65: 4150.364 | N65: 4500.9321
A66: Constant Currency Growth (%) | B66: REVENUE_GROWTH_CC_1_YR | C66: M0025 | D66: SEG0000173697 Segment | E66: 11.9 | F66: 8.6 | G66: -11 | H66: 20.8 | I66: 15.9 | J66: 11.7 | K66: 11 | L66: 12.3 | M66: 9.3885851 | N66: 8.5840938
A67: Medical | B67: SALES_REV_TURN | C67: IS010 | D67: SEG0000173720 Segment | E67: 2118 | F67: 2264 | G67: 2524 | H67: 2607 | I67: 3031 | J67: 3459 | K67: 3852 | L67: 4204 | M67: 4604.4725 | N67: 5005.0768
A68: Constant Currency Growth (%) | B68: REVENUE_GROWTH_CC_1_YR | C68: M0025 | D68: SEG0000173720 Segment | E68: 7.5 | F68: 8.1 | G68: 11.8 | H68: 2.2 | I68: 18.6 | J68: 14.4 | K68: 11.7 | L68: 8.8 | M68: 9.3784615 | N68: 8.794942
A69: Vascular | B69: SALES_REV_TURN | C69: IS010 | D69: SEG0000608022 Segment | F69: 924 | G69: 973 | H69: 1188 | I69: 1200 | J69: 1226 | K69: 1307 | L69: 1968 | M69: 2273.4045 | N69: 2502.0556
A70: Constant Currency Growth (%) | B70: REVENUE_GROWTH_CC_1_YR | C70: M0025 | D70: SEG0000608022 Segment | G70: 4.9 | H70: 19.5 | I70: 7.2 | J70: 4 | K70: 8.2 | L70: 50 | M70: 13.881297 | N70: 8.8941092
A71: Neuro Cranial | B71: SALES_REV_TURN | C71: IS010 | D71: SEG0000608023 Segment | F71: 1059 | G71: 972 | H71: 1214 | I71: 1658 | J71: 1876 | K71: 2136 | L71: 2485 | M71: 2762.5909 | N71: 3027.7051
A72: Constant Currency Growth (%) | B72: REVENUE_GROWTH_CC_1_YR | C72: M0025 | D72: SEG0000608023 Segment | G72: -8.3 | H72: 24.3 | I72: 15.4 | J72: 13.4 | K72: 14.1 | L72: 15.9 | M72: 10.658548 | N72: #N/A Invalid Parameter: Undefined item: REVENUE_GROWTH_CC_1_YR.
A74: Prior Disclosure
A75: Revenue
A76: Spine | B76: SALES_REV_TURN | C76: IS010 | D76: SEG0000173732 Segment | E76: 828 | F76: 1157 | G76: 1047 | H76: 1167 | I76: 1146 | J76: 1189 | K76: 1097 | M76: 280.16787 | N76: 548.83958
A77: Constant Currency Growth (%) | B77: REVENUE_GROWTH_CC_1_YR | C77: M0025 | D77: SEG0000173732 Segment | E77: 9.9 | F77: 32.3 | G77: -9.6 | H77: 10.5 | I77: 1.1 | J77: 4 | M77: -99.99477
A79: Regional Breakdown
A80: United States | B80: SALES_REV_TURN | C80: IS010 | D80: SEG0000173628 Segment | E80: 9848 | F80: 10957 | G80: 10455 | H80: 12321 | I80: 13638 | J80: 15257 | K80: 16943 | L80: 19006 | M80: 20613.935 | N80: 22288.105
A81: Orthopaedics | B81: SALES_REV_TURN | C81: IS010 | D81: SEG0000608371 Segment | F81: 4487 | G81: 4237 | H81: 5295 | I81: 5390 | J81: 5929 | K81: 6426 | L81: 6701 | M81: 7113.4641 | N81: 7625.4874
A82: Knees | B82: SALES_REV_TURN | C82: IS010 | D82: SEG0000173638 Segment | E82: 1244 | F82: 1347 | G82: 1170 | H82: 1351 | I82: 1493 | J82: 1676 | K82: 1788 | L82: 1924 | M82: 2035.2309 | N82: 2152.706
A83: Hips | B83: SALES_REV_TURN | C83: IS010 | D83: SEG0000173703 Segment | E83: 838 | F83: 882 | G83: 777 | H83: 822 | I83: 896 | J83: 988 | K83: 1059 | L83: 1137 | M83: 1212.8028 | N83: 1284.3354
A84: Trauma & Extremities | B84: SALES_REV_TURN | C84: IS010 | D84: SEG0000173723 Segment | E84: 1001 | F84: 1051 | G84: 1139 | H84: 1866 | I84: 2035 | J84: 2297 | K84: 2586 | L84: 2926 | M84: 3191.2926 | N84: 3436.4615
A85: Spinal Implants | B85: SALES_REV_TURN | C85: IS010 | D85: SEG8722495305 Segment | I85: 511 | J85: 500 | K85: 489 | L85: 118
A86: As Reported Growth (%) | B86: IS_REVENUE_GROWTH_PERCENTAGE | C86: IC060 | D86: SEG8722495305 Segment | J86: -2.2 | K86: -2.1 | L86: -76
A87: Other | B87: SALES_REV_TURN | C87: IS010 | D87: SEG0000608389 Segment | F87: 334 | G87: 387 | H87: 425 | I87: 455 | J87: 468 | K87: 504 | L87: 596 | M87: 587.60178 | N87: 626.90073
A88: MedSurg & Neurotechnology | B88: SALES_REV_TURN | C88: IS010 | D88: SEG0000608369 Segment | F88: 6470 | G88: 6218 | H88: 7026 | I88: 8248 | J88: 9328 | K88: 10517 | L88: 12305 | M88: 13589.638 | N88: 14860.547
A89: Instruments | B89: SALES_REV_TURN | C89: IS010 | D89: SEG0000173692 Segment | E89: 1424 | F89: 1542 | G89: 1471 | H89: 1637 | I89: 1776 | J89: 2016 | K89: 2267 | L89: 2562 | M89: 2790.1249 | N89: 3038.2062
A90: Endoscopy | B90: SALES_REV_TURN | C90: IS010 | D90: SEG0000173706 Segment | E90: 1432 | F90: 1577 | G90: 1408 | H90: 1670 | I90: 2245 | J90: 2513 | K90: 2792 | L90: 3133 | M90: 3418.4594 | N90: 3712.2732
A91: Medical | B91: SALES_REV_TURN | C91: IS010 | D91: SEG0000173652 Segment | E91: 1630 | F91: 1787 | G91: 1910 | H91: 2007 | I91: 2422 | J91: 2785 | K91: 3191 | L91: 3510 | M91: 3803.4432 | N91: 4115.9286
A92: Vascular | B92: SALES_REV_TURN | C92: IS010 | D92: SEG0000608375 Segment | F92: 391 | G92: 381 | H92: 451 | I92: 446 | J92: 483 | K92: 506 | M92: 1234.1615 | N92: 1359.0648
A93: Neuro Cranial | B93: SALES_REV_TURN | C93: IS010 | D93: SEG0000608376 Segment | F93: 890 | G93: 801 | H93: 988 | I93: 1359 | J93: 1531 | K93: 1761 | L93: 2052 | M93: 2220.8862 | N93: 2431.6798
A95: International | B95: SALES_REV_TURN | C95: IS010 | D95: SEG0000173693 Segment | E95: 3753 | F95: 3927 | G95: 3896 | H95: 4787 | I95: 4811 | J95: 5241 | K95: 5652 | L95: 6110 | M95: 6702.6737 | N95: 7246.4268
A96: As Reported Growth (%) | B96: IS_REVENUE_GROWTH_PERCENTAGE | C96: IC060 | D96: SEG0000173693 Segment | E96: 10.9 | F96: 4.6 | G96: -0.8 | H96: 22.8 | I96: 0.5 | J96: 8.9 | K96: 7.9 | L96: 8.1
A97: Constant Currency Growth (%) | B97: REVENUE_GROWTH_CC_1_YR | C97: M0025 | D97: SEG0000173693 Segment | E97: 9.7 | F97: 9.3 | G97: -0.9 | H97: 18.8 | I97: 11.7 | J97: 10.9 | K97: 9.8 | L97: 6.4 | M97: 6.9798978 | N97: 8.0356419
A98: Orthopaedics | B98: SALES_REV_TURN | C98: IS010 | D98: SEG0000608372 Segment | F98: 1922 | G98: 1769 | H98: 2275 | I98: 2166 | J98: 2406 | K98: 2651 | L98: 2768 | M98: 2928.4483 | N98: 3142.8237
A99: As Reported Growth (%) | B99: IS_REVENUE_GROWTH_PERCENTAGE | C99: IC060 | D99: SEG0000608372 Segment | G99: -8 | H99: 28.6 | I99: -2.2 | J99: 11.1 | K99: 10.2 | L99: 4.4
A100: Constant Currency Growth (%) | B100: REVENUE_GROWTH_CC_1_YR | C100: M0025 | D100: SEG0000608372 Segment | G100: -8.4 | H100: 24.5 | I100: 9.3 | J100: 13.1 | K100: 12 | L100: 2.6
A101: Knees | B101: SALES_REV_TURN | C101: IS010 | D101: SEG0000173712 Segment | E101: 457 | F101: 468 | G101: 397 | H101: 497 | I101: 504 | J101: 597 | K101: 659 | L101: 732 | M101: 783.85258 | N101: 838.49531
A102: As Reported Growth (%) | B102: IS_REVENUE_GROWTH_PERCENTAGE | C102: IC060 | D102: SEG0000173712 Segment | E102: 7.3 | F102: 2.6 | G102: -15.3 | H102: 25.5 | I102: 1 | J102: 18.5 | K102: 10.4 | L102: 11
A103: Constant Currency Growth (%) | B103: REVENUE_GROWTH_CC_1_YR | C103: M0025 | D103: SEG0000173712 Segment | E103: 5.7 | F103: 7.6 | G103: -15.5 | H103: 21.3 | I103: 12.9 | J103: 20.9 | K103: 12.2 | L103: 9.7 | M103: 7.032249 | N103: 6.705303
A104: Hips | B104: SALES_REV_TURN | C104: IS010 | D104: SEG0000173707 Segment | E104: 498 | F104: 501 | G104: 429 | H104: 520 | I104: 517 | J104: 556 | K104: 645 | L104: 728 | M104: 778.31797 | N104: 829.46674
A105: As Reported Growth (%) | B105: IS_REVENUE_GROWTH_PERCENTAGE | C105: IC060 | D105: SEG0000173707 Segment | E105: 3.1 | F105: 0.3 | G105: -14.1 | H105: 21.1 | I105: -0.6 | J105: 7.5 | K105: 15.9 | L105: 12.9
A106: Constant Currency Growth (%) | B106: REVENUE_GROWTH_CC_1_YR | C106: M0025 | D106: SEG0000173707 Segment | E106: 2 | F106: 4.8 | G106: -13.8 | H106: 17.2 | I106: 11.5 | J106: 10.7 | K106: 18.4 | L106: 11.2 | M106: 6.4746345 | N106: 6.266339
A107: Trauma & Extremities | B107: SALES_REV_TURN | C107: IS010 | D107: SEG0000173696 Segment | E107: 579 | F107: 588 | G107: 583 | H107: 798 | I107: 772 | J107: 850 | K107: 921 | L107: 1022 | M107: 1124.6793 | N107: 1209.7657
A108: As Reported Growth (%) | B108: IS_REVENUE_GROWTH_PERCENTAGE | C108: IC060 | D108: SEG0000173696 Segment | E108: 9.7 | F108: 1.6 | G108: -0.9 | H108: 36.8 | I108: -3.2 | J108: 10.1 | K108: 8.3 | L108: 11
A109: Constant Currency Growth (%) | B109: REVENUE_GROWTH_CC_1_YR | C109: M0025 | D109: SEG0000173696 Segment | E109: 7.4 | F109: 5.8 | G109: -1.9 | H109: 32.3 | I109: 8 | J109: 10.5 | K109: 9.1 | L109: 8.2 | M109: 8.1689654 | N109: 6.9772293
A110: Spinal Implants | B110: SALES_REV_TURN | C110: IS010 | D110: SEG1944566105 Segment | I110: 222 | J110: 213 | K110: 218 | L110: 67
A111: As Reported Growth (%) | B111: IS_REVENUE_GROWTH_PERCENTAGE | C111: IC060 | D111: SEG1944566105 Segment | J111: -4.1 | K111: 2.5 | L111: -69.3
...

Sheet BBG Adj Highlights
A2: Stryker Corp (SYK US) - BBG Adj Highlights
A4: In Millions of USD | C4: FY 2019 | D4: FY 2020 | E4: FY 2021 | F4: FY 2022 | G4: FY 2023 | H4: FY 2024 | I4: FY 2025 | J4: Current/LTM | K4: FY 2026 Est | L4: FY 2027 Est
A5: 12 Months Ending | C5: 12/31/2019 | D5: 12/31/2020 | E5: 12/31/2021 | F5: 12/31/2022 | G5: 12/31/2023 | H5: 12/31/2024 | I5: 12/31/2025 | J5: 12/31/2025 | K5: 12/31/2026 | L5: 12/31/2027
A6: Market Capitalization | B6: HISTORICAL_MARKET_CAP | C6: 78638.306 | D6: 92184.279 | E6: 100963 | F6: 92620.452 | G6: 113873.87 | H6: 137323.07 | I6: 134437.27 | J6: 131583.67
A7: - Cash & Equivalents | B7: CASH_AND_MARKETABLE_SECURITIES | C7: 4425 | D7: 3024 | E7: 3019 | F7: 1928 | G7: 3053 | H7: 4493 | I7: 4100 | J7: 4100
A8: + Preferred & Other | B8: PFD_EQTY_MINORTY_INTEREST | C8: 0 | D8: 0 | E8: 0 | F8: 0 | G8: 0 | H8: 0 | I8: 0 | J8: 0
A9: + Total Debt | B9: SHORT_AND_LONG_TERM_DEBT | C9: 11477 | D9: 14425 | E9: 12901 | F9: 13526 | G9: 13494 | H9: 14120 | I9: 16360 | J9: 16360
A10: Enterprise Value | B10: ENTERPRISE_VALUE | C10: 85690.306 | D10: 103585.28 | E10: 110845 | F10: 104218.45 | G10: 124314.87 | H10: 146950.07 | I10: 146697.27 | J10: 143843.67
A12: Revenue, Adj | B12: SALES_REV_TURN | C12: 14884 | D12: 14351 | E12: 17108 | F12: 18449 | G12: 20498 | H12: 22595 | I12: 25116 | J12: 25116 | K12: 27317.214 | L12: 29602.893
A13: Growth %, YoY | B13: SALES_GROWTH | C13: 9.4331 | D13: -3.581 | E13: 19.2112 | F13: 7.8384 | G13: 11.1063 | H13: 10.2303 | I13: 11.1573 | J13: 11.157336 | K13: 8.7641913 | L13: 8.367173
A14: Gross Profit, Adj | B14: GROSS_PROFIT | C14: 9807 | D14: 9160 | E14: 11267 | F14: 11649 | G14: 13099 | H14: 14565 | I14: 16391 | J14: 16391 | K14: 17835.409 | L14: 19399.664
A15: Margin % | B15: GROSS_PROFIT | C15: 65.889546 | D15: 63.828305 | E15: 65.858078 | F15: 63.141634 | G15: 63.903795 | H15: 64.461164 | I15: 65.261188 | J15: 65.261188 | K15: 65.29 | L15: 65.533
A16: EBITDA, Adj | B16: EBITDA | C16: 4355 | D16: 3969 | E16: 4886 | F16: 4904 | G16: 5520 | H16: 6332 | I16: 7269 | J16: 7269 | K16: 7838.9167 | L16: 8626.3478
A17: Margin % | B17: EBITDA | C17: 29.259608 | D17: 27.656609 | E17: 28.559738 | F17: 26.581387 | G17: 26.929457 | H17: 28.023899 | I17: 28.94171 | J17: 28.94171 | K17: 28.695886 | L17: 29.140219
A18: Net Income, Adj | B18: EARN_FOR_COMMON | C18: 2764 | D18: 2446 | E18: 2985 | F18: 3076 | G18: 3563 | H18: 4205 | I18: 4686 | J18: 4686 | K18: 5814.833 | L18: 6484.64
A19: Margin % | B19: EARN_FOR_COMMON | C19: 18.570277 | D19: 17.044108 | E19: 17.447978 | F19: 16.67299 | G19: 17.382184 | H19: 18.610312 | I19: 18.65743 | J19: 18.65743 | K19: 21.286332 | L19: 21.905427
A20: EPS, Adj | B20: IS_DIL_EPS_CONT_OPS | C20: 7.2726 | D20: 6.4272 | E20: 7.8022 | F20: 8.0486 | G20: 9.2873 | H20: 10.9032 | I20: 12.1257 | J20: 12.125771 | K20: 15.013 | L20: 16.746
A21: Growth %, YoY | B21: DILUTED_EPS_AFT_XO_ITEMS_GROWTH | C21: 13.3508 | D21: -11.6243 | E21: 21.3937 | F21: 3.158 | G21: 15.3899 | H21: 17.3989 | I21: 11.2132 | J21: 11.531854 | K21: 23.81096 | L21: 11.543329
A23: Cash from Operations | B23: CF_CASH_FROM_OPER | C23: 2191 | D23: 3277 | E23: 3263 | F23: 2624 | G23: 3711 | H23: 4242 | I23: 5044 | J23: 5044
A24: Capital Expenditures | B24: CAPITAL_EXPEND | C24: -649 | D24: -487 | E24: -525 | F24: -588 | G24: -575 | H24: -755 | I24: -761 | J24: -761 | K24: -833.4 | L24: -889.667
A25: Free Cash Flow | B25: CF_FREE_CASH_FLOW | C25: 1542 | D25: 2790 | E25: 2738 | F25: 2036 | G25: 3136 | H25: 3487 | I25: 4283 | J25: 4283 | K25: 5415.525 | L25: 5637.65
A26: Source: Bloomberg | C26: Right click to show data transparency (not supported for all values)

Sheet BBG Adjusted
A2: Stryker Corp (SYK US) - BBG Adjusted
A4: In Millions of USD except Per Share | C4: FY 2019 | D4: FY 2020 | E4: FY 2021 | F4: FY 2022 | G4: FY 2023 | H4: FY 2024 | I4: FY 2025 | J4: Last 12M | K4: FY 2026 Est | L4: FY 2027 Est
A5: 12 Months Ending | C5: 12/31/2019 | D5: 12/31/2020 | E5: 12/31/2021 | F5: 12/31/2022 | G5: 12/31/2023 | H5: 12/31/2024 | I5: 12/31/2025 | J5: 12/31/2025 | K5: 12/31/2026 | L5: 12/31/2027
A6: Revenue | B6: SALES_REV_TURN | C6: 14884 | D6: 14351 | E6: 17108 | F6: 18449 | G6: 20498 | H6: 22595 | I6: 25116 | J6: 25116 | K6: 27317.214 | L6: 29602.893
A7: + Sales & Services Revenue | B7: IS_SALES_AND_SERVICES_REVENUES | C7: 14884 | D7: 14351 | E7: 17108 | F7: 18449 | G7: 20498 | H7: 22595 | I7: 25116 | J7: 25116
A8: - Cost of Revenue | B8: IS_COGS_TO_FE_AND_PP_AND_G | C8: 5077 | D8: 5191 | E8: 5841 | F8: 6800 | G8: 7399 | H8: 8030 | I8: 8725 | J8: 8725
A9: + Cost of Goods & Services | B9: IS_COG_AND_SERVICES_SOLD | C9: 5077 | D9: 5191 | E9: 5841 | F9: 6800 | G9: 7399 | H9: 8030 | I9: 8725 | J9: 8725
A10: Gross Profit | B10: GROSS_PROFIT | C10: 9807 | D10: 9160 | E10: 11267 | F10: 11649 | G10: 13099 | H10: 14565 | I10: 16391 | J10: 16391 | K10: 17835.409 | L10: 19399.664
A11: + Other Operating Income | B11: IS_OTHER_OPER_INC | C11: 0 | D11: 0 | E11: 0 | F11: 0 | G11: 0 | H11: 0 | I11: 0 | J11: 0
A12: - Operating Expenses | B12: IS_OPERATING_EXPN | C12: 6363 | D12: 6133 | E12: 7504 | F12: 7892 | G12: 8779 | H12: 9473 | I12: 10520 | J12: 10520
A13: + Selling, General & Admin | B13: IS_SGA_EXPENSE | C13: 4984 | D13: 4755 | E13: 5752 | F13: 6035 | G13: 6851 | H13: 7436 | I13: 8221 | J13: 8221
A14: + Research & Development | B14: IS_OPERATING_EXPENSES_RD | C14: 915 | D14: 905 | E14: 1133 | F14: 1230 | G14: 1293 | H14: 1414 | I14: 1567 | J14: 1503
A15: + Other Operating Expense | B15: IS_OTHER_OPERATING_EXPENSES | C15: 464 | D15: 473 | E15: 619 | F15: 627 | G15: 635 | H15: 623 | I15: 732 | J15: 796
A16: Operating Income (Loss) | B16: IS_OPER_INC | C16: 3444 | D16: 3027 | E16: 3763 | F16: 3757 | G16: 4320 | H16: 5092 | I16: 5871 | J16: 5871 | K16: 7296.6923 | L16: 8076.7692
A17: - Non-Operating (Income) Loss | B17: IS_NONOP_INCOME_LOSS | C17: 151 | D17: 269 | E17: 303 | F17: 158 | G17: 215 | H17: 196 | I17: 402 | J17: 402
A18: + Interest Expense, Net | B18: IS_NET_INTEREST_EXPENSE | C18: 287 | D18: 315 | E18: 337 | F18: 337 | G18: 356 | H18: 396 | I18: 582
A19: + Interest Expense | B19: IS_INT_EXPENSE | C19: 287 | D19: 315 | E19: 337 | F19: 337 | G19: 356 | H19: 396 | I19: 582
A20: - Interest Income | B20: IS_INT_INC | C20: 0 | D20: 0 | E20: 0 | F20: 0 | G20: 0 | H20: 0 | I20: 0
A21: + Foreign Exch (Gain) Loss | B21: IS_FOREIGN_EXCH_LOSS | C21: 0 | D21: 0 | E21: 0 | F21: 0 | G21: 0 | H21: 0 | I21: 0
A22: + Other Non-Op (Income) Loss | B22: IS_OTHER_NON_OPERATING_INC_LOSS | C22: -136 | D22: -46 | E22: -34 | F22: -179 | G22: -141 | H22: -200 | I22: -180 | J22: 402
A23: Pretax Income (Loss), Adjusted | B23: PRETAX_INC | C23: 3293 | D23: 2758 | E23: 3460 | F23: 3599 | G23: 4105 | H23: 4896 | I23: 5469 | J23: 5469 | K23: 6872.739 | L23: 7680.261
A24: - Abnormal Losses (Gains) | B24: IS_ABNORMAL_ITEM | C24: 731 | D24: 804 | E24: 1179 | F24: 916 | G24: 432 | H24: 1404 | I24: 955 | J24: 955
A25: + Merger/Acquisition Expense | B25: IS_MERGER_ACQUISITION_EXPENSE | C25: 275 | D25: 242 | E25: 585 | F25: 150 | G25: 20 | H25: 154 | I25: 508 | J25: 508
A26: + Impairment of Goodwill | B26: IS_IMPAIRMENT_GOODWILL_INTANGIBL | C26: — | D26: — | E26: — | F26: 216 | G26: — | H26: 456 | I26: —
A27: + Impairment of Intangibles | B27: IS_IMPAIR_OF_INTANG_ASSETS | C27: — | D27: — | E27: — | F27: — | G27: — | H27: 521 | I27: 170 | J27: 170
A28: + Legal Settlement | B28: IS_LEGAL_LITIGATION_SETTLEMENT | C28: 168 | D28: 23 | E28: 101 | F28: 61 | G28: 110 | H28: 36 | I28: 17 | J28: 17
A29: + Restructuring | B29: IS_RESTRUCTURING_EXPENSES | C29: 226 | D29: 458 | E29: 386 | F29: 349 | G29: 206 | H29: 139 | I29: 164 | J29: 164
A30: + Other Abnormal Items | B30: IS_OTHER_ONE_TIME_ITEMS | C30: 62 | D30: 81 | E30: 107 | F30: 140 | G30: 96 | H30: 98 | I30: 96 | J30: 96
A31: Pretax Income (Loss), GAAP | B31: PRETAX_INC | C31: 2562 | D31: 1954 | E31: 2281 | F31: 2683 | G31: 3673 | H31: 3492 | I31: 4514 | J31: 4514 | K31: 6872.739 | L31: 7680.261
A32: - Income Tax Expense (Benefit) | B32: IS_INC_TAX_EXP | C32: 479 | D32: 355 | E32: 287 | F32: 325 | G32: 508 | H32: 499 | I32: 1268 | J32: 1268
A33: + Current Income Tax | B33: IS_CURRENT_INCOME_TAX_BENEFIT | C33: 353 | D33: 307 | E33: 524 | F33: 267 | G33: 714 | H33: 869 | I33: 876
A34: + Deferred Income Tax | B34: IS_DEFERRED_INCOME_TAX_BENEFIT | C34: 126 | D34: 48 | E34: -237 | F34: 58 | G34: -206 | H34: -370 | I34: 392
A35: Income (Loss) from Cont Ops | B35: IS_INC_BEF_XO_ITEM | C35: 2083 | D35: 1599 | E35: 1994 | F35: 2358 | G35: 3165 | H35: 2993 | I35: 3246 | J35: 3246 | K35: 4807.25 | L35: 5481.563
A36: - Net Extraordinary Losses (Gains) | B36: XO_GL_NET_OF_TAX | C36: 0 | D36: 0 | E36: 0 | F36: 0 | G36: 0 | H36: 0 | I36: 0 | J36: 0
A37: + Discontinued Operations | B37: IS_DISCONTINUED_OPERATIONS | C37: 0 | D37: 0 | E37: 0 | F37: 0 | G37: 0 | H37: 0 | I37: 0 | J37: 0
A38: + XO & Accounting Changes | B38: EXTRAORD_ITEMS_ACCOUNTING_CHANGS | C38: 0 | D38: 0 | E38: 0 | F38: 0 | G38: 0 | H38: 0 | I38: 0 | J38: 0
A39: Income (Loss) Incl. MI | B39: NI_INCLUDING_MINORITY_INT_RATIO | C39: 2083 | D39: 1599 | E39: 1994 | F39: 2358 | G39: 3165 | H39: 2993 | I39: 3246 | J39: 3246
A40: - Minority Interest | B40: MIN_NONCONTROL_INTEREST_CREDITS | C40: 0 | D40: 0 | E40: 0 | F40: 0 | G40: 0 | H40: 0 | I40: 0 | J40: 0
A41: Net Income, GAAP | B41: NET_INCOME | C41: 2083 | D41: 1599 | E41: 1994 | F41: 2358 | G41: 3165 | H41: 2993 | I41: 3246 | J41: 3246 | K41: 4807.25 | L41: 5481.563
A42: - Preferred Dividends | B42: IS_TOT_CASH_PFD_DVD | C42: 0 | D42: 0 | E42: 0 | F42: 0 | G42: 0 | H42: 0 | I42: 0 | J42: 0
A43: - Other Adjustments | B43: OTHER_ADJUSTMENTS | C43: 0 | D43: 0 | E43: 0 | F43: 0 | G43: 0 | H43: 0 | I43: 0 | J43: 0
A44: Net Income Avail to Common, GAAP | B44: EARN_FOR_COMMON | C44: 2083 | D44: 1599 | E44: 1994 | F44: 2358 | G44: 3165 | H44: 2993 | I44: 3246 | J44: 3246 | K44: 4807.25 | L44: 5481.563
A46: Net Income Avail to Common, Adj | B46: EARN_FOR_COMMON | C46: 2764 | D46: 2446 | E46: 2985 | F46: 3076 | G46: 3563 | H46: 4205 | I46: 4686 | J46: 4686 | K46: 5814.833 | L46: 6484.64
A47: Net Abnormal Losses (Gains) | B47: IS_NET_ABNORMAL_ITEMS | C47: 681 | D47: 847 | E47: 991 | F47: 718 | G47: 398 | H47: 1212 | I47: 1440 | J47: 1440
A48: Net Extraordinary Losses (Gains) | B48: XO_GL_NET_OF_TAX | C48: 0 | D48: 0 | E48: 0 | F48: 0 | G48: 0 | H48: 0 | I48: 0 | J48: 0
A50: Basic Weighted Avg Shares | B50: IS_AVG_NUM_SH_FOR_EPS | C50: 374 | D50: 375.5 | E50: 377 | F50: 378.2 | G50: 379.6 | H50: 381 | I50: 382.2 | J50: 382.5
A51: Basic EPS, GAAP | B51: IS_EPS | C51: 5.57 | D51: 4.26 | E51: 5.29 | F51: 6.23 | G51: 8.34 | H51: 7.86 | I51: 8.49 | J51: 8.49 | K51: 12.845 | L51: 14.536
A52: Basic EPS from Cont Ops, GAAP | B52: IS_EARN_BEF_XO_ITEMS_PER_SH | C52: 5.57 | D52: 4.26 | E52: 5.29 | F52: 6.23 | G52: 8.34 | H52: 7.86 | I52: 8.49 | J52: 8.49 | K52: 12.845 | L52: 14.536
A53: Basic EPS from Cont Ops, Adjusted | B53: IS_BASIC_EPS_CONT_OPS | C53: 7.3904 | D53: 6.514 | E53: 7.9178 | F53: 8.1333 | G53: 9.3862 | H53: 11.0367 | I53: 12.2606 | J53: 12.259184 | K53: 15.013 | L53: 16.746
A55: Diluted Weighted Avg Shares | B55: IS_SH_FOR_DILUTED_EPS | C55: 379.9 | D55: 380.3 | E55: 382.3 | F55: 382.2 | G55: 383.7 | H55: 385.6 | I55: 386.5 | J55: 386.5
A56: Diluted EPS, GAAP | B56: IS_DILUTED_EPS | C56: 5.48 | D56: 4.2 | E56: 5.21 | F56: 6.17 | G56: 8.25 | H56: 7.76 | I56: 8.4 | J56: 8.4 | K56: 12.845 | L56: 14.536
A57: Diluted EPS from Cont Ops, GAAP | B57: IS_DIL_EPS_BEF_XO | C57: 5.48 | D57: 4.2 | E57: 5.21 | F57: 6.17 | G57: 8.25 | H57: 7.76 | I57: 8.4 | J57: 8.4 | K57: 12.845 | L57: 14.536
A58: Diluted EPS from Cont Ops, Adjusted | B58: IS_DIL_EPS_CONT_OPS | C58: 7.2726 | D58: 6.4272 | E58: 7.8022 | F58: 8.0486 | G58: 9.2873 | H58: 10.9032 | I58: 12.1257 | J58: 12.125771 | K58: 15.013 | L58: 16.746
A60: Reference Items
A61: Accounting Standard | B61: ACCOUNTING_STANDARD | C61: US GAAP | D61: US GAAP | E61: US GAAP | F61: US GAAP | G61: US GAAP | H61: US GAAP | I61: US GAAP
A62: EBITDA | B62: EBITDA | C62: 4355 | D62: 3969 | E62: 4886 | F62: 4904 | G62: 5520 | H62: 6332 | I62: 7269 | J62: 7269 | K62: 7838.9167 | L62: 8626.3478
A63: EBITDA Margin (T12M) | B63: EBITDA_MARGIN | C63: 29.2596 | D63: 27.6566 | E63: 28.5597 | F63: 26.5814 | G63: 26.9295 | H63: 28.0239 | I63: 28.9417 | J63: 28.94171 | K63: 28.695888 | L63: 29.14022
A64: EBITA | B64: EBITA | C64: 4041 | D64: 3629 | E64: 4515 | F64: 4533 | G64: 5127 | H64: 5905 | I64: 6808 | J64: 6808
A65: EBIT | B65: EBIT | C65: 3444 | D65: 3027 | E65: 3763 | F65: 3757 | G65: 4320 | H65: 5092 | I65: 5871 | J65: 5871 | K65: 7296.6923 | L65: 8076.7692
A66: Gross Margin | B66: GROSS_MARGIN | C66: 65.8895 | D66: 63.8283 | E66: 65.8581 | F66: 63.1416 | G66: 63.9038 | H66: 64.4612 | I66: 65.2612 | J66: 65.261188 | K66: 65.29 | L66: 65.533
A67: Operating Margin | B67: OPER_MARGIN | C67: 23.1389 | D67: 21.0926 | E67: 21.9956 | F67: 20.3642 | G67: 21.0752 | H67: 22.536 | I67: 23.3755 | J67: 23.375538 | K67: 26.710967 | L67: 27.283715
A68: Profit Margin | B68: PROF_MARGIN | C68: 18.5703 | D68: 17.0441 | E68: 17.448 | F68: 16.673 | G68: 17.3822 | H68: 18.6103 | I68: 18.6574 | J68: 18.65743 | K68: 21.286332 | L68: 21.905427
A69: Sales per Employee | B69: ACTUAL_SALES_PER_EMPL | C69: 372100 | D69: 333744.19 | E69: 371913.04 | F69: 361745.1 | G69: 394192.31 | H69: 426320.75 | I69: —
A70: Dividends per Share | B70: EQY_DPS | C70: 2.08 | D70: 2.3 | E70: 2.52 | F70: 2.78 | G70: 3 | H70: 3.2 | I70: 3.36 | J70: 3.4 | K70: 3.555 | L70: 3.808
A71: Total Cash Common Dividends | B71: IS_TOT_CASH_COM_DVD | C71: 778 | D71: 863 | E71: 950 | F71: 1051 | G71: 1139 | H71: 1219 | I71: 1284 | J71: 1285.216
A72: Capitalized Interest Expense | B72: IS_CAP_INT_EXP | C72: 0 | D72: — | E72: — | F72: — | G72: — | H72: — | I72: —
A73: Depreciation Expense | B73: IS_DEPR_EXP | C73: 314 | D73: 340 | E73: 371 | F73: 371 | G73: 393 | H73: 427 | I73: 461 | J73: 461
A74: Rental Expense | B74: BS_CURR_RENTAL_EXPENSE | C74: 133 | D74: 130 | E74: 133 | F74: 149 | G74: 172 | H74: 190 | I74: 205 | J74: 205
A75: Source: Bloomberg | C75: Right click to show data transparency (not supported for all values)

Sheet BS
A2: Stryker Corp (SYK US) - Standardized
A4: In Millions of USD except Per Share | C4: FY 2016 | D4: FY 2017 | E4: FY 2018 | F4: FY 2019 | G4: FY 2020 | H4: FY 2021 | I4: FY 2022 | J4: FY 2023 | K4: FY 2024 | L4: FY 2025
A5: 12 Months Ending | C5: 12/31/2016 | D5: 12/31/2017 | E5: 12/31/2018 | F5: 12/31/2019 | G5: 12/31/2020 | H5: 12/31/2021 | I5: 12/31/2022 | J5: 12/31/2023 | K5: 12/31/2024 | L5: 12/31/2025
A6: Total Assets
A7: + Cash, Cash Equivalents & STI | B7: CASH_CASH_EQTY_STI_DETAILED | C7: 3384 | D7: 2793 | E7: 3699 | F7: 4425 | G7: 3024 | H7: 3019 | I7: 1928 | J7: 3053 | K7: 4493 | L7: 4100
A8: + Cash & Cash Equivalents | B8: BS_CASH_NEAR_CASH_ITEM | C8: 3316 | D8: 2542 | E8: 3616 | F8: 4337 | G8: 2943 | H8: 2944 | I8: 1844 | J8: 2971 | K8: 3652 | L8: 4011
A9: + ST Investments | B9: BS_MKT_SEC_OTHER_ST_INVEST | C9: 68 | D9: 251 | E9: 83 | F9: 88 | G9: 81 | H9: 75 | I9: 84 | J9: 82 | K9: 841 | L9: 89
A10: + Accounts & Notes Receiv | B10: BS_ACCT_NOTE_RCV | C10: 1967 | D10: 2198 | E10: 2332 | F10: 2893 | G10: 2701 | H10: 3022 | I10: 3565 | J10: 3765 | K10: 3987 | L10: 4039
A11: + Accounts Receivable, Net | B11: BS_ACCTS_REC_EXCL_NOTES_REC | C11: 1967 | D11: 2198 | E11: 2332 | F11: 2893 | G11: 2701 | H11: 3022 | I11: 3565 | J11: 3765 | K11: 3987 | L11: 4039
A12: + Notes Receivable, Net | B12: NOTES_RECEIVABLE | C12: 0 | D12: 0 | E12: 0 | F12: 0 | G12: 0 | H12: 0 | I12: 0 | J12: 0 | K12: 0 | L12: 0
A13: + Inventories | B13: BS_INVENTORIES | C13: 2030 | D13: 2465 | E13: 2955 | F13: 2980 | G13: 3494 | H13: 3314 | I13: 3995 | J13: 4843 | K13: 4774 | L13: 5310
A14: + Raw Materials | B14: INVTRY_RAW_MATERIALS | C14: 0 | D14: 0 | E14: 0 | F14: 0 | G14: 0 | H14: 0 | I14: 0 | J14: 0 | K14: 0 | L14: 0
A15: + Work In Process | B15: INVTRY_IN_PROGRESS | C15: 130 | D15: 148 | E15: 149 | F15: 178 | G15: 251 | H15: 264 | I15: 348 | J15: 330 | K15: 336 | L15: 415
A16: + Finished Goods | B16: INVTRY_FINISHED_GOODS | C16: 1475 | D16: 1789 | E16: 2200 | F16: 2125 | G16: 2565 | H16: 2359 | I16: 2641 | J16: 3271 | K16: 3291 | L16: 3546
A17: + Other Inventory | B17: BS_OTHER_INV | C17: 425 | D17: 528 | E17: 606 | F17: 677 | G17: 678 | H17: 691 | I17: 1006 | J17: 1242 | K17: 1147 | L17: 1349
A18: + Other ST Assets | B18: OTHER_CURRENT_ASSETS_DETAILED | C18: 480 | D18: 537 | E18: 747 | F18: 760 | G18: 488 | H18: 662 | I18: 787 | J18: 857 | K18: 1593 | L18: 1306
A19: + Derivative & Hedging Assets | B19: BS_DERIV_HEDGING_ASST_ST | C19: 41 | D19: 15 | E19: 43 | F19: 185 | G19: 16 | H19: 146 | I19: 29 | J19: 114 | K19: 186 | L19: 44
A20: + Deferred Tax Assets | B20: BS_DEFERRED_TAX_ASSETS_ST | C20: 0 | D20: 0 | E20: 0 | F20: 0 | G20: 0 | H20: 0 | I20: 0 | J20: 0 | K20: — | L20: —
A21: + Misc ST Assets | B21: BS_OTHER_CUR_ASSET_LESS_PREPAY | C21: 439 | D21: 522 | E21: 704 | F21: 575 | G21: 472 | H21: 516 | I21: 758 | J21: 743 | K21: 1407 | L21: 1262
A22: Total Current Assets | B22: BS_CUR_ASSET_REPORT | C22: 7861 | D22: 7993 | E22: 9733 | F22: 11058 | G22: 9707 | H22: 10017 | I22: 10275 | J22: 12518 | K22: 14847 | L22: 14755
A23: + Property, Plant & Equip, Net | B23: BS_NET_FIX_ASSET | C23: 1569 | D23: 1975 | E23: 2291 | F23: 2951 | G23: 3175 | H23: 3252 | I23: 3443 | J23: 3709 | K23: 3964 | L23: 4395
A24: + Property, Plant & Equip | B24: BS_GROSS_FIX_ASSET | C24: 3161 | D24: 3800 | E24: 4277 | F24: 5098 | G24: 5605 | H24: 5917 | I24: 6278 | J24: 6838 | K24: 7199 | L24: 8056
A25: - Accumulated Depreciation | B25: BS_ACCUM_DEPR | C25: 1592 | D25: 1825 | E25: 1986 | F25: 2147 | G25: 2430 | H25: 2665 | I25: 2835 | J25: 3129 | K25: 3235 | L25: 3661
A26: + LT Investments & Receivables | B26: BS_LT_INVEST | C26: 0 | D26: 0 | E26: 0 | F26: 0 | G26: 0 | H26: 0 | I26: 0 | J26: 0 | K26: 0 | L26: 0
A27: + Other LT Assets | B27: BS_OTHER_ASSETS_DEF_CHRG_OTHER | C27: 11005 | D27: 12229 | E27: 15205 | F27: 16158 | G27: 21448 | H27: 21362 | I27: 23166 | J27: 23685 | K27: 24160 | L27: 28694
A28: + Total Intangible Assets | B28: BS_DISCLOSED_INTANGIBLES | C28: 9864 | D28: 10645 | E28: 12726 | F28: 13296 | G28: 18332 | H28: 17758 | I28: 19765 | J28: 19836 | K28: 20250 | L28: 24972
A29: + Goodwill | B29: BS_GOODWILL | C29: 6356 | D29: 7168 | E29: 8563 | F29: 9069 | G29: 12778 | H29: 12918 | I29: 14880 | J29: 15243 | K29: 15855 | L29: 19291
A30: + Other Intangible Assets | B30: OTHER_INTANGIBLE_ASSETS_DETAILED | C30: 3508 | D30: 3477 | E30: 4163 | F30: 4227 | G30: 5554 | H30: 4840 | I30: 4885 | J30: 4593 | K30: 4395 | L30: 5681
A31: + Deferred Tax Assets | B31: BS_DEFERRED_TAX_ASSETS_LT | C31: 302 | D31: 283 | E31: 1678 | F31: 1575 | G31: 1530 | H31: 1760 | I31: 1410 | J31: 1670 | K31: 1742 | L31: 1098
A32: + Derivative & Hedging Assets | B32: BS_DERIV_HEDGING_ASST_LT | C32: 4 | D32: 1 | E32: 34 | F32: 1 | G32: 4 | H32: 66 | I32: 90 | J32: 2 | K32: 39 | L32: 2
A33: + Prepaid Pension Costs | B33: BS_PREPAID_PENSION_COSTS_LT | C33: 0 | D33: 0 | E33: 0 | F33: 0 | G33: 0 | H33: 0 | I33: — | J33: — | K33: — | L33: —
A34: + Misc LT Assets | B34: OTHER_NONCURRENT_ASSETS_DETAILED | C34: 835 | D34: 1300 | E34: 767 | F34: 1286 | G34: 1582 | H34: 1778 | I34: 1901 | J34: 2177 | K34: 2129 | L34: 2622
A35: Total Noncurrent Assets | B35: BS_TOT_NON_CUR_ASSET | C35: 12574 | D35: 14204 | E35: 17496 | F35: 19109 | G35: 24623 | H35: 24614 | I35: 26609 | J35: 27394 | K35: 28124 | L35: 33089
A36: Total Assets | B36: BS_TOT_ASSET | C36: 20435 | D36: 22197 | E36: 27229 | F36: 30167 | G36: 34330 | H36: 34631 | I36: 36884 | J36: 39912 | K36: 42971 | L36: 47844
A38: Liabilities & Shareholders' Equity
A39: + Payables & Accruals | B39: ACCT_PAYABLE_ACCRUALS_DETAILED | C39: 2904 | D39: 2817 | E39: 3414 | F39: 3103 | G39: 3533 | H39: 4012 | I39: 4676 | J39: 5423 | K39: 5993 | L39: 6539
A40: + Accounts Payable | B40: BS_ACCT_PAYABLE | C40: 437 | D40: 487 | E40: 646 | F40: 675 | G40: 810 | H40: 1129 | I40: 1413 | J40: 1517 | K40: 1679 | L40: 1799
A41: + Accrued Taxes | B41: BS_TAXES_PAYABLE | C41: 40 | D41: 143 | E41: 158 | F41: 171 | G41: 207 | H41: 192 | I41: 292 | J41: 391 | K41: 539 | L41: 418
A42: + Interest & Dividends Payable | B42: INTEREST_DIVIDENDS_PAYABLE | C42: 159 | D42: 178 | E42: 192 | F42: 213 | G42: 237 | H42: 263 | I42: 284 | J42: 304 | K42: 320 | L42: 337
A43: + Other Payables & Accruals | B43: BS_ACCRUAL | C43: 2268 | D43: 2009 | E43: 2418 | F43: 2044 | G43: 2279 | H43: 2428 | I43: 2687 | J43: 3211 | K43: 3455 | L43: 3985
A44: + ST Debt | B44: BS_ST_BORROW | C44: 228 | D44: 632 | E44: 1373 | F44: 945 | G44: 870 | H44: 119 | I44: 1312 | J44: 2237 | K44: 1553 | L44: 1153
A45: + ST Borrowings | B45: SHORT_TERM_DEBT_DETAILED | C45: 0 | D45: 0 | E45: 0 | F45: 0 | G45: 0 | H45: 0 | I45: 0 | J45: 0 | K45: 0 | L45: 0
A46: + ST Lease Liabilities | B46: ST_CAPITALIZED_LEASE_LIABILITIES | C46: 0 | D46: 0 | E46: 0 | F46: 86 | G46: 109 | H46: 112 | I46: 121 | J46: 143 | K46: 144 | L46: 153
A47: + ST Finance Leases | B47: ST_CAPITAL_LEASE_OBLIGATIONS | C47: 0 | D47: 0 | E47: 0 | F47: — | G47: — | H47: — | I47: — | J47: — | K47: — | L47: —
A48: + ST Operating Leases | B48: BS_ST_OPERATING_LEASE_LIABS | C48: — | D48: — | E48: — | F48: 86 | G48: 109 | H48: 112 | I48: 121 | J48: 143 | K48: 144 | L48: 153
A49: + Current Portion of LT Debt | B49: BS_CURR_PORTION_LT_DEBT | C49: 228 | D49: 632 | E49: 1373 | F49: 859 | G49: 761 | H49: 7 | I49: 1191 | J49: 2094 | K49: 1409 | L49: 1000
A50: + Other ST Liabilities | B50: OTHER_CURRENT_LIABS_SUB_DETAILED | C50: 16 | D50: 36 | E50: 20 | F50: 352 | G50: 638 | H50: 418 | I50: 315 | J50: 261 | K50: 70 | L50: 102
A51: + Deferred Revenue | B51: ST_DEFERRED_REVENUE | C51: 0 | D51: 0 | E51: 0 | F51: 0 | G51: 0 | H51: 0 | I51: 0 | J51: 0 | K51: 0 | L51: 0
A52: + Derivatives & Hedging | B52: BS_DERIV_HEDGING_LIAB_ST | C52: 16 | D52: 36 | E52: 20 | F52: 21 | G52: 123 | H52: 17 | I52: 85 | J52: 52 | K52: 70 | L52: 102
A53: + Misc ST Liabilities | B53: OTHER_CURRENT_LIABS_DETAILED | C53: 0 | D53: 0 | E53: 0 | F53: 331 | G53: 515 | H53: 401 | I53: 230 | J53: 209 | K53: 0 | L53: 0
A54: Total Current Liabilities | B54: BS_CUR_LIAB | C54: 3148 | D54: 3485 | E54: 4807 | F54: 4400 | G54: 5041 | H54: 4549 | I54: 6303 | J54: 7921 | K54: 7616 | L54: 7794
A55: + LT Debt | B55: BS_LT_BORROW | C55: 6686 | D55: 6590 | E55: 8486 | F55: 10532 | G55: 13555 | H55: 12782 | I55: 12214 | J55: 11257 | K55: 12567 | L55: 15207
A56: + LT Borrowings | B56: LONG_TERM_BORROWINGS_DETAILED | C56: 6686 | D56: 6590 | E56: 8486 | F56: 10231 | G56: 13230 | H56: 12472 | I56: 11857 | J56: 10901 | K56: 12188 | L56: 14859
A57: + LT Lease Liabilities | B57: LT_CAPITALIZED_LEASE_LIABILITIES | C57: 0 | D57: 0 | E57: 0 | F57: 301 | G57: 325 | H57: 310 | I57: 357 | J57: 356 | K57: 379 | L57: 348
A58: + LT Finance Leases | B58: LT_CAPITAL_LEASE_OBLIGATIONS | C58: 0 | D58: 0 | E58: 0 | F58: — | G58: — | H58: — | I58: — | J58: — | K58: — | L58: —
A59: + LT Operating Leases | B59: BS_LT_OPERATING_LEASE_LIABS | C59: — | D59: — | E59: — | F59: 301 | G59: 325 | H59: 310 | I59: 357 | J59: 356 | K59: 379 | L59: 348
A60: + Other LT Liabilities | B60: OTHER_NONCUR_LIABS_SUB_DETAILED | C60: 1051 | D60: 2142 | E60: 2206 | F60: 2428 | G60: 2650 | H60: 2423 | I60: 1751 | J60: 2141 | K60: 2154 | L60: 2423
A61: + Accrued Liabilities | B61: BS_ACCRUED_LIABILITIES | C61: 0 | D61: 0 | E61: 0 | F61: 0 | G61: 0 | H61: 0 | I61: 0 | J61: 0 | K61: 0 | L61: 0
A62: + Pension Liabilities | B62: PENSION_LIABILITIES | C62: 279 | D62: 336 | E62: 357 | F62: 439 | G62: 594 | H62: 491 | I62: 271 | J62: 359 | K62: 335 | L62: 336
A63: + Deferred Revenue | B63: LT_DEFERRED_REVENUE | C63: 0 | D63: 0 | E63: 0 | F63: 0 | G63: 0 | H63: 0 | I63: 0 | J63: 0 | K63: 0 | L63: 0
A64: + Deferred Tax Liabilities | B64: BS_DEFERRED_TAX_LIABILITIES_LT | C64: 55 | D64: 47 | E64: 54 | F64: 108 | G64: 117 | H64: 68 | I64: 67 | J64: 63 | K64: 82 | L64: 137
A65: + Derivatives & Hedging | B65: BS_DERIV_HEDGING_LIAB_LT | C65: 2 | D65: 1 | E65: 0 | F65: 2 | G65: 0 | H65: 0 | I65: 17 | J65: 45 | K65: 7 | L65: 68
A66: + Misc LT Liabilities | B66: OTHER_NONCURRENT_LIABS_DETAILED | C66: 715 | D66: 1758 | E66: 1795 | F66: 1879 | G66: 1939 | H66: 1864 | I66: 1396 | J66: 1674 | K66: 1730 | L66: 1882
A67: Total Noncurrent Liabilities | B67: NON_CUR_LIAB | C67: 7737 | D67: 8732 | E67: 10692 | F67: 12960 | G67: 16205 | H67: 15205 | I67: 13965 | J67: 13398 | K67: 14721 | L67: 17630
A68: Total Liabilities | B68: BS_TOT_LIAB2 | C68: 10885 | D68: 12217 | E68: 15499 | F68: 17360 | G68: 21246 | H68: 19754 | I68: 20268 | J68: 21319 | K68: 22337 | L68: 25424
A69: + Preferred Equity and Hybrid Capital | B69: PFD_EQTY_HYBRID_CAPITAL | C69: 0 | D69: 0 | E69: 0 | F69: 0 | G69: 0 | H69: 0 | I69: 0 | J69: 0 | K69: 0 | L69: 0
A70: + Share Capital & APIC | B70: BS_SH_CAP_AND_APIC | C70: 1469 | D70: 1533 | E70: 1596 | F70: 1665 | G70: 1779 | H70: 1928 | I70: 2072 | J70: 2238 | K70: 2399 | L70: 2635
A71: + Common Stock | B71: BS_COMMON_STOCK | C71: 37 | D71: 37 | E71: 37 | F71: 37 | G71: 38 | H71: 38 | I71: 38 | J71: 38 | K71: 38 | L71: 38
... A79: Total Liabilities & Equity | B79: TOT_LIAB_AND_EQY | C79: 20435 | D79: 22197 | E79: 27229 | F79: 30167 | G79: 34330 | H79: 34631 | I79: 36884 | J79: 39912 | K79: 42971 | L79: 47844
A81: Reference Items
A82: Accounting Standard | B82: ACCOUNTING_STANDARD | C82: US GAAP | D82: US GAAP | E82: US GAAP | F82: US GAAP | G82: US GAAP | H82: US GAAP | I82: US GAAP | J82: US GAAP | K82: US GAAP | L82: US GAAP
A83: Shares Outstanding | B83: BS_SH_OUT | C83: 375 | D83: 374.2376 | E83: 372.6646 | F83: 374.5751 | G83: 376.2009 | H83: 377.5447 | I83: 378.8312 | J83: 380.264 | K83: 381.4 | L83: 382.5
A84: Number of Treasury Shares | B84: BS_NUM_OF_TSY_SH | C84: 0 | D84: 0 | E84: 0 | F84: 0 | G84: 0 | H84: 0 | I84: 0 | J84: 0 | K84: 0 | L84: 0
A85: Pension Obligations | B85: BS_PENSION_RSRV | C85: 279 | D85: 336 | E85: 357 | F85: 439 | G85: 594 | H85: 491 | I85: 271 | J85: 359 | K85: 335 | L85: 336
A86: Future Minimum Operating Lease Obligations | B86: BS_FUTURE_MIN_OPER_LEASE_OBLIG | C86: 269 | D86: 326 | E86: 342 | F86: 395 | G86: 420 | H86: 402 | I86: 466 | J86: 520 | K86: 550 | L86: 524
A87: Capital Leases - Total | B87: BS_TOTAL_CAPITAL_LEASES | C87: 0 | D87: 0 | E87: 0 | F87: — | G87: — | H87: — | I87: — | J87: — | K87: — | L87: —
A88: Options Granted During Period | B88: BS_OPTIONS_GRANTED | C88: 3.1 | D88: 2.9 | E88: 2.4 | F88: 2.1 | G88: 1.8 | H88: 1.8 | I88: 1.9 | J88: 1.6 | K88: 1.3 | L88: 1
A89: Options Outstanding at Period End | B89: BS_OPTIONS_OUTSTANDING | C89: 14.9 | D89: 14.7 | E89: 14.1 | F89: 12.8 | G89: 12.2 | H89: 12.1 | I89: 12.1 | J89: 11.5 | K89: 10.8 | L89: 10.4
A90: Net Debt | B90: NET_DEBT | C90: 3530 | D90: 4429 | E90: 6160 | F90: 7052 | G90: 11401 | H90: 9882 | I90: 11598 | J90: 10441 | K90: 9627 | L90: 12260
A91: Net Debt to Equity | B91: NET_DEBT_TO_SHRHLDR_EQTY | C91: 36.9634 | D91: 44.3788 | E91: 52.5149 | F91: 55.0636 | G91: 87.137 | H91: 66.4247 | I91: 69.8002 | J91: 56.1555 | K91: 46.656 | L91: 54.6833
A92: Tangible Common Equity Ratio | B92: TCE_RATIO | C92: -2.9704 | D92: -5.8778 | E92: -6.8675 | F92: -2.8985 | G92: -32.8041 | H92: -17.0746 | I92: -18.3948 | J92: -6.1915 | K92: 1.6901 | L92: -11.1577
A93: Current Ratio | B93: CUR_RATIO | C93: 2.4971 | D93: 2.2935 | E93: 2.0248 | F93: 2.5132 | G93: 1.9256 | H93: 2.202 | I93: 1.6302 | J93: 1.5804 | K93: 1.9494 | L93: 1.8931
A94: Cash Conversion Cycle | B94: CASH_CONVERSION_CYCLE | C94: 197.5612 | D94: 217.5831 | E94: 232.7849 | F94: 226.5973 | G94: 248.3329 | H94: 204.0315 | I94: 197.8637 | J94: 217.5356 | K94: 206.2612 | L94: 195.4402
A95: Cash Held Overseas | B95: BS_CASH_HELD_OVERSEAS | C95: 2842.56 | D95: 1731.66 | E95: 924.75 | F95: 1106.25 | G95: 81 | H95: 75 | I95: 84 | J95: 82 | K95: 91 | L95: 89
A96: Number of Employees | B96: NUM_OF_EMPLOYEES | C96: 33000 | D96: 33000 | E96: 36000 | F96: 40000 | G96: 43000 | H96: 46000 | I96: 51000 | J96: 52000 | K96: 53000 | L96: —
A97: Source: Bloomberg | C97: Right click to show data transparency (not supported for all values)

Sheet CF
A2: Stryker Corp (SYK US) - Standardized
A4: In Millions of USD except Per Share | C4: FY 2017 | D4: FY 2018 | E4: FY 2019 | F4: FY 2020 | G4: FY 2021 | H4: FY 2022 | I4: FY 2023 | J4: FY 2024 | K4: FY 2025 | L4: Last 12M
A5: 12 Months Ending | C5: 12/31/2017 | D5: 12/31/2018 | E5: 12/31/2019 | F5: 12/31/2020 | G5: 12/31/2021 | H5: 12/31/2022 | I5: 12/31/2023 | J5: 12/31/2024 | K5: 12/31/2025 | L5: 12/31/2025
A6: Cash from Operating Activities
A7: + Net Income | B7: CF_NET_INC | C7: 1020 | D7: 3553 | E7: 2083 | F7: 1599 | G7: 1994 | H7: 2358 | I7: 3165 | J7: 2993 | K7: 3246 | L7: 3246
A8: + Depreciation & Amortization | B8: CF_DEPR_AMORT | C8: 642 | D8: 723 | E8: 778 | F8: 812 | G8: 990 | H8: 998 | I8: 1028 | J8: 1050 | K8: 1193 | L8: 1193
A9: + Non-Cash Items | B9: NON_CASH_ITEMS_DETAILED | C9: 90 | D9: -1380 | E9: 399 | F9: 472 | G9: 520 | H9: 386 | I9: -81 | J9: 576 | K9: 508 | L9: 508
A10: + Stock-Based Compensation | B10: CF_STOCK_BASED_COMPENSATION | C10: 113 | D10: 119 | E10: 127 | F10: 142 | G10: 171 | H10: 168 | I10: 205 | J10: 229 | K10: 243 | L10: 243
A11: + Deferred Income Taxes | B11: CF_DEF_INC_TAX | C11: 36 | D11: -1582 | E11: 126 | F11: 48 | G11: -237 | H11: 58 | I11: -206 | J11: -370 | K11: 392 | L11: 392
A12: + Other Non-Cash Adj | B12: OTHER_NON_CASH_ADJ_LESS_DETAILED | C12: -59 | D12: 83 | E12: 146 | F12: 282 | G12: 586 | H12: 160 | I12: -80 | J12: 717 | K12: -127 | L12: -127
A13: + Chg in Non-Cash Work Cap | B13: CF_CHNG_NON_CASH_WORK_CAP | C13: -193 | D13: -286 | E13: -1069 | F13: 394 | G13: -241 | H13: -1118 | I13: -401 | J13: -377 | K13: 97 | L13: 97
A14: + (Inc) Dec in Accts Receiv | B14: CF_ACCT_RCV_UNBILLED_REV | C14: -162 | D14: -60 | E14: -563 | F14: 354 | G14: -377 | H14: -579 | I14: -175 | J14: -321 | K14: 127 | L14: 127
A15: + (Inc) Dec in Inventories | B15: CF_CHANGE_IN_INVENTORIES | C15: -320 | D15: -385 | E15: -400 | F15: 27 | G15: -189 | H15: -762 | I15: -797 | J15: -206 | K15: -297 | L15: -297
A16: + Inc (Dec) in Accts Payable | B16: CF_CHANGE_IN_ACCOUNTS_PAYABLE | C16: 21 | D16: 116 | E16: 63 | F16: 100 | G16: 329 | H16: 290 | I16: 77 | J16: 192 | K16: 94 | L16: 94
A17: + Inc (Dec) in Other | B17: INC_DEC_IN_OT_OP_AST_LIAB_DETAIL | C17: 268 | D17: 43 | E17: -169 | F17: -87 | G17: -4 | H17: -67 | I17: 494 | J17: -42 | K17: 173 | L17: 173
A18: + Net Cash From Disc Ops | B18: CF_NET_CASH_DISCONT_OPS_OPER | C18: 0 | D18: 0 | E18: 0 | F18: 0 | G18: 0 | H18: 0 | I18: 0 | J18: 0 | K18: 0 | L18: 0
A19: Cash from Operating Activities | B19: CF_CASH_FROM_OPER | C19: 1559 | D19: 2610 | E19: 2191 | F19: 3277 | G19: 3263 | H19: 2624 | I19: 3711 | J19: 4242 | K19: 5044 | L19: 5044
A21: Cash from Investing Activities
A22: + Change in Fixed & Intang | B22: FIXED_INTANG_ASST_CHANGE | C22: -598 | D22: -572 | E22: -649 | F22: -487 | G22: -525 | H22: -588 | I22: -575 | J22: -755 | K22: -761 | L22: -761
A23: + Disp in Fixed & Intang | B23: DISPOSAL_OF_FIXED_INTANG | C23: 0 | D23: 0 | E23: 0 | F23: 0 | G23: 0 | H23: 0 | I23: 0 | J23: 0 | K23: 0 | L23: 0
A24: + Disp of Fixed Prod Assets | B24: CF_DISPOSAL_OF_FIXED_PROD_ASSETS | C24: 0 | D24: 0 | E24: 0 | F24: 0 | G24: 0 | H24: 0 | I24: 0 | J24: 0 | K24: 0 | L24: 0
A25: + Disp of Intangible Assets | B25: CF_DISPOSAL_OF_INTANGIBLE_ASSETS | C25: 0 | D25: 0 | E25: 0 | F25: 0 | G25: 0 | H25: 0 | I25: 0 | J25: 0 | K25: 0 | L25: 0
A26: + Acq of Fixed & Intang | B26: ACQUIS_OF_FIXED_INTANG | C26: -598 | D26: -572 | E26: -649 | F26: -487 | G26: -525 | H26: -588 | I26: -575 | J26: -755 | K26: -761 | L26: -761
A27: + Acq of Fixed Prod Assets | B27: CF_PURCHASE_OF_FIXED_PROD_ASSETS | C27: -598 | D27: -572 | E27: -649 | F27: -487 | G27: -525 | H27: -588 | I27: -575 | J27: -755 | K27: -761 | L27: -761
A28: + Acq of Intangible Assets | B28: CF_ACQUISITION_OF_INTANG_ASSETS | C28: 0 | D28: 0 | E28: 0 | F28: 0 | G28: 0 | H28: 0 | I28: 0 | J28: 0 | K28: 0 | L28: 0
A29: + Net Change in LT Investment | B29: NET_CHG_IN_LT_INVEST_DETAILED | C29: 0 | D29: 0 | E29: 0 | F29: 0 | G29: 0 | H29: 0 | I29: 0 | J29: 0 | K29: 0 | L29: 0
A30: + Dec in LT Investment | B30: CF_DECR_INVEST | C30: 0 | D30: 0 | E30: 0 | F30: 0 | G30: 0 | H30: 0 | I30: 0 | J30: 0 | K30: 0 | L30: 0
A31: + Inc in LT Investment | B31: CF_INCR_INVEST | C31: 0 | D31: 0 | E31: 0 | F31: 0 | G31: 0 | H31: 0 | I31: 0 | J31: 0 | K31: 0 | L31: 0
A32: + Net Cash From Acq & Div | B32: CF_NT_CSH_RCVD_PD_FOR_ACQUIS_DIV | C32: -831 | D32: -2451 | E32: -802 | F32: -4222 | G32: -339 | H32: -2563 | I32: -390 | J32: -1628 | K32: -4960 | L32: -4960
A33: + Cash from Divestitures | B33: CF_CASH_FOR_DIVESTITURES | C33: 0 | D33: 0 | E33: 0 | F33: 0 | G33: 0 | H33: 0 | I33: 0 | J33: 0 | K33: 0 | L33: 0
... A38: Cash from Investing Activities | B38: CF_CASH_FROM_INV_ACT | C38: -1613 | D38: -2857 | E38: -1455 | F38: -4701 | G38: -859 | H38: -2924 | I38: -962 | J38: -3000 | K38: -4866 | L38: -4866
A40: Cash from Financing Activities
A41: + Dividends Paid | B41: CF_DVD_PAID | C41: -636 | D41: -703 | E41: -778 | F41: -863 | G41: -950 | H41: -1051 | I41: -1139 | J41: -1219 | K41: -1284 | L41: -1284
A42: + Cash From (Repayment) Debt | B42: PROC_FR_REPAYMNTS_BOR_DETAILED | C42: 299 | D42: 2456 | E42: 1293 | F42: 989 | G42: -1153 | H42: 472 | I42: -277 | J42: 940 | K42: 1579 | L42: 1580
A43: + Cash From (Repay) ST Debt | B43: CF_NET_CHG_ST_DEBT_CPTL_LEAS | C43: -200 | D43: -1 | E43: -7 | F43: -6 | G43: -7 | H43: -375 | I43: 540 | J43: -32 | K43: 0
A44: + Cash From LT Debt | B44: CF_LT_DEBT_CAP_LEAS_PROCEEDS | C44: 499 | D44: 3126 | E44: 2642 | F44: 3292 | G44: 5 | H44: 1500 | I44: 1241 | J44: 3011 | K44: 2979 | L44: 2979
A45: + Repayments of LT Debt | B45: CF_LT_DEBT_CAP_LEAS_PAYMENT | C45: 0 | D45: -669 | E45: -1342 | F45: -2297 | G45: -1151 | H45: -653 | I45: -2058 | J45: -2039 | K45: -1400 | L45: -1400
A46: + Cash (Repurchase) of Equity | B46: PROC_FR_REPURCH_EQTY_DETAILED | C46: -230 | D46: -300 | E46: -307 | F46: 0 | G46: 0 | H46: 0 | I46: 0 | J46: 0 | K46: 0 | L46: 0
A47: + Increase in Capital Stock | B47: CF_INCR_CAP_STOCK | C47: 0 | D47: 0 | E47: 0 | F47: 0 | G47: 0 | H47: 0 | I47: 0 | J47: 0 | K47: 0 | L47: 0
A48: + Decrease in Capital Stock | B48: CF_DECR_CAP_STOCK | C48: -230 | D48: -300 | E48: -307 | F48: 0 | G48: 0 | H48: 0 | I48: 0 | J48: 0 | K48: 0 | L48: 0
A49: + Other Financing Activities | B49: OTHER_FIN_AND_DEC_CAP | C49: -227 | D49: -124 | E49: -205 | F49: -137 | G49: -262 | H49: -170 | I49: -178 | J49: -246 | K49: -182 | L49: -183
A50: + Net Cash From Disc Ops | B50: CF_NET_CASH_DISCONTINUED_OPS_FIN | C50: 0 | D50: 0 | E50: 0 | F50: 0 | G50: 0 | H50: 0 | I50: 0 | J50: 0 | K50: 0 | L50: 0
A51: Cash from Financing Activities | B51: CFF_ACTIVITIES_DETAILED | C51: -794 | D51: 1329 | E51: 3 | F51: -11 | G51: -2365 | H51: -749 | I51: -1594 | J51: -525 | K51: 113 | L51: 113
A53: Effect of Foreign Exchange Rates | B53: CF_EFFECT_FOREIGN_EXCHANGES | C53: 74 | D53: -8 | E53: -18 | F53: 41 | G53: -38 | H53: -51 | I53: -28 | J53: -36 | K53: 68 | L53: 68
A55: Net Changes in Cash | B55: CF_NET_CHNG_CASH | C55: -774 | D55: 1074 | E55: 721 | F55: -1394 | G55: 1 | H55: -1100 | I55: 1127 | J55: 681 | K55: 359 | L55: 359
A57: Cash Paid for Taxes | B57: CF_CASH_PAID_FOR_TAX | C57: 312 | D57: 539 | E57: 286 | F57: 304 | G57: 325 | H57: 324 | I57: 693 | J57: 989 | K57: 1002
A58: Cash Paid for Interest | B58: CF_ACT_CASH_PAID_FOR_INT_DEBT | C58: 231 | D58: 248 | E58: 457 | F58: 323 | G58: 622 | H58: 505 | I58: 356 | J58: 396 | K58: 582
A60: Reference Items
A61: EBITDA | B61: EBITDA | C61: 2939 | D61: 3260 | E61: 3624 | F61: 3165 | G61: 3707 | H61: 3988 | I61: 5088 | J61: 4929 | K61: 6287 | L61: 6287
A62: Trailing 12M EBITDA Margin | B62: EBITDA_MARGIN | C62: 23.6178 | D62: 23.9688 | E62: 24.3483 | F62: 22.0542 | G62: 21.6682 | H62: 21.6163 | I62: 24.8219 | J62: 21.8146 | K62: 25.0319 | L62: 25.031852
A63: Net Cash Paid for Acquisitions | B63: CF_NET_CASH_PAID_FOR_AQUIS | C63: 831 | D63: 2451 | E63: 802 | F63: 4222 | G63: 339 | H63: 2563 | I63: 390 | J63: 1628 | K63: 4960 | L63: 4960
A64: Free Cash Flow | B64: CF_FREE_CASH_FLOW | C64: 961 | D64: 2038 | E64: 1542 | F64: 2790 | G64: 2738 | H64: 2036 | I64: 3136 | J64: 3487 | K64: 4283 | L64: 4283
A65: Free Cash Flow to Firm | B65: CF_FREE_CASH_FLOW_FIRM | C65: 1083.1231 | D65: — | E65: 1775.3415 | F65: 3047.7712 | G65: 3032.598 | H65: 2332.1782 | I65: 3442.7629 | J65: 3826.4124 | K65: 4701.514
A66: Free Cash Flow to Equity | B66: FREE_CASH_FLOW_EQUITY | C66: 1260 | D66: 4494 | E66: 2835 | F66: 3779 | G66: 1585 | H66: 2508 | I66: 2859 | J66: 4427 | K66: 5862 | L66: 5863
A67: Free Cash Flow per Basic Share | B67: FREE_CASH_FLOW_PER_SH | C67: 2.5695 | D67: 5.4477 | E67: 4.123 | F67: 7.4301 | G67: 7.2626 | H67: 5.3834 | I67: 8.2613 | J67: 9.1522 | K67: 11.2062 | L67: 11.200911
A68: Price to Free Cash Flow | B68: PX_TO_FREE_CASH_FLOW | C68: 60.2603 | D68: 28.7734 | E68: 50.9193 | F68: 32.9794 | G68: 36.8215 | H68: 45.4156 | I68: 36.2484 | J68: 39.3401 | K68: 31.364 | L68: 30.710894
A69: Cash Flow to Net Income | B69: CASH_FLOW_TO_NET_INC | C69: 1.5284 | D69: 0.7346 | E69: 1.0518 | F69: 2.0494 | G69: 1.6364 | H69: 1.1128 | I69: 1.1725 | J69: 1.4173 | K69: 1.5539 | L69: 2.5241461
A70: Source: Bloomberg | C70: Right click to show data transparency (not supported for all values)

Sheet Profitability
A2: Stryker Corp (SYK US) - Profitability
A4: In Millions of USD except Per Share | C4: FY 2016 | D4: FY 2017 | E4: FY 2018 | F4: FY 2019 | G4: FY 2020 | H4: FY 2021 | I4: FY 2022 | J4: FY 2023 | K4: FY 2024 | L4: FY 2025
A5: 12 Months Ending | C5: 12/31/2016 | D5: 12/31/2017 | E5: 12/31/2018 | F5: 12/31/2019 | G5: 12/31/2020 | H5: 12/31/2021 | I5: 12/31/2022 | J5: 12/31/2023 | K5: 12/31/2024 | L5: 12/31/2025
A6: Returns
A7: Return on Common Equity | B7: RETURN_COM_EQY | C7: 18.2382 | D7: 10.453 | E7: 32.7526 | F7: 16.9784 | G7: 12.3518 | H7: 14.2627 | I7: 14.9748 | J7: 17.9784 | K7: 15.2599 | L7: 15.0787
A8: Return on Assets | B8: RETURN_ON_ASSET | C8: 8.9858 | D8: 4.7851 | E8: 14.377 | F8: 7.2583 | G8: 4.9584 | H8: 5.783 | I8: 6.5944 | J8: 8.2426 | K8: 7.2222 | L8: 7.1486
A9: Return on Capital | B9: RETURN_ON_CAP | C9: 12.7186 | D9: 6.785 | E9: 19.394 | F9: 10.0989 | G9: 7.17 | H9: 8.279 | I9: 9.165 | J9: 11.158 | K9: 9.9712 | L9: 9.9669
A10: Return on Invested Capital | B10: RETURN_ON_INV_CAPITAL | C10: 13.1115 | D10: 6.8259 | E10: 19.8366 | F10: 10.234 | G10: 7.3768 | H10: 8.5511 | I10: 8.9778 | J10: 11.1124 | K10: 9.7501 | L10: 9.7309
A12: Margins
A13: Gross Margin | B13: GROSS_MARGIN | C13: 66.2605 | D13: 65.7345 | E13: 65.7158 | F13: 65.1438 | G13: 63.1106 | H13: 64.1104 | I13: 62.7568 | J13: 63.7038 | K13: 63.9079 | L13: 63.9632
A14: EBITDA Margin | B14: EBITDA_TO_REVENUE | C14: 24.0265 | D14: 23.6178 | E14: 23.9688 | F14: 24.3483 | G14: 22.0542 | H14: 21.6682 | I14: 21.6163 | J14: 24.8219 | K14: 21.8146 | L14: 25.0319
A15: Operating Margin | B15: OPER_MARGIN | C15: 19.2053 | D15: 18.4587 | E15: 18.653 | F15: 18.2276 | G15: 15.4902 | H15: 15.104 | I15: 15.3992 | J15: 18.9677 | K15: 16.3266 | L15: 19.4657
A16: Incremental Operating Margin | B16: INCREMENTAL_OPERATING_MARGIN | C16: 22.7701 | D16: 10.9026 | E16: 20.7433 | F16: 13.7178 | G16: -91.9325 | H16: 13.0939 | I16: 19.1648 | J16: 51.0981 | K16: — | L16: 47.6002
A17: Pretax Margin | B17: PRETAX_INC_TO_NET_SALES | C17: 16.9625 | D17: 16.5783 | E17: 17.3223 | F17: 17.2131 | G17: 13.6158 | H17: 13.3329 | I17: 14.5428 | J17: 17.9188 | K17: 15.4547 | L17: 17.9726
A18: Income before XO Margin | B18: INC_BEF_XO_ITEMS_TO_NET_SALES | C18: 14.543 | D18: 8.1967 | E18: 26.1231 | F18: 13.9949 | G18: 11.1421 | H18: 11.6554 | I18: 12.7812 | J18: 15.4405 | K18: 13.2463 | L18: 12.924
A19: Net Income Margin | B19: PROF_MARGIN | C19: 14.543 | D19: 8.1967 | E19: 26.1231 | F19: 13.9949 | G19: 11.1421 | H19: 11.6554 | I19: 12.7812 | J19: 15.4405 | K19: 13.2463 | L19: 12.924
A20: Net Income to Common Margin | B20: NET_INCOME_TO_COMMON_MARGIN | C20: 14.543 | D20: 8.1967 | E20: 26.1231 | F20: 13.9949 | G20: 11.1421 | H20: 11.6554 | I20: 12.7812 | J20: 15.4405 | K20: 13.2463 | L20: 12.924
A22: Additional
A23: Effective Tax Rate | B23: EFF_TAX_RATE | C23: 14.2634 | D23: 50.5574 | E23: — | F23: 18.6963 | G23: 18.1679 | H23: 12.5822 | I23: 12.1133 | J23: 13.8307 | K23: 14.2898 | L23: 28.0904
A24: Dvd Payout Ratio | B24: DVD_PAYOUT_RATIO | C24: 34.4869 | D24: 62.3529 | E24: 19.7861 | F24: 37.35 | G24: 53.9712 | H24: 47.6429 | I24: 44.5717 | J24: 35.9874 | K24: 40.7284 | L24: 39.5564
A25: Sustainable Growth Rate | B25: SUSTAIN_GROWTH_RT | C25: 11.9484 | D25: 3.9352 | E25: 26.2721 | F25: 10.637 | G25: 5.6854 | H25: 7.4675 | I25: 8.3003 | J25: 11.5084 | K25: 9.0448 | L25: 9.1141
A26: Source: Bloomberg | C26: Right click to show data transparency (not supported for all values)

Sheet Segments
A1: SYK US Equity- Company Financial (Multiple Periods)
A2: SYK US Equity Periodicity:A Currency:USD Estimate Source:BST Actual Source:Bloomberg
A3: In Millions of USD | E3: FY 2019 | F3: FY 2020 | G3: FY 2021 | H3: FY 2022 | I3: FY 2023 | J3: FY 2024 | K3: FY 2025 | L3: Current/LTM | M3: FY 2026 Est | N3: FY 2027 Est
A4: 12 Months Ending | B4: Field Expression | C4: Calcrt Field | D4: Segment Id | E4: {=BQL("SYK US Equity", "IS_COMP_SALES().period_end_date", "FPT=A", "FPO=-7A", "FA_ACT_EST_DATA=AAE", "ACT_EST_MAPPING=PRECISE", "FS=MRC", "CURRENCY=USD", "XLFILL=b")} -> #NAME? | F4: {=_xll.BQL("SYK US Equity", "IS_COMP_SALES().period_end_date", "FPT=A", "FPO=-6A", "FA_ACT_EST_DATA=AAE", "ACT_EST_MAPPING=PRECISE", "FS=MRC", "CURRENCY=USD", "XLFILL=b")} -> #NAME? | G4: {=_xll.BQL("SYK US Equity", "IS_COMP_SALES().period_end_date", "FPT=A", "FPO=-5A", "FA_ACT_EST_DATA=AAE", "ACT_EST_MAPPING=PRECISE", "FS=MRC", "CURRENCY=USD", "XLFILL=b")} -> #NAME? | H4: {=_xll.BQL("SYK US Equity", "IS_COMP_SALES().period_end_date", "FPT=A", "FPO=-4A", "FA_ACT_EST_DATA=AAE", "ACT_EST_MAPPING=PRECISE", "FS=MRC", "CURRENCY=USD", "XLFILL=b")} -> #NAME? | I4: {=_xll.BQL("SYK US Equity", "IS_COMP_SALES().period_end_date", "FPT=A", "FPO=-3A", "FA_ACT_EST_DATA=AAE", "ACT_EST_MAPPING=PRECISE", "FS=MRC", "CURRENCY=USD", "XLFILL=b")} -> #NAME? | J4: {=_xll.BQL("SYK US Equity", "IS_COMP_SALES().period_end_date", "FPT=A", "FPO=-2A", "FA_ACT_EST_DATA=AAE", "ACT_EST_MAPPING=PRECISE", "FS=MRC", "CURRENCY=USD", "XLFILL=b")} -> #NAME? | K4: {=_xll.BQL("SYK US Equity", "IS_COMP_SALES().period_end_date", "FPT=A", "FPO=-1A", "FA_ACT_EST_DATA=AAE", "ACT_EST_MAPPING=PRECISE", "FS=MRC", "CURRENCY=USD", "XLFILL=b")} -> #NAME? | L4: {=_xll.BQL("SYK US Equity", "IS_COMP_SALES().period_end_date", "FPT=A", "FPO=0A", "FA_ACT_EST_DATA=AAE", "ACT_EST_MAPPING=PRECISE", "FS=MRC", "CURRENCY=USD", "XLFILL=b")} -> #NAME? | M4: {=_xll.BQL("SYK US Equity", "IS_COMP_SALES().period_end_date", "FPT=A", "FPO=1A", "FA_ACT_EST_DATA=AAE", "ACT_EST_MAPPING=PRECISE", "FS=MRC", "CURRENCY=USD", "XLFILL=b")} -> #NAME? | N4: {=_xll.BQL("SYK US Equity", "IS_COMP_SALES().period_end_date", "FPT=A", "FPO=2A", "FA_ACT_EST_DATA=AAE", "ACT_EST_MAPPING=PRECISE", "FS=MRC", "CURRENCY=USD", "XLFILL=b")} -> #NAME?
A5: Revenue | B5: SALES_REV_TURN | C5: IS010 | E5: 13601 | F5: 14884 | G5: 14351 | H5: 17108 | I5: 18449 | J5: 20498 | K5: 22595 | L5: 25116
A6: MedSurg & Neurotechnology | B6: SALES_REV_TURN | C6: IS010 | D6: SEG0000608020 Segment | E6: 6073.44 | F6: 8475 | G6: 8345 | H6: 9538 | I6: 10893 | J6: 12163 | K6: 13518 | L6: 15647 | M6: 17286.229 | N6: 18832.269
A7: % of Total | B7: SALES_REV_TURN | C7: IS010 | D7: SEG0000608020 Segment | E7: 44.654364 | F7: 56.940339 | G7: 58.149258 | H7: 55.751695 | I7: 59.043851 | J7: 59.337496 | K7: 59.827395 | L7: 62.298933
A8: Instruments | B8: SALES_REV_TURN | C8: IS010 | D8: SEG0000173634 Segment | E8: 1822 | F8: 1959 | G8: 1863 | H8: 2111 | I8: 2245 | J8: 2534 | K8: 2834 | L8: 3183 | M8: 3495.7616 | N8: 3793.802
A9: % of Total | B9: SALES_REV_TURN | C9: IS010 | D9: SEG0000173634 Segment | E9: 13.396074 | F9: 13.161784 | G9: 12.981674 | H9: 12.339256 | I9: 12.168681 | J9: 12.362182 | K9: 12.542598 | L9: 12.673196
A10: Endoscopy | B10: SALES_REV_TURN | C10: IS010 | D10: SEG0000173697 Segment | E10: 1846 | F10: 1983 | G10: 1763 | H10: 2141 | I10: 2759 | J10: 3068 | K10: 3389 | L10: 3807 | M10: 4150.4048 | N10: 4500.8534
A11: % of Total | B11: SALES_REV_TURN | C11: IS010 | D11: SEG0000173697 Segment | E11: 13.572531 | F11: 13.323031 | G11: 12.284858 | H11: 12.514613 | I11: 14.95474 | J11: 14.967314 | K11: 14.998894 | L11: 15.157668
A12: Medical | B12: SALES_REV_TURN | C12: IS010 | D12: SEG0000173720 Segment | E12: 2118 | F12: 2264 | G12: 2524 | H12: 2607 | I12: 3031 | J12: 3459 | K12: 3852 | L12: 4204 | M12: 4608.0365 | N12: 5010.7174
A13: % of Total | B13: SALES_REV_TURN | C13: IS010 | D13: SEG0000173720 Segment | E13: 15.572384 | F13: 15.210965 | G13: 17.587625 | H13: 15.238485 | I13: 16.429075 | J13: 16.874817 | K13: 17.048019 | L13: 16.738334
A14: Vascular | B14: SALES_REV_TURN | C14: IS010 | D14: SEG0000608022 Segment | F14: 924 | G14: 973 | H14: 1188 | I14: 1200 | J14: 1226 | K14: 1307 | L14: 1968 | M14: 2272.8781 | N14: 2504.0858
A15: % of Total | B15: SALES_REV_TURN | C15: IS010 | D15: SEG0000608022 Segment | F15: 6.2080086 | G15: 6.7800153 | H15: 6.9441197 | I15: 6.5044176 | J15: 5.9810713 | K15: 5.7844656 | L15: 7.8356426
A16: Neuro Cranial | B16: SALES_REV_TURN | C16: IS010 | D16: SEG0000608023 Segment | F16: 1059 | G16: 972 | H16: 1214 | I16: 1658 | J16: 1876 | K16: 2136 | L16: 2485 | M16: 2766.9682 | N16: 3036.3739
A17: % of Total | B17: SALES_REV_TURN | C17: IS010 | D17: SEG0000608023 Segment | F17: 7.1150228 | G17: 6.7730472 | H17: 7.0960954 | I17: 8.986937 | J17: 9.1521124 | K17: 9.4534189 | L17: 9.8940914
A18: Other | B18: SALES_REV_TURN | C18: IS010 | D18: SEG0000608251 Segment | E18: 270.94104 | F18: 286 | G18: 250 | H18: 277 | I18: 302 | J18: 308.27105 | K18: 334.41477 | L18: 423.52647 | M18: 535.55856 | N18: 549.22929
A19: % of Total | B19: SALES_REV_TURN | C19: IS010 | D19: SEG0000608251 Segment | E19: 1.9920671 | F19: 1.9215265 | G19: 1.7420389 | H19: 1.6191256 | I19: 1.6369451 | J19: 1.503908 | K19: 1.4800388 | L19: 1.6862815
A20: Orthopaedics | B20: SALES_REV_TURN | C20: IS010 | D20: SEG0000608032 Segment | F20: 6409 | G20: 6006 | H20: 7570 | I20: 7556 | J20: 8335 | K20: 9077 | L20: 9469 | M20: 10037.248 | N20: 10760.333
A21: % of Total | B21: SALES_REV_TURN | C21: IS010 | D21: SEG0000608032 Segment | F21: 43.059661 | G21: 41.850742 | H21: 44.248305 | I21: 40.956149 | J21: 40.662504 | K21: 40.172605 | L21: 37.701067
A22: Knees | B22: SALES_REV_TURN | C22: IS010 | D22: SEG0000173641 Segment | E22: 1701 | F22: 1815 | G22: 1567 | H22: 1848 | I22: 1997 | J22: 2273 | K22: 2447 | L22: 2656 | M22: 2840.0502 | N22: 3019.2977
A23: % of Total | B23: SALES_REV_TURN | C23: IS010 | D23: SEG0000173641 Segment | E23: 12.506433 | F23: 12.194303 | G23: 10.9191 | H23: 10.801964 | I23: 10.824435 | J23: 11.088887 | K23: 10.82983 | L23: 10.574932
A24: Hips | B24: SALES_REV_TURN | C24: IS010 | D24: SEG0000173657 Segment | E24: 1336 | F24: 1383 | G24: 1206 | H24: 1342 | I24: 1413 | J24: 1544 | K24: 1704 | L24: 1865 | M24: 1989.2873 | N24: 2109.6078
A25: % of Total | B25: SALES_REV_TURN | C25: IS010 | D25: SEG0000173657 Segment | E25: 9.8228071 | F25: 9.291857 | G25: 8.4035956 | H25: 7.8442834 | I25: 7.6589517 | J25: 7.5324422 | K25: 7.5414915 | L25: 7.4255455
A26: Trauma & Extremities | B26: SALES_REV_TURN | C26: IS010 | D26: SEG0000173644 Segment | E26: 1580 | F26: 1639 | G26: 1722 | H26: 2664 | I26: 2807 | J26: 3147 | K26: 3507 | L26: 3948 | M26: 4316.7664 | N26: 4671.0017
A27: % of Total | B27: SALES_REV_TURN | C27: IS010 | D27: SEG0000173644 Segment | E27: 11.616793 | F27: 11.011825 | G27: 11.999164 | H27: 15.571662 | I27: 15.214917 | J27: 15.352717 | K27: 15.521133 | L27: 15.719064
A28: Spinal Implants | B28: SALES_REV_TURN | C28: IS010 | D28: SEG4388955483 Segment | H28: 1171.5608 | I28: 733 | J28: 713 | K28: 707 | L28: 185 | M28: 24
A29: % of Total | B29: SALES_REV_TURN | C29: IS010 | D29: SEG4388955483 Segment | H29: 6.8480287 | I29: 3.9731151 | J29: 3.4783881 | K29: 3.1290108 | L29: 0.73658226
A30: Other | B30: SALES_REV_TURN | C30: IS010 | D30: SEG0000608256 Segment | E30: 374 | F30: 415 | G30: 464 | H30: 549 | I30: 606 | J30: 658 | K30: 712 | L30: 815 | M30: 873.14515 | N30: 938.39743
A31: % of Total | B31: SALES_REV_TURN | C31: IS010 | D31: SEG0000608256 Segment | E31: 2.7497978 | F31: 2.788229 | G31: 3.2332242 | H31: 3.209025 | I31: 3.2847309 | J31: 3.2100693 | K31: 3.1511396 | L31: 3.2449435
A32: Adjustment | B32: SALES_REV_TURN | C32: IS010 | D32: SEG1498846643 Segment
A33: % of Total | B33: SALES_REV_TURN | C33: IS010 | D33: SEG1498846643 Segment
A34: Spine | B34: SALES_REV_TURN | C34: IS010 | D34: SEG0000173732 Segment | E34: 828 | F34: 1157 | G34: 1047 | H34: 1167 | I34: 1146 | J34: 1189 | K34: 1097 | L34: 269.34232 | M34: 280.16787 | N34: 1097.3092
A35: % of Total | B35: SALES_REV_TURN | C35: IS010 | D35: SEG0000173732 Segment | E35: 6.0877877 | F35: 7.773448 | G35: 7.2956588 | H35: 6.8213701 | I35: 6.2117188 | J35: 5.8005659 | K35: 4.8550564 | L35: 1.0723934
A36: Inactive Segments
A37: Orthopedic Implants | B37: SALES_REV_TURN | C37: IS010 | D37: SEG0000173654 Segment
A38: Neurotechnology | B38: SALES_REV_TURN | C38: IS010 | D38: SEG0000173705 Segment | E38: 1737 | F38: 1983 | G38: 1945
A39: Neurotechnology & Spine | B39: SALES_REV_TURN | C39: IS010 | D39: SEG0000173648 Segment | E39: 2565 | F39: 3140 | G39: 2992
A40: Corporate & Other | B40: SALES_REV_TURN | C40: IS010 | D40: SEG0000173709 Segment
A41: Physical Therapy Services | B41: SALES_REV_TURN | C41: IS010 | D41: SEG0000331771 Segment
A42: Sustainability | B42: SALES_REV_TURN | C42: IS010 | D42: SEG0000173661 Segment | E42: 259 | F42: 286 | G42: 250 | H42: 277 | I42: 295.454 | J42: 311.47462 | K42: 285.84418
A43: Orthopaedics | B43: SALES_REV_TURN | C43: IS010 | D43: SEG0000173667 Segment | E43: 4991 | F43: 5252 | G43: 4959 | H43: 7570
A44: MedSurg | B44: SALES_REV_TURN | C44: IS010 | D44: SEG0000173699 Segment | E44: 6045 | F44: 6492 | G44: 6400 | H44: 9538
A46: 1 Yr Revenue Growth: Constant Currency | B46: REVENUE_GROWTH_CC_1_YR | C46: M0025 | E46: 9 | F46: 10.7 | G46: 3.6 | H46: 18.1 | I46: 11 | J46: 11.6 | K46: 10.7
A47: MedSurg & Neurotechnology | B47: REVENUE_GROWTH_CC_1_YR | C47: M0025 | D47: SEG0000608020 Segment | E47: 8.3814947 | F47: 9.9681393 | G47: -1.5 | H47: 13.3 | I47: 14.1 | J47: 12.2 | K47: 11.6 | L47: 15.4 | M47: 10.372364 | N47: 8.8298462
A48: % of Total | B48: REVENUE_GROWTH_CC_1_YR | C48: M0025 | D48: SEG0000608020 Segment | E48: 93.127719 | F48: 93.16018 | G48: -41.666667 | H48: 73.480663 | I48: 128.18182 | J48: 105.17241 | K48: 108.41121
A49: Instruments | B49: REVENUE_GROWTH_CC_1_YR | C49: M0025 | D49: SEG0000173634 Segment | E49: 8.4 | F49: 13.1 | G49: -5 | H49: 12.5 | I49: 10.4 | J49: 13 | K49: 12.1 | L49: 11.9 | M49: 9.5434233 | N49: 8.5851084
A50: % of Total | B50: REVENUE_GROWTH_CC_1_YR | C50: M0025 | D50: SEG0000173634 Segment | E50: 93.333333 | F50: 122.42991 | G50: -138.88889 | H50: 69.060773 | I50: 94.545455 | J50: 112.06897 | K50: 113.08411
A51: Endoscopy | B51: REVENUE_GROWTH_CC_1_YR | C51: M0025 | D51: SEG0000173697 Segment | E51: 11.9 | F51: 8.6 | G51: -11 | H51: 20.8 | I51: 15.9 | J51: 11.7 | K51: 11 | L51: 12.3 | M51: 9.3885851 | N51: 8.5840938
A52: % of Total | B52: REVENUE_GROWTH_CC_1_YR | C52: M0025 | D52: SEG0000173697 Segment | E52: 132.22222 | F52: 80.373832 | G52: -305.55556 | H52: 114.91713 | I52: 144.54545 | J52: 100.86207 | K52: 102.80374
A53: Medical | B53: REVENUE_GROWTH_CC_1_YR | C53: M0025 | D53: SEG0000173720 Segment | E53: 7.5 | F53: 8.1 | G53: 11.8 | H53: 2.2 | I53: 18.6 | J53: 14.4 | K53: 11.7 | L53: 8.8 | M53: 9.5037762 | N53: 8.8672095
A54: % of Total | B54: REVENUE_GROWTH_CC_1_YR | C54: M0025 | D54: SEG0000173720 Segment | E54: 83.333333 | F54: 75.700935 | G54: 327.77778 | H54: 12.154696 | I54: 169.09091 | J54: 124.13793 | K54: 109.34579
A55: Vascular | B55: REVENUE_GROWTH_CC_1_YR | C55: M0025 | D55: SEG0000608022 Segment | E55: 22.389075 | F55: 13.11663 | G55: 4.9 | H55: 19.5 | I55: 7.2 | J55: 4 | K55: 8.2 | L55: 50 | M55: 13.881297 | N55: 8.8941092
A56: % of Total | B56: REVENUE_GROWTH_CC_1_YR | C56: M0025 | D56: SEG0000608022 Segment | E56: 248.76751 | F56: 122.58532 | G56: 136.11111 | H56: 107.73481 | I56: 65.454545 | J56: 34.482759 | K56: 76.635514
A57: Neuro Cranial | B57: REVENUE_GROWTH_CC_1_YR | C57: M0025 | D57: SEG0000608023 Segment | G57: -8.3 | H57: 24.3 | I57: 15.4 | J57: 13.4 | K57: 14.1 | L57: 15.9 | M57: 10.658548 | N57: 9.2600709
A58: % of Total | B58: REVENUE_GROWTH_CC_1_YR | C58: M0025 | D58: SEG0000608023 Segment | G58: -230.55556 | H58: 134.25414 | I58: 140 | J58: 115.51724 | K58: 131.7757
A59: Other | B59: REVENUE_GROWTH_CC_1_YR | C59: M0025 | D59: SEG0000608251 Segment | E59: 3.1528962 | F59: 10.229299 | G59: -12.3 | H59: 10.3 | I59: 9.3 | K59: 30.049562
A60: % of Total | B60: REVENUE_GROWTH_CC_1_YR | C60: M0025 | D60: SEG0000608251 Segment | E60: 35.03218 | F60: 95.600928 | G60: -341.66667 | H60: 56.906077 | I60: 84.545455 | K60: 280.83703
A61: Orthopaedics | B61: REVENUE_GROWTH_CC_1_YR | C61: M0025 | D61: SEG0000608032 Segment | E61: 5.0590473 | F61: 6.4299317 | G61: -6.4 | H61: 24.8 | I61: 7 | J61: 10.9 | K61: 9.4 | L61: 3.8 | M61: 6.2311649 | N61: 7.6879715
A62: % of Total | B62: REVENUE_GROWTH_CC_1_YR | C62: M0025 | D62: SEG0000608032 Segment | E62: 56.211637 | F62: 60.092819 | G62: -177.77778 | H62: 137.01657 | I62: 63.636364 | J62: 93.965517 | K62: 87.850467
A63: Knees | B63: REVENUE_GROWTH_CC_1_YR | C63: M0025 | D63: SEG0000173641 Segment | E63: 6.3 | F63: 8.1 | G63: -13.7 | H63: 16.9 | I63: 11.2 | J63: 14.4 | K63: 8.2 | L63: 8.2 | M63: 6.9176037 | N63: 6.1508638
A64: % of Total | B64: REVENUE_GROWTH_CC_1_YR | C64: M0025 | D64: SEG0000173641 Segment | E64: 70 | F64: 75.700935 | G64: -380.55556 | H64: 93.370166 | I64: 101.81818 | J64: 124.13793 | K64: 76.635514
A65: Hips | B65: REVENUE_GROWTH_CC_1_YR | C65: M0025 | D65: SEG0000173657 Segment | E65: 2.1 | F65: 5.2 | G65: -12.7 | H65: 9.9 | I65: 10.1 | J65: 10.4 | K65: 11.3 | L65: 8.9 | M65: 6.674145 | N65: 6.1965386
A66: % of Total | B66: REVENUE_GROWTH_CC_1_YR | C66: M0025 | D66: SEG0000173657 Segment | E66: 23.333333 | F66: 48.598131 | G66: -352.77778 | H66: 54.696133 | I66: 91.818182 | J66: 89.655172 | K66: 105.60748
A67: Trauma & Extremities | B67: REVENUE_GROWTH_CC_1_YR | C67: M0025 | D67: SEG0000173644 Segment | E67: 6.2 | F67: 5.2 | G67: 4.7 | H67: 53 | I67: 8.7 | J67: 12.2 | K67: 11.6 | L67: 11.8 | M67: 8.8134107 | N67: 8.3396247
A68: % of Total | B68: REVENUE_GROWTH_CC_1_YR | C68: M0025 | D68: SEG0000173644 Segment | E68: 68.888889 | F68: 48.598131 | G68: 130.55556 | H68: 292.81768 | I68: 79.090909 | J68: 105.17241 | K68: 108.41121
A69: Spinal Implants | B69: REVENUE_GROWTH_CC_1_YR | C69: M0025 | D69: SEG4388955483 Segment | J69: -2 | K69: -0.3 | L69: -73.9
A70: % of Total | B70: REVENUE_GROWTH_CC_1_YR | C70: M0025 | D70: SEG4388955483 Segment | J70: -17.241379 | K70: -2.8037383
A71: Other | B71: REVENUE_GROWTH_CC_1_YR | C71: M0025 | D71: SEG0000608256 Segment | E71: 11 | F71: 12 | G71: 11.4 | H71: 18 | I71: -10.3 | J71: 9.5 | K71: 9.6 | L71: 14 | M71: 8.2378766 | N71: 7.8160895
A72: % of Total | B72: REVENUE_GROWTH_CC_1_YR | C72: M0025 | D72: SEG0000608256 Segment | E72: 122.22222 | F72: 112.14953 | G72: 316.66667 | H72: 99.447514 | I72: -93.636364 | J72: 81.896552 | K72: 89.719626
A73: Spine | B73: REVENUE_GROWTH_CC_1_YR | C73: M0025 | D73: SEG0000173732 Segment | E73: 9.9 | F73: 32.3 | G73: -9.6 | H73: 10.5 | I73: 1.1 | J73: 4 | K73: 4.7453619 | L73: -57.770162 | M73: -99.99477
A74: % of Total | B74: REVENUE_GROWTH_CC_1_YR | C74: M0025 | D74: SEG0000173732 Segment | E74: 110 | F74: 301.86916 | G74: -266.66667 | H74: 58.01105 | I74: 10 | J74: 34.482759 | K74: 44.349176
A75: Inactive Segments
A76: Orthopedic Implants | B76: REVENUE_GROWTH_CC_1_YR | C76: M0025 | D76: SEG0000173654 Segment
A77: Neurotechnology | B77: REVENUE_GROWTH_CC_1_YR | C77: M0025 | D77: SEG0000173705 Segment | E77: 21.4 | F77: 14.9 | G77: -2.1
A78: Neurotechnology & Spine | B78: REVENUE_GROWTH_CC_1_YR | C78: M0025 | D78: SEG0000173648 Segment | E78: 17.4 | F78: 20.5 | G78: -4.9
A79: Trauma | B79: REVENUE_GROWTH_CC_1_YR | C79: M0025 | D79: SEG0000173682 Segment
A80: Corporate & Other | B80: REVENUE_GROWTH_CC_1_YR | C80: M0025 | D80: SEG0000173709 Segment | E80: 11
A81: Craniomaxillofacial | B81: REVENUE_GROWTH_CC_1_YR | C81: M0025 | D81: SEG0000173633 Segment
A82: Sustainability | B82: REVENUE_GROWTH_CC_1_YR | C82: M0025 | D82: SEG0000173661 Segment | E82: 0.1 | F82: 10.4 | G82: -12.3
A83: Orthopaedics | B83: REVENUE_GROWTH_CC_1_YR | C83: M0025 | D83: SEG0000173667 Segment | E83: 5.4 | F83: 6.7 | G83: -5.7
A84: Micro Implant | B84: REVENUE_GROWTH_CC_1_YR | C84: M0025 | D84: SEG0000173726 Segment
A85: MedSurg | B85: REVENUE_GROWTH_CC_1_YR | C85: M0025 | D85: SEG0000173699 Segment | E85: 8.7 | F85: 9.9 | G85: -1.3
A87: Organic Growth Rate | B87: IS_ORGANIC_GROWTH_RATE | C87: IS950 | E87: 7.9 | F87: 8.1 | G87: -4.8 | H87: 12.6 | I87: 9.7 | J87: 11.5 | K87: 10.2 | L87: 10.3 | M87: 8.5920806 | N87: 8.2693969
A88: MedSurg & Neurotechnology | B88: IS_ORGANIC_GROWTH_RATE | C88: IS950 | D88: SEG0000608020 Segment | E88: 7.2593149 | F88: 9.4006154 | G88: -1.3682994 | H88: 13.1 | I88: 11.8 | J88: 11.8 | K88: 11.2 | L88: 10.7 | M88: 8.902267 | N88: 9.1432523
A89: % of Total | B89: IS_ORGANIC_GROWTH_RATE | C89: IS950 | D89: SEG0000608020 Segment | E89: 91.890062 | F89: 116.05698 | G89: 28.506238 | H89: 103.96825 | I89: 121.64948 | J89: 102.6087 | K89: 109.80392 | L89: 103.8835 | M89: 103.61014 | N89: 110.56734
A90: Orthopaedics | B90: IS_ORGANIC_GROWTH_RATE | C90: IS950 | D90: SEG0000608032 Segment | E90: 5.281335 | F90: 6.4222788 | G90: -4.4268881 | H90: 12 | I90: 7 | J90: 11.1 | K90: 8.7 | L90: 9.5 | M90: 7.631669 | N90: 7.5633887
A91: % of Total | B91: IS_ORGANIC_GROWTH_RATE | C91: IS950 | D91: SEG0000608032 Segment | E91: 66.852342 | F91: 79.287392 | G91: 92.226835 | H91: 95.238095 | I91: 72.164948 | J91: 96.521739 | K91: 85.294118 | L91: 92.23301 | M91: 88.82213 | N91: 91.462398
A92: Inactive Segments
A93: Neurotechnology & Spine | B93: IS_ORGANIC_GROWTH_RATE | C93: IS950 | D93: SEG0000173648 Segment | E93: 10.6 | F93: 8.9 | G93: -5.7
A94: Orthopaedics | B94: IS_ORGANIC_GROWTH_RATE | C94: IS950 | D94: SEG0000173667 Segment | E94: 5.9 | F94: 6.7 | G94: -8.1
A95: MedSurg | B95: IS_ORGANIC_GROWTH_RATE | C95: IS950 | D95: SEG0000173699 Segment | E95: 8.6 | F95: 8.9 | G95: -1.8
A97: Volume and Mix Change Percentage | B97: VOLUME_AND_MIX_CHANGE_PERCENTAGE | C97: M6098
A98: MedSurg & Neurotechnology | B98: VOLUME_AND_MIX_CHANGE_PERCENTAGE | C98: M6098 | D98: SEG0000608020 Segment | G98: 5.7 | H98: 11.9 | I98: 11.2 | J98: 10.2 | K98: 9.5 | L98: 10
A99: % of Total | B99: VOLUME_AND_MIX_CHANGE_PERCENTAGE | C99: M6098 | D99: SEG0000608020 Segment
A100: Orthopaedics | B100: VOLUME_AND_MIX_CHANGE_PERCENTAGE | C100: M6098 | D100: SEG0000608032 Segment | G100: 6.6 | H100: 4.4 | I100: 9.9 | J100: 11.9 | K100: 8.7 | L100: 9.6
A101: % of Total | B101: VOLUME_AND_MIX_CHANGE_PERCENTAGE | C101: M6098 | D101: SEG0000608032 Segment
A102: Inactive Segments
A103: Neurotechnology & Spine | B103: VOLUME_AND_MIX_CHANGE_PERCENTAGE | C103: M6098 | D103: SEG0000173648 Segment
...

Sheet JNJ
A1: JNJ US Equity- Company Financial (Multiple Periods)
A2: JNJ US Equity Periodicity:A Currency:USD Estimate Source:BST Actual Source:Bloomberg
A3: In Millions of USD | E3: 2018 A (Rep) | F3: 2019 A (Rep) | G3: 2020 A (Rep) | H3: 2021 A (Rep) | I3: 2022 A (Rep) | J3: 2023 A (Rep) | K3: 2024 A (Rep) | L3: 2025 A (Rep) | M3: 2026 A (Fwd) | N3: 2027 A (Fwd)
A4: 12 Months Ending | B4: Field Expression | C4: Calcrt Field | D4: Segment Id | E4: 43464 | F4: 43828 | G4: 44199 | H4: 44563 | I4: 44927 | J4: 45291 | K4: 45655 | L4: 46019 | M4: 46390 | N4: 46754
A5: Highlights
A6: Adjusted Diluted EPS | B6: IS_COMP_EPS_ADJUSTED_OLD | C6: IS900 | E6: 8.18 | F6: 8.68 | G6: 8.03 | H6: 9.8 | I6: 10.15 | J6: 9.92 | K6: 9.98 | L6: 10.79 | M6: 11.572692 | N6: 12.550769
A7: Revenue | B7: IS_COMP_SALES | C7: IS902 | E7: 81581 | F7: 82059 | G7: 82584 | H7: 93775 | I7: 94943 | J7: 85159 | K7: 88821 | L7: 94193 | M7: 100625.6 | N7: 106508.4
A9: Segment Revenue
A10: Innovative Medicine | B10: SALES_REV_TURN | C10: IS010 | D10: SEG0000336691 Segment | E10: 40734 | F10: 42201 | G10: 45980 | H10: 51680 | I10: 52563 | J10: 54759 | K10: 56964 | L10: 60401 | M10: 64940.384 | N10: 68893.776
A11: Darzalex | B11: SALES_REV_TURN | C11: IS010 | D11: SEG0000336459 Segment | E11: 2025 | F11: 2998 | G11: 4190 | H11: 6023 | I11: 7977 | J11: 9744 | K11: 11670 | L11: 14351 | M11: 16858.919 | N11: 18794.842
A12: Tremfya | B12: SALES_REV_TURN | C12: IS010 | D12: SEG0000336538 Segment | E12: 544 | F12: 1012 | G12: 1347 | H12: 2127 | I12: 2668 | J12: 3147 | K12: 3670 | L12: 5155 | M12: 7046.4612 | N12: 8549.9211
A13: Erleada | B13: SALES_REV_TURN | C13: IS010 | D13: SEG0000387621 Segment | F13: 332 | G13: 760 | H13: 1291 | I13: 1881 | J13: 2387 | K13: 2999 | L13: 3574 | M13: 4132.7085 | N13: 4551.9887
A14: Stelara | B14: SALES_REV_TURN | C14: IS010 | D14: SEG0000336802 Segment | E14: 5156 | F14: 6361 | G14: 7707 | H14: 9134 | I14: 9723 | J14: 10858 | K14: 10361 | L14: 6078 | M14: 3725.3115 | N14: 2559.521
A15: Invega Sustenna | B15: SALES_REV_TURN | C15: IS010 | D15: SEG0000336548 Segment | E15: 2928 | F15: 3330 | G15: 3653 | H15: 4022 | I15: 4140 | J15: 4115 | K15: 4222 | L15: 3810 | M15: 3683.0141 | N15: 3637.5111
A16: Carvykti | B16: SALES_REV_TURN | C16: IS010 | D16: SEG0000863947 Segment | I16: 133 | J16: 500 | K16: 963 | L16: 1887 | M16: 2836.895 | N16: 3860.1775
A17: Spravato | B17: SALES_REV_TURN | C17: IS010 | D17: SEG0001304378 Segment | I17: 374 | J17: 689 | K17: 1077 | L17: 1696 | M17: 2327.8252 | N17: 2843.9743
A18: Rybrevant + Lazcluze | B18: SALES_REV_TURN | C18: IS010 | D18: SEG0001470832 Segment | K18: 327 | L18: 734 | M18: 1332.0873 | N18: 2103.4452
A19: Simponi | B19: SALES_REV_TURN | C19: IS010 | D19: SEG0000336550 Segment | E19: 2084 | F19: 2188 | G19: 2243 | H19: 2276 | I19: 2184 | J19: 2197 | K19: 2190 | L19: 2668 | M19: 2354.6298 | N19: 1921.6869
A20: Imbruvica | B20: SALES_REV_TURN | C20: IS010 | D20: SEG0000336546 Segment | E20: 2615 | F20: 3411 | G20: 4128 | H20: 4369 | I20: 3784 | J20: 3264 | K20: 3038 | L20: 2823 | M20: 2516.0227 | N20: 2212.7408
A21: Xarelto | B21: SALES_REV_TURN | C21: IS010 | D21: SEG0000336576 Segment | E21: 2477 | F21: 2313 | G21: 2345 | H21: 2438 | I21: 2473 | J21: 2365 | K21: 2373 | L21: 2633 | M21: 2458.1552 | N21: 1725.9712
A22: Remicade | B22: SALES_REV_TURN | C22: IS010 | D22: SEG0000336784 Segment | E22: 5326 | F22: 4384 | G22: 3747 | H22: 3190 | I22: 2343 | J22: 1839 | K22: 1605 | L22: 1768 | M22: 1564.6362 | N22: 1376.6295
A23: Opsumit | B23: SALES_REV_TURN | C23: IS010 | D23: SEG0000336686 Segment | E23: 1215 | F23: 1327 | G23: 1639 | H23: 1819 | I23: 1783 | J23: 1973 | K23: 2184 | L23: 2325 | M23: 1924.9932 | N23: 1309.1742
A24: Uptravi | B24: SALES_REV_TURN | C24: IS010 | D24: SEG0000336405 Segment | E24: 663 | F24: 819 | G24: 1093 | H24: 1237 | I24: 1322 | J24: 1582 | K24: 1817 | L24: 1902 | M24: 1859.6777 | N24: 1501.6414
A25: Caplyta | B25: SALES_REV_TURN | C25: IS010 | D25: SEG4822019841 Segment | L25: 700 | M25: 1265.4184 | N25: 1824.5477
A26: Tecvayli (teclistamab-cqyv) | B26: SALES_REV_TURN | C26: IS010 | D26: SEG0000662377 Segment | K26: 549 | L26: 670 | M26: 996.82541 | N26: 1489.7052
A27: Talvey (talquetamab) | B27: SALES_REV_TURN | C27: IS010 | D27: SEG0000461849 Segment | K27: 287 | L27: 463 | M27: 745.37032 | N27: 1071.613
A28: Zytiga | B28: SALES_REV_TURN | C28: IS010 | D28: SEG0000336424 Segment | E28: 3498 | F28: 2795 | G28: 2470 | H28: 2297 | I28: 1770 | J28: 887 | K28: 631 | L28: 502 | M28: 399.88247 | N28: 310.34643
A29: MedTech | B29: SALES_REV_TURN | C29: IS010 | D29: SEG0000336757 Segment | E29: 26994 | F29: 25961 | G29: 22959 | H29: 27060 | I29: 27426 | J29: 30400 | K29: 31857 | L29: 33792 | M29: 35855.63 | N29: 37811.186
A30: Adjusted Gross Margin (%) | B30: IS_COMP_GROSS_MARGIN_PERCENTAGE | C30: IM092 | E30: 72.261924 | F30: 71.937265 | G30: 71.220818 | H30: 73.421488 | I30: 71.549245 | J30: 74.116652 | K30: 74.70418 | L30: 72.973576 | M30: 73.054908 | N30: 73.13775
A31: Adjusted Research & Development | B31: IS_ADJ_R_AND_D_AS_REPORTED | C31: IS925 | E31: 10775 | F31: 11308 | G31: 12091 | H31: 14589 | I31: 13672 | J31: 14805 | K31: 17034 | L31: 14702 | M31: 15472.029 | N31: 16231.209
A32: Adjusted Selling, General, & Administrative | B32: IS_ADJ_SG_AND_A_AS_REPORTED | C32: IS926 | E32: 22540 | F32: 22178 | G32: 22067 | H32: 24635 | I32: 20218 | J32: 21483 | K32: 22853 | L32: 23676 | M32: 24789.758 | N32: 25897.672
A33: Adjusted Pre-Tax Income | B33: IS_COMP_PTP_EX_STK_BASED_COMP | C33: IM383 | E33: 26698 | F33: 28225 | G33: 25428 | H33: 30464 | I33: 31880 | J33: 29811 | K33: 28979 | L33: 31681 | M33: 34237.609 | N33: 37149.304
A35: Business Breakdown
A36: Total Revenue | B36: IS_COMP_SALES | C36: IS902 | E36: 81581 | F36: 82059 | G36: 82584 | H36: 93775 | I36: 94943 | J36: 85159 | K36: 88821 | L36: 94193 | M36: 100625.6 | N36: 106508.4
A37: Innovative Medicine | B37: SALES_REV_TURN | C37: IS010 | D37: SEG0000336691 Segment | E37: 40734 | F37: 42201 | G37: 45980 | H37: 51680 | I37: 52563 | J37: 54759 | K37: 56964 | L37: 60401 | M37: 64940.384 | N37: 68893.776
A38: Organic Growth (%) | B38: IS_ORGANIC_GROWTH_RATE | C38: IS950 | D38: SEG0000336691 Segment | F38: 5.8 | G38: 8.4 | H38: 13.6 | I38: 6.8 | J38: 4.9 | K38: 7.6 | L38: 5.3 | M38: 7.0256734 | N38: 4.9837877
A39: Constant Currency Growth (%) | B39: REVENUE_GROWTH_CC_1_YR | C39: M0025 | D39: SEG0000336691 Segment | E39: 11.8 | F39: 5.8 | G39: 8.2 | H39: 13.1 | I39: 6.7 | J39: 4.8 | K39: 5.7 | L39: 5.3 | M39: 7.1688779 | N39: 4.987095
A40: Currencies (%) | B40: IS_SALES_CHANGE_CURRENCIES_PCT | C40: IC056 | D40: SEG0000336691 Segment | E40: 0.6 | F40: 5.8 | G40: -0.2 | H40: 1.2 | I40: -5 | J40: -0.6 | K40: -1.7 | L40: 0.7 | M40: 1.3318965 | N40: -0.088981445
A41: MedTech | B41: SALES_REV_TURN | C41: IS010 | D41: SEG0000336757 Segment | E41: 26994 | F41: 25961 | G41: 22959 | H41: 27060 | I41: 27426 | J41: 30400 | K41: 31857 | L41: 33792 | M41: 35855.63 | N41: 37811.186
A42: Organic Growth (%) | B42: IS_ORGANIC_GROWTH_RATE | C42: IS950 | D42: SEG0000336757 Segment | F42: 3.9 | G42: -10.5 | H42: 16.8 | I42: 6.1 | J42: 7.8 | K42: 4.7 | L42: 5.4 | M42: 5.3871411 | N42: 4.6574443
A43: Constant Currency Growth (%) | B43: REVENUE_GROWTH_CC_1_YR | C43: M0025 | D43: SEG0000336757 Segment | E43: 1.1 | F43: -1.7 | G43: -11.4 | H43: 16.2 | I43: 6.2 | J43: 12.4 | K43: 6.2 | L43: 5.4 | M43: 5.6051647 | N43: 5.1081985
A44: Currencies (%) | B44: IS_SALES_CHANGE_CURRENCIES_PCT | C44: IC056 | D44: SEG0000336757 Segment | E44: 0.4 | F44: -2.1 | G44: -0.2 | H44: 1.7 | I44: -4.8 | J44: -1.6 | K44: -1.4 | L44: 0.7
A46: Innovative Medicine
A47: Immunology | B47: SALES_REV_TURN | C47: IS010 | D47: SEG0000336431 Segment | E47: 13120 | F47: 13955 | G47: 15055 | H47: 16750 | I47: 16935 | J47: 18052 | K47: 17828 | L47: 15728 | M47: 14933.691 | N47: 14895.106
A48: Remicade | B48: SALES_REV_TURN | C48: IS010 | D48: SEG0000336784 Segment | E48: 5326 | F48: 4384 | G48: 3747 | H48: 3190 | I48: 2343 | J48: 1839 | K48: 1605 | L48: 1768 | M48: 1564.6362 | N48: 1376.6295
A49: U.S. | B49: SALES_REV_TURN | C49: IS010 | D49: SEG0000336585 Segment | E49: 3664 | F49: 3079 | G49: 2508 | H49: 2019 | I49: 1417 | J49: 1143 | K49: 1009 | L49: 1171 | M49: 1056.0484 | N49: 906.81987
A50: International | B50: SALES_REV_TURN | C50: IS010 | D50: SEG0000336698 Segment | E50: 1226 | F50: 1006 | G50: 893 | H50: 935 | I50: 722 | J50: 549 | K50: 497 | L50: 523 | M50: 480.48937 | N50: 429.03717
A51: Remicade Export | B51: SALES_REV_TURN | C51: IS010 | D51: SEG0000374470 Segment | E51: 436 | F51: 294 | G51: 346 | H51: 236 | I51: 204 | J51: 147 | K51: 98 | L51: 74 | M51: 54.770954 | N51: 45.450332
A52: Simponi/Simponi Aria | B52: SALES_REV_TURN | C52: IS010 | D52: SEG0000336550 Segment | E52: 2084 | F52: 2188 | G52: 2243 | H52: 2276 | I52: 2184 | J52: 2197 | K52: 2190 | L52: 2668 | M52: 2354.6298 | N52: 1921.6869
A53: U.S. | B53: SALES_REV_TURN | C53: IS010 | D53: SEG0000336639 Segment | E53: 1051 | F53: 1159 | G53: 1155 | H53: 1127 | I53: 1166 | J53: 1124 | K53: 1082 | L53: 1193 | M53: 1104.6613 | N53: 884.27411
A54: International | B54: SALES_REV_TURN | C54: IS010 | D54: SEG0000336540 Segment | E54: 1033 | F54: 1029 | G54: 1088 | H54: 1148 | I54: 1018 | J54: 1073 | K54: 1108 | L54: 1475 | M54: 1242.4393 | N54: 1013.118
A55: Stelara | B55: SALES_REV_TURN | C55: IS010 | D55: SEG0000336802 Segment | E55: 5156 | F55: 6361 | G55: 7707 | H55: 9134 | I55: 9723 | J55: 10858 | K55: 10361 | L55: 6078 | M55: 3725.3115 | N55: 2559.521
A56: U.S. | B56: SALES_REV_TURN | C56: IS010 | D56: SEG0000336658 Segment | E56: 3469 | F56: 4346 | G56: 5240 | H56: 5938 | I56: 6388 | J56: 6966 | K56: 6720 | L56: 3847 | M56: 2111.8064 | N56: 1372.803
A57: PsO/PsA | B57: SALES_REV_TURN | C57: IS010 | D57: SEG7832019769 Segment
A58: UC | B58: SALES_REV_TURN | C58: IS010 | D58: SEG2720922428 Segment
A59: CD | B59: SALES_REV_TURN | C59: IS010 | D59: SEG6609825080 Segment
A60: International | B60: SALES_REV_TURN | C60: IS010 | D60: SEG0000336450 Segment | E60: 1687 | F60: 2015 | G60: 2467 | H60: 3196 | I60: 3335 | J60: 3892 | K60: 3641 | L60: 2230 | M60: 1597.8702 | N60: 1181.4532
A61: Tremfya | B61: SALES_REV_TURN | C61: IS010 | D61: SEG0000336538 Segment | E61: 544 | F61: 1012 | G61: 1347 | H61: 2127 | I61: 2668 | J61: 3147 | K61: 3670 | L61: 5155 | M61: 7046.4612 | N61: 8549.9211
A62: U.S. | B62: SALES_REV_TURN | C62: IS010 | D62: SEG0000336467 Segment | E62: 453 | F62: 764 | G62: 926 | H62: 1504 | I62: 1844 | J62: 2147 | K62: 2443 | L62: 3529 | M62: 4967.7846 | N62: 6073.8643
A63: PsO/PsA | B63: SALES_REV_TURN | C63: IS010 | D63: SEG2943241013 Segment
A64: UC | B64: SALES_REV_TURN | C64: IS010 | D64: SEG6832143665 Segment
A65: CD | B65: SALES_REV_TURN | C65: IS010 | D65: SEG5609948976 Segment
A66: International | B66: SALES_REV_TURN | C66: IS010 | D66: SEG0000336797 Segment | E66: 91 | F66: 249 | G66: 421 | H66: 624 | I66: 824 | J66: 999 | K66: 1227 | L66: 1626 | M66: 2095.4211 | N66: 2443.263
A67: Other Immunology | B67: SALES_REV_TURN | C67: IS010 | D67: SEG0000336662 Segment | E67: 10 | F67: 10 | G67: 11 | H67: 23 | I67: 17 | J67: 11 | K67: 3 | L67: 59 | M67: 85.767972 | N67: 137.25373
A68: U.S. | B68: SALES_REV_TURN | C68: IS010 | D68: SEG0000336483 Segment | E68: 0 | F68: 0 | G68: 0 | H68: 20 | I68: 17 | J68: 11 | K68: 3 | L68: 58 | M68: 109.33333 | N68: 204.426
A69: International | B69: SALES_REV_TURN | C69: IS010 | D69: SEG0000336750 Segment | E69: 10 | F69: 10 | G69: 11 | H69: 4 | I69: 0 | J69: 0 | K69: 0 | L69: 2
A71: Infectious Diseases | B71: SALES_REV_TURN | C71: IS010 | D71: SEG0000336727 Segment | E71: 3304 | F71: 3412 | G71: 3574 | H71: 5825 | I71: 5449 | J71: 4418 | K71: 3396 | L71: 3241 | M71: 3058.6893 | N71: 2675.8464
A72: Edurant | B72: SALES_REV_TURN | C72: IS010 | D72: SEG0000336765 Segment | E72: 816 | F72: 861 | G72: 963 | H72: 994 | I72: 1008 | J72: 1150 | K72: 1272 | L72: 1486 | M72: 1447.2483 | N72: 1197.5587
A73: U.S. | B73: SALES_REV_TURN | C73: IS010 | D73: SEG0000336643 Segment | E73: 58 | F73: 50 | G73: 44 | H73: 41 | I73: 36 | J73: 35 | K73: 31 | L73: 26 | M73: 22.320257 | N73: 19.752114
A74: International | B74: SALES_REV_TURN | C74: IS010 | D74: SEG0000336593 Segment | E74: 758 | F74: 812 | G74: 919 | H74: 953 | I74: 972 | J74: 1115 | K74: 1241 | L74: 1461 | M74: 1442.8807 | N74: 1178.465
A75: Prezista | B75: SALES_REV_TURN | C75: IS010 | D75: SEG0000336422 Segment | E75: 1955 | F75: 2110 | G75: 2184 | H75: 2083 | I75: 1943 | J75: 1854 | K75: 1712 | L75: 1579 | M75: 1435.2154 | N75: 1193.0787
A76: U.S. | B76: SALES_REV_TURN | C76: IS010 | D76: SEG0000336770 Segment | E76: 1169 | F76: 1422 | G76: 1587 | H76: 1508 | I76: 1494 | J76: 1446 | K76: 1312 | L76: 1226 | M76: 1122.447 | N76: 891.00225
A77: International | B77: SALES_REV_TURN | C77: IS010 | D77: SEG0000336796 Segment | E77: 786 | F77: 689 | G77: 597 | H77: 575 | I77: 449 | J77: 408 | K77: 401 | L77: 353 | M77: 315.56516 | N77: 276.03994
A78: Other Infectious Diseases | B78: SALES_REV_TURN | C78: IS010 | D78: SEG0000336507 Segment | E78: 533 | F78: 441 | G78: 427 | H78: 363 | I78: 319 | J78: 297 | K78: 412 | L78: 176 | M78: 160.63147 | N78: 155.91735
A79: U.S. | B79: SALES_REV_TURN | C79: IS010 | D79: SEG0000336584 Segment | E79: 151 | F79: 126 | G79: 104 | H79: 66 | I79: 30 | J79: 19 | K79: 11 | L79: 12 | M79: 10.579571 | N79: 10.036904
A80: International | B80: SALES_REV_TURN | C80: IS010 | D80: SEG0000336815 Segment | E80: 382 | F80: 315 | G80: 292 | H80: 297 | I80: 289 | J80: 278 | K80: 400 | L80: 163 | M80: 144.01944 | N80: 138.13764
A82: Neuroscience | B82: SALES_REV_TURN | C82: IS010 | D82: SEG0000336458 Segment | E82: 6077 | F82: 6328 | G82: 6548 | H82: 6988 | I82: 6892 | J82: 7140 | K82: 7115 | L82: 7837 | M82: 8845.8697 | N82: 9721.9048
A83: Caplyta | B83: SALES_REV_TURN | C83: IS010 | D83: SEG4822019841 Segment | L83: 700 | M83: 1265.4184 | N83: 1824.5477
A84: U.S. | B84: SALES_REV_TURN | C84: IS010 | D84: SEG8710922493 Segment | K84: 0 | L84: 700
A85: International | B85: SALES_REV_TURN | C85: IS010 | D85: SEG3822143737 Segment | K85: 0 | L85: 0
A86: Concerta/Methylphenidate | B86: SALES_REV_TURN | C86: IS010 | D86: SEG0000336526 Segment | E86: 663 | F86: 696 | G86: 621 | H86: 667 | I86: 644 | J86: 783 | K86: 641 | L86: 584 | M86: 517.4845 | N86: 488.39723
A87: U.S. | B87: SALES_REV_TURN | C87: IS010 | D87: SEG0000336671 Segment | E87: 229 | F87: 233 | G87: 183 | H87: 172 | I87: 151 | J87: 230 | K87: 134 | L87: 82 | M87: 49.567935 | N87: 44.04144
A88: International | B88: SALES_REV_TURN | C88: IS010 | D88: SEG0000336539 Segment | E88: 434 | F88: 463 | G88: 439 | H88: 495 | I88: 493 | J88: 554 | K88: 507 | L88: 502 | M88: 464.55725 | N88: 441.85543
A89: Invega Sustenna | B89: SALES_REV_TURN | C89: IS010 | D89: SEG0000336548 Segment | E89: 2928 | F89: 3330 | G89: 3653 | H89: 4022 | I89: 4140 | J89: 4115 | K89: 4222 | L89: 3810 | M89: 3683.0141 | N89: 3637.5111
A90: U.S. | B90: SALES_REV_TURN | C90: IS010 | D90: SEG0000336427 Segment | E90: 1791 | F90: 2107 | G90: 2314 | H90: 2550 | I90: 2714 | J90: 2897 | K90: 3125 | L90: 2725 | M90: 2662.3878 | N90: 2634.7003
A91: International | B91: SALES_REV_TURN | C91: IS010 | D91: SEG0000336553 Segment | E91: 1137 | F91: 1224 | G91: 1339 | H91: 1472 | I91: 1426 | J91: 1218 | K91: 1097 | L91: 1085 | M91: 1027.7752 | N91: 981.45903
A92: Spravato | B92: SALES_REV_TURN | C92: IS010 | D92: SEG0001304378 Segment | I92: 374 | J92: 689 | K92: 1077 | L92: 1696 | M92: 2327.8252 | N92: 2843.9743
A93: U.S. | B93: SALES_REV_TURN | C93: IS010 | D93: SEG0001304389 Segment | H93: 198 | I93: 328 | J93: 589 | K93: 929 | L93: 1485 | M93: 2016.6569 | N93: 2427.2484
A94: International | B94: SALES_REV_TURN | C94: IS010 | D94: SEG0001304390 Segment | H94: 27 | I94: 46 | J94: 100 | K94: 148 | L94: 210 | M94: 317.1996 | N94: 436.10805
A95: Other Neuroscience | B95: SALES_REV_TURN | C95: IS010 | D95: SEG0000336516 Segment | E95: 1749 | F95: 1614 | G95: 1632 | H95: 1707 | I95: 1734 | J95: 1553 | K95: 1175 | L95: 1047 | M95: 1001.5898 | N95: 971.71971
A96: U.S. | B96: SALES_REV_TURN | C96: IS010 | D96: SEG0000336600 Segment | E96: 239 | F96: 266 | G96: 298 | H96: 427 | I96: 376 | J96: 349 | K96: 210 | L96: 159 | M96: 149.3896 | N96: 142.52428
A97: International | B97: SALES_REV_TURN | C97: IS010 | D97: SEG0000336733 Segment | E97: 1510 | F97: 1349 | G97: 1312 | H97: 1647 | I97: 1358 | J97: 1204 | K97: 966 | L97: 889 | M97: 833.0827 | N97: 791.55049
A99: Oncology | B99: SALES_REV_TURN | C99: IS010 | D99: SEG0000336666 Segment | E99: 9844 | F99: 10692 | G99: 12777 | H99: 14548 | I99: 15983 | J99: 17661 | K99: 20781 | L99: 25380 | M99: 30397.46 | N99: 35228.99
A100: Carvykti (Citra-Cel) | B100: SALES_REV_TURN | C100: IS010 | D100: SEG0000863947 Segment | I100: 133 | J100: 500 | K100: 963 | L100: 1887 | M100: 2836.895 | N100: 3860.1775
A101: U.S. | B101: SALES_REV_TURN | C101: IS010 | D101: SEG0001285883 Segment | H101: 0 | I101: 133 | J101: 469 | K101: 869 | L101: 1492 | M101: 2134.8903 | N101: 2759.5648
A102: International | B102: SALES_REV_TURN | C102: IS010 | D102: SEG0001285884 Segment | H102: 0 | I102: 0 | J102: 30 | K102: 94 | L102: 395 | M102: 712.90314 | N102: 1111.4773
A103: Darzalex | B103: SALES_REV_TURN | C103: IS010 | D103: SEG0000336459 Segment | E103: 2025 | F103: 2998 | G103: 4190 | H103: 6023 | I103: 7977 | J103: 9744 | K103: 11670 | L103: 14351 | M103: 16858.919 | N103: 18794.842
A104: U.S. | B104: SALES_REV_TURN | C104: IS010 | D104: SEG0000336783 Segment | E104: 1203 | F104: 1567 | G104: 2232 | H104: 3169 | I104: 4210 | J104: 5277 | K104: 6588 | L104: 8266 | M104: 9916.9914 | N104: 11074.936
A105: International | B105: SALES_REV_TURN | C105: IS010 | D105: SEG0000336595 Segment | E105: 822 | F105: 1430 | G105: 1957 | H105: 2854 | I105: 3767 | J105: 4467 | K105: 5082 | L105: 6085 | M105: 6952.363 | N105: 7652.1445
A106: Erleada | B106: SALES_REV_TURN | C106: IS010 | D106: SEG0000387621 Segment | F106: 332 | G106: 760 | H106: 1291 | I106: 1881 | J106: 2387 | K106: 2999 | L106: 3574 | M106: 4132.7085 | N106: 4551.9887
...

Sheet ABBOTT
A1: ABT US Equity- Company Financial (Multiple Periods)
A2: ABT US Equity Periodicity:A Currency:USD Estimate Source:BST Actual Source:Bloomberg
A3: In Millions of USD | E3: 2018 A (Rep) | F3: 2019 A (Rep) | G3: 2020 A (Rep) | H3: 2021 A (Rep) | I3: 2022 A (Rep) | J3: 2023 A (Rep) | K3: 2024 A (Rep) | L3: 2025 A (Rep) | M3: 2026 A (Fwd) | N3: 2027 A (Fwd)
A4: 12 Months Ending | B4: Field Expression | C4: Calcrt Field | D4: Segment Id | E4: 43465 | F4: 43830 | G4: 44196 | H4: 44561 | I4: 44926 | J4: 45291 | K4: 45657 | L4: 46022 | M4: 46387 | N4: 46752
A5: Highlights
A6: Adjusted Diluted EPS | B6: IS_COMP_EPS_ADJUSTED_OLD | C6: IS900 | E6: 2.88 | F6: 3.24 | G6: 3.65 | H6: 5.21 | I6: 5.34 | J6: 4.44 | K6: 4.67 | L6: 5.15 | M6: 5.6771429 | N6: 6.2459259
A7: Revenue | B7: IS_COMP_SALES | C7: IS902 | E7: 30578 | F7: 31904 | G7: 34608 | H7: 43075 | I7: 43653 | J7: 40109 | K7: 41950 | L7: 44328 | M7: 47812.731 | N7: 51498.111
A8: YoY Organic Growth (%) | B8: IS_ORGANIC_GROWTH_RATE | C8: IS950 | E8: 7.3 | F8: 7.7 | G8: 9.8 | H8: 22.9 | I8: 6.4 | J8: -6.2 | K8: 7.1 | L8: 5.5 | M8: 6.8330072 | N8: 7.3823842
A9: Organic Growth Ex. Covid Impact (%) | B9: IS_ORGANIC_REV_GRWTH_N_GAAP_PCT | C9: IC390 | G9: 9.8 | H9: 13.7 | I9: 7.4 | J9: 11.7 | K9: 9.6 | L9: 6.7 | M9: 7.3834133 | N9: 7.7224184
A11: Segment Revenue
A12: Nutrition | B12: SALES_REV_TURN | C12: IS010 | D12: SEG0000306650 Segment | E12: 7229 | F12: 7409 | G12: 7647 | H12: 8294 | I12: 7459 | J12: 8154 | K12: 8413 | L12: 8451 | M12: 8555.6585 | N12: 8833.4777
A13: Diagnostics | B13: SALES_REV_TURN | C13: IS010 | D13: SEG0000306682 Segment | E13: 7495 | F13: 7713 | G13: 10805 | H13: 15526 | I13: 16469 | J13: 9988 | K13: 9341 | L13: 8937 | M13: 9468.1579 | N13: 10039.395
A14: Covid-19 Testing | B14: IS_REV_INCLUDING_EX_CRT_ITEMS | C14: IC304 | D14: SEG0000584186 Segment | H14: 8368 | I14: 8368 | J14: 1586 | K14: 747 | L14: 297 | M14: 241.74829 | N14: 212.61594
A15: Established Pharmaceuticals | B15: SALES_REV_TURN | C15: IS010 | D15: SEG0000306738 Segment | E15: 4422 | F15: 4486 | G15: 4303 | H15: 4718 | I15: 4912 | J15: 5066 | K15: 5194 | L15: 5536 | M15: 6037.1041 | N15: 6467.8137
A16: Medical Devices | B16: SALES_REV_TURN | C16: IS010 | D16: SEG0000306728 Segment | E16: 11370 | F16: 12239 | G16: 11787 | H16: 14485 | I16: 14802 | J16: 16887 | K16: 18986 | L16: 21387 | M16: 23811.167 | N16: 26181.095
A17: Diabetes | B17: SALES_REV_TURN | C17: IS010 | D17: SEG0000306521 Segment | E17: 1933 | F17: 2524 | G17: 3267 | H17: 4328 | I17: 4756 | J17: 5761 | K17: 6805 | L17: 7998 | M17: 9138.6046 | N17: 10322.37
A19: Adjusted Gross Margin (%) | B19: IS_COMP_GROSS_MARGIN_PERCENTAGE | C19: IM092 | E19: 59.3 | F19: 59.2 | G19: 57.6 | H19: 57.961695 | I19: 56.923923 | J19: 55.54115 | K19: 56.20739 | L19: 56.738405 | M19: 56.971138 | N19: 57.376932
A20: Adjusted Operating Margin (%) | B20: ADJ_OPERATING_MARGIN | C20: RX609 | E20: 21.436981 | F20: 22.285607 | G20: 23.142048 | H20: 26.289031 | I20: 25.7279 | J20: 22.216959 | K20: 22.15733 | L20: 23.238134 | M20: 23.802788 | N20: 24.46244
A21: Adjusted Net Income | B21: IS_COMP_NET_INCOME_ADJUST_OLD | C21: IS903 | E21: 5131 | F21: 5810 | G21: 6552 | H21: 9367 | I21: 9466 | J21: 7802 | K21: 8200 | L21: 9040 | M21: 9928.9231 | N21: 10902.154
A23: Net Debt | B23: HEADLINE_NET_DEBT | C23: F1708 | E23: 15439 | F23: 14912 | G23: 12697 | H23: 8934 | I23: 7568 | J23: 8350 | K23: 6975 | L23: 4876 | M23: 716.28571 | N23: -4032.8571
A24: Free Cash Flow | B24: CF_FREE_CASH_FLOW | C24: RR008 | E24: 4906 | F24: 4498 | G24: 5724 | H24: 8648 | I24: 7804 | J24: 5059 | K24: 6351 | L24: 7395 | M24: 8746.5809 | N24: 9550.4932
A26: Company Operating Metrics
A27: FX Impact on Revenue Growth (%)
A28: Established Pharmaceuticals | B28: IS_SALES_CHANGE_CURRENCIES_PCT | C28: IC056 | D28: SEG0000306738 Segment | E28: -3.8 | F28: -3.8 | G28: -6 | H28: -0.8 | I28: -6.5 | J28: -7.8 | K28: -6.7 | L28: -0.8 | M28: 3.255548 | N28: 0
A29: Key Emerging Markets | B29: IS_SALES_CHANGE_CURRENCIES_PCT | C29: IC056 | D29: SEG0000306601 Segment | E29: -5 | F29: -5 | G29: -8 | H29: -2 | I29: -7 | J29: -9.2 | K29: -8.2 | L29: -1.5 | M29: 1.7792999
A30: Other Markets | B30: IS_SALES_CHANGE_CURRENCIES_PCT | C30: IC056 | D30: SEG0000306516 Segment | E30: 2 | F30: 2 | G30: 1 | H30: 2 | I30: -7 | J30: -3 | K30: -2.3 | L30: 1.1 | M30: 1.3099643
A31: Nutrition | B31: IS_SALES_CHANGE_CURRENCIES_PCT | C31: IC056 | D31: SEG0000306650 Segment | E31: -0.5 | F31: -0.5 | G31: -1.5 | H31: 0.8 | I31: -3.9 | J31: -2.3 | K31: -2.7 | L31: -0.7 | M31: 0.93051035
A32: Diagnostics | B32: IS_SALES_CHANGE_CURRENCIES_PCT | C32: IC056 | D32: SEG0000306682 Segment | E32: -0.1 | F32: -0.1 | G32: -0.5 | H32: 2.1 | I32: -4.4 | J32: -1.2 | K32: -2.6 | L32: 0.2 | M32: 1.0734913 | N32: 0
A33: Medical Devices | B33: IS_SALES_CHANGE_CURRENCIES_PCT | C33: IC056 | D33: SEG0000425256 Segment | F33: -2.9 | G33: 0.1 | H33: 2.5 | I33: -5.9 | J33: -1 | K33: -1.3 | L33: 0.7 | M33: 0.98455046 | N33: 0
A34: Rhythm Management | B34: IS_SALES_CHANGE_CURRENCIES_PCT | C34: IC056 | D34: SEG0000306753 Segment | E34: 1 | F34: 1 | G34: 0 | H34: 2 | I34: -6 | J34: -1 | K34: -0.9 | L34: 0.7 | M34: 0.91293562
A35: Electrophysiology | B35: IS_SALES_CHANGE_CURRENCIES_PCT | C35: IC056 | D35: SEG0000306577 Segment | E35: 1 | F35: 1 | G35: 1 | H35: 2 | I35: -6 | J35: -2 | K35: -2.1 | L35: 0.4 | M35: 0.90874223
A36: Heart Failure | B36: IS_SALES_CHANGE_CURRENCIES_PCT | C36: IC056 | D36: SEG0000306575 Segment | E36: 0 | F36: 0 | G36: 0 | H36: 1 | I36: -2 | J36: 0.1 | K36: -0.1 | L36: 0.5 | M36: 1.0849499
A37: Vascular | B37: IS_SALES_CHANGE_CURRENCIES_PCT | C37: IC056 | D37: SEG0000306592 Segment | E37: 1 | F37: 1.1 | G37: 0 | H37: 3 | I37: -5 | J37: -1.3 | K37: -0.9 | L37: 0.5 | M37: 1.0169328
A38: Structural Heart | B38: IS_SALES_CHANGE_CURRENCIES_PCT | C38: IC056 | D38: SEG0000306748 Segment | E38: 1 | F38: 1 | G38: 0 | H38: 2 | I38: -7 | J38: -0.7 | K38: -1.5 | L38: 0.8 | M38: 0.91061293
A39: Diabetes Care | B39: IS_SALES_CHANGE_CURRENCIES_PCT | C39: IC056 | D39: SEG0000306521 Segment | F39: 2 | G39: 0 | H39: 4 | I39: -7 | J39: -0.8 | K39: -1.6 | L39: 1.2 | M39: 0.99748095
A41: Business Breakdown
A42: Revenue
A43: Established Pharmaceuticals | B43: SALES_REV_TURN | C43: IS010 | D43: SEG0000306738 Segment | E43: 4422 | F43: 4486 | G43: 4303 | H43: 4718 | I43: 4912 | J43: 5066 | K43: 5194 | L43: 5536 | M43: 6037.1041 | N43: 6467.8137
A44: Key Emerging Markets | B44: SALES_REV_TURN | C44: IS010 | D44: SEG0000306601 Segment | E44: 3363 | F44: 3392 | G44: 3209 | H44: 3565 | I44: 3766 | J44: 3807 | K44: 3858 | L44: 4167 | M44: 4581.5345 | N44: 4927.9758
A45: Other Emerging Markets | B45: IS_REV_INCLUDING_EX_CRT_ITEMS | C45: IC304 | D45: SEG0000306516 Segment | E45: 1059 | F45: 1094 | G45: 1094 | H45: 1179 | I45: 1184 | J45: 1259 | K45: 1336 | L45: 1369 | M45: 1462.9223 | N45: 1548.9446
A46: Nutritionals | B46: SALES_REV_TURN | C46: IS010 | D46: SEG0000306650 Segment | E46: 7229 | F46: 7409 | G46: 7647 | H46: 8294 | I46: 7459 | J46: 8154 | K46: 8413 | L46: 8451 | M46: 8555.6585 | N46: 8833.4777
A47: Pediatric | B47: SALES_REV_TURN | C47: IS010 | D47: SEG0000306513 Segment | E47: 4097 | F47: 4161 | G47: 4127 | H47: 4298 | I47: 3481 | J47: 3934 | K47: 4023 | L47: 3974 | M47: 3989.0665 | N47: 4105.7099
A48: Adult | B48: SALES_REV_TURN | C48: IS010 | D48: SEG0000306656 Segment | E48: 3132 | F48: 3248 | G48: 3520 | H48: 3996 | I48: 3978 | J48: 4220 | K48: 4390 | L48: 4477 | M48: 4571.7592 | N48: 4725.3015
A49: Diagnostics | B49: SALES_REV_TURN | C49: IS010 | D49: SEG0000306682 Segment | E49: 7495 | F49: 7713 | G49: 10805 | H49: 15526 | I49: 16469 | J49: 9988 | K49: 9341 | L49: 8937 | M49: 9468.1579 | N49: 10039.395
A50: Core Laboratory | B50: SALES_REV_TURN | C50: IS010 | D50: SEG0000306685 Segment | E50: 4386 | F50: 4656 | G50: 4475 | H50: 5128 | I50: 4888 | J50: 5159 | K50: 5235 | L50: 5360 | M50: 5671.0201 | N50: 5971.2549
A51: Molecular | B51: SALES_REV_TURN | C51: IS010 | D51: SEG0000306634 Segment | E51: 484 | F51: 442 | G51: 1438 | H51: 1427 | I51: 995 | J51: 574 | K51: 521 | L51: 517 | M51: 596.77606 | N51: 899.62676
A52: Point of Care | B52: SALES_REV_TURN | C52: IS010 | D52: SEG0000306727 Segment | E52: 553 | F52: 561 | G52: 516 | H52: 536 | I52: 525 | J52: 565 | K52: 588 | L52: 606 | M52: 649.69335 | N52: 681.94984
A53: Rapid Diagnostics | B53: SALES_REV_TURN | C53: IS010 | D53: SEG0000306678 Segment | E53: 2072 | F53: 2054 | G53: 4376 | H53: 8435 | I53: 10061 | J53: 3690 | K53: 2997 | L53: 2454 | M53: 2363.0251 | N53: 2536.275
A54: Covid-19 Testing | B54: IS_REV_INCLUDING_EX_CRT_ITEMS | C54: IC304 | D54: SEG0000584186 Segment | H54: 8368 | I54: 8368 | J54: 1586 | K54: 747 | L54: 297 | M54: 241.74829 | N54: 212.61594
A55: Medical Devices | B55: SALES_REV_TURN | C55: IS010 | D55: SEG0000306728 Segment | E55: 11370 | F55: 12239 | G55: 11787 | H55: 14485 | I55: 14802 | J55: 16887 | K55: 18986 | L55: 21387 | M55: 23811.167 | N55: 26181.095
A56: Cardiovascular & Neuromodulation | B56: SALES_REV_TURN | C56: IS010 | D56: SEG0000306729 Segment | E56: 9437 | F56: 9715 | G56: 8520 | H56: 10157 | I56: 10046 | J56: 11126 | K56: 12181 | L56: 13389 | M56: 14659.152 | N56: 15824.562
A57: Rhythm Management | B57: SALES_REV_TURN | C57: IS010 | D57: SEG0000306753 Segment | E57: 2091 | F57: 2144 | G57: 1914 | H57: 2198 | I57: 2119 | J57: 2255 | K57: 2390 | L57: 2649 | M57: 2893.7966 | N57: 3063.078
A58: Electrophysiology | B58: SALES_REV_TURN | C58: IS010 | D58: SEG0000306577 Segment | E58: 1668 | F58: 1721 | G58: 1578 | H58: 1907 | I58: 1927 | J58: 2195 | K58: 2467 | L58: 2764 | M58: 3213.9878 | N58: 3689.9141
A59: Heart Failure | B59: SALES_REV_TURN | C59: IS010 | D59: SEG0000306575 Segment | E59: 646 | F59: 769 | G59: 740 | H59: 1007 | I59: 1035 | J59: 1161 | K59: 1279 | L59: 1448 | M59: 1568.7078 | N59: 1677.3855
A60: Vascular | B60: SALES_REV_TURN | C60: IS010 | D60: SEG0000306592 Segment | E60: 2929 | F60: 2850 | G60: 2339 | H60: 2654 | I60: 2483 | J60: 2681 | K60: 2837 | L60: 2995 | M60: 3151.4631 | N60: 3274.263
A61: Structural Heart | B61: SALES_REV_TURN | C61: IS010 | D61: SEG0000306748 Segment | E61: 1239 | F61: 1400 | G61: 1247 | H61: 1610 | I61: 1712 | J61: 1944 | K61: 2246 | L61: 2523 | M61: 2771.1499 | N61: 3027.2723
A62: Neuromodulation | B62: SALES_REV_TURN | C62: IS010 | D62: SEG0000306550 Segment | E62: 864 | F62: 831 | G62: 702 | H62: 781 | I62: 770 | J62: 890 | K62: 962 | L62: 1010 | M62: 1056.3081 | N62: 1099.6526
A63: Diabetes Care | B63: SALES_REV_TURN | C63: IS010 | D63: SEG0000306521 Segment | E63: 1933 | F63: 2524 | G63: 3267 | H63: 4328 | I63: 4756 | J63: 5761 | K63: 6805 | L63: 7998 | M63: 9138.6046 | N63: 10322.37
A64: Continuous Glucose Monitors | B64: SALES_REV_TURN | C64: IS010 | D64: SEG6558657440 Segment | F64: 1800 | G64: 2600 | H64: 3700 | I64: 4200 | J64: 5300 | K64: 6400 | L64: 7600 | M64: 8757.4271 | N64: 9909.5899
A65: Other | B65: SALES_REV_TURN | C65: IS010 | D65: SEG1447560099 Segment | F65: 724 | G65: 667 | H65: 628 | I65: 556 | J65: 461 | K65: 405 | L65: 398 | M65: 339.594 | N65: 301.23771
A67: Organic Revenue Growth (%) | B67: IS_ORGANIC_GROWTH_RATE | C67: IS950 | E67: 7.3 | F67: 7.7 | G67: 9.8 | H67: 22.9 | I67: 6.4 | J67: -6.2 | K67: 7.1 | L67: 5.5 | M67: 6.8330072 | N67: 7.3823842
A68: Established Pharmaceuticals | B68: IS_ORGANIC_GROWTH_RATE | C68: IS950 | D68: SEG0000306738 Segment | E68: 7 | F68: 7.3 | G68: 1.9 | H68: 10.4 | I68: 10.6 | J68: 10.9 | K68: 9.2 | L68: 7.4 | M68: 7.8062855 | N68: 7.1010795
A69: Key Emerging Markets | B69: IS_ORGANIC_GROWTH_RATE | C69: IS950 | D69: SEG0000306601 Segment | E69: 7.4 | F69: 7.9 | G69: 2.6 | H69: 11.9 | I69: 11.8 | J69: 10.3 | K69: 9.5 | L69: 9.5 | M69: 8.7209711 | N69: 7.5225052
A70: Other Emerging Markets | B70: IS_ORGANIC_GROWTH_RATE | C70: IS950 | D70: SEG0000306516 Segment | E70: 5.8 | F70: 5.6 | G70: -0.5 | H70: 6 | I70: 7.3 | J70: 12.8 | K70: 8.4 | L70: 1.4 | M70: 6.6043825 | N70: 5.75
A71: Nutritionals | B71: IS_ORGANIC_GROWTH_RATE | C71: IS950 | D71: SEG0000306650 Segment | E71: 5.2 | F71: 5.3 | G71: 4.7 | H71: 7.7 | I71: -6.2 | J71: 13 | K71: 6.4 | L71: 1.2 | M71: 0.69726773 | N71: 3.1729519
A72: Pediatric | B72: IS_ORGANIC_GROWTH_RATE | C72: IS950 | D72: SEG0000306513 Segment | E72: 5.6 | F72: 3.4 | G72: 0.3 | H72: 3.3 | I72: -16.6 | J72: 17.9 | K72: 3.7 | L72: -0.7 | M72: -0.22010154 | N72: 3.143308
A73: Adult | B73: IS_ORGANIC_GROWTH_RATE | C73: IS950 | D73: SEG0000306656 Segment | E73: 4.6 | F73: 7.9 | G73: 10.3 | H73: 12.8 | I73: -4.8 | J73: 8.8 | K73: 8.9 | L73: 3 | M73: 1.0812606 | N73: 3.5857264
A74: Diagnostics Consolidated | B74: IS_ORGANIC_GROWTH_RATE | C74: IS950 | D74: SEG0000306682 Segment | E74: 6.7 | F74: 5.9 | G74: 40.6 | H74: 42.7 | I74: 10.4 | J74: -38.2 | K74: -3.9 | L74: -4.5 | M74: 3.6264114 | N74: 4.7110889
A75: Core Laboratory | B75: IS_ORGANIC_GROWTH_RATE | C75: IS950 | D75: SEG0000306685 Segment | E75: 8 | F75: 10 | G75: -2.8 | H75: 12.4 | I75: 1.9 | J75: 8.4 | K75: 5.6 | L75: 2.1 | M75: 5.0494349 | N75: 5.5333343
A76: Molecular | B76: IS_ORGANIC_GROWTH_RATE | C76: IS950 | D76: SEG0000306634 Segment | E76: 4.3 | F76: -6.3 | G76: 225.7 | H76: -2.9 | I76: -27.4 | J76: -41.6 | K76: -8.5 | L76: -1.2 | M76: 3.2712035 | N76: 4.0960041
A77: Point of Care | B77: IS_ORGANIC_GROWTH_RATE | C77: IS950 | D77: SEG0000306727 Segment | E77: 0.3 | F77: 1.9 | G77: -7.9 | H77: 3.2 | I77: -0.6 | J77: 7.7 | K77: 4.1 | L77: 3.1 | M77: 6.6800659 | N77: 4.9033703
A78: Rapid Diagnostics | B78: IS_ORGANIC_GROWTH_RATE | C78: IS950 | D78: SEG0000306678 Segment | F78: 1.2 | G78: 112.3 | H78: 93.3 | I78: 22.5 | J78: -62.9 | K78: -17.8 | L78: -18 | M78: -0.33030727 | N78: 3.572487
A79: Medical Devices | B79: IS_ORGANIC_GROWTH_RATE | C79: IS950 | D79: SEG0000306728 Segment | E79: 9.1 | F79: 10.5 | G79: -3.8 | H79: 19.4 | I79: 8.1 | J79: 14.2 | K79: 13.4 | L79: 11.9 | M79: 10.471931 | N79: 9.9329384
A80: Rhythm Management | B80: IS_ORGANIC_GROWTH_RATE | C80: IS950 | D80: SEG0000306753 Segment | E80: -1.5 | F80: 0 | G80: -10.8 | H80: 12.7 | I80: 1.5 | J80: 7.5 | K80: 6.9 | L80: 10.2 | M80: 8.7388894 | N80: 6.4448763
A81: Electrophysiology | B81: IS_ORGANIC_GROWTH_RATE | C81: IS950 | D81: SEG0000306577 Segment | E81: 19.6 | F81: 12.5 | G81: -8.6 | H81: 19.1 | I81: 7.3 | J81: 15.9 | K81: 14.4 | L81: 11.6 | M81: 14.949957 | N81: 13.287709
A82: Heart Failure | B82: IS_ORGANIC_GROWTH_RATE | C82: IS950 | D82: SEG0000306575 Segment | E82: 0 | F82: 20.5 | G82: -3.9 | H82: 19.1 | I82: 5.9 | J82: 12 | K82: 10.3 | L82: 12.7 | M82: 7.6479763 | N82: 6.5398985
A83: Vascular | B83: IS_ORGANIC_GROWTH_RATE | C83: IS950 | D83: SEG0000306592 Segment | E83: 0.5 | F83: 0.2 | G83: -17.8 | H83: 11.1 | I83: -1 | J83: 4 | K83: 4.6 | L83: 5.1 | M83: 4.4737388 | N83: 3.9639519
A84: Structural Heart | B84: IS_ORGANIC_GROWTH_RATE | C84: IS950 | D84: SEG0000306748 Segment | E84: 13 | F84: 16.2 | G84: -11.2 | H84: 26.8 | I84: 13 | J84: 14.3 | K84: 17 | L84: 11.5 | M84: 9.7612476 | N84: 9.4468488
A85: Neuromodulation | B85: IS_ORGANIC_GROWTH_RATE | C85: IS950 | D85: SEG0000306550 Segment | E85: 6.5 | F85: -2.4 | G85: -15.5 | H85: 10.3 | I85: 0.9 | J85: 16.4 | K85: 9.5 | L85: 4.8 | M85: 4.0292516 | N85: 4.3013448
A86: Diabetes Care | B86: IS_ORGANIC_GROWTH_RATE | C86: IS950 | D86: SEG0000306521 Segment | E86: 34.8 | F86: 35.7 | G86: 29.4 | H86: 28.5 | I86: 17.4 | J86: 21.9 | K86: 19.7 | L86: 16.3 | M86: 13.272066 | N86: 12.990205
A87: Continuous Glucose Monitors | B87: IS_ORGANIC_GROWTH_RATE | C87: IS950 | D87: SEG6558657440 Segment
A89: Adjusted Organic Revenue Growth (%)
A90: Diagnostics (Ex. Covid) | B90: IS_ORGANIC_REV_GRWTH_N_GAAP_PCT | C90: IC390 | D90: SEG0000306682 Segment | H90: 42.7 | I90: 8.6 | J90: 5.8 | K90: 5.2 | L90: -4.5 | M90: 4.1827175 | N90: 5.3145634
A91: Core Laboratory | B91: IS_ORGANIC_REV_GRWTH_N_GAAP_PCT | C91: IC390 | D91: SEG0000306685 Segment | H91: 12.4 | I91: 4.8 | J91: 9.4 | K91: 5.8 | L91: 2.1
A92: Molecular | B92: IS_ORGANIC_REV_GRWTH_N_GAAP_PCT | C92: IC390 | D92: SEG0000306634 Segment | H92: -2.9 | I92: 13.8 | J92: -8.1 | K92: -3.2 | L92: -1.2
A93: Point of Care | B93: IS_ORGANIC_REV_GRWTH_N_GAAP_PCT | C93: IC390 | D93: SEG0000306727 Segment | H93: 3.2 | I93: -0.6 | J93: 7.7 | K93: 4.1 | L93: 3.1
A94: Rapid Diagnostics | B94: IS_ORGANIC_REV_GRWTH_N_GAAP_PCT | C94: IC390 | D94: SEG0000306678 Segment | H94: 93.3 | I94: 19.1 | J94: 1.3 | K94: 6 | L94: 11.9
A96: Regional Breakdown
A97: United States
A98: Revenue | B98: SALES_REV_TURN | C98: IS010 | D98: SEG0000306687 Segment | E98: 10839 | F98: 11398 | G98: 13022 | H98: 16642 | I98: 18142 | J98: 15452 | K98: 16323 | L98: 17126 | M98: 18366.506 | N98: 19805.958
A99: Nutrition | B99: SALES_REV_TURN | C99: IS010 | D99: SEG0000306750 Segment | E99: 3075 | F99: 3110 | G99: 3279 | H99: 3556 | I99: 2919 | J99: 3413 | K99: 3689 | L99: 3606 | M99: 3605.4835 | N99: 3703.4379
A100: Organic Growth (%) | B100: IS_ORGANIC_GROWTH_RATE | C100: IS950 | D100: SEG0000306750 Segment | E100: 2.1 | F100: 2.4 | G100: 5.4 | H100: 8.4 | I100: -17.9 | J100: 16.9 | K100: 9.2 | L100: -1.9 | M100: -0.095677989 | N100: 2.8089963
A101: Pediatric | B101: SALES_REV_TURN | C101: IS010 | D101: SEG0000306569 Segment | E101: 1843 | F101: 1879 | G101: 1987 | H101: 2192 | I101: 1562 | J101: 1977 | K101: 2208 | L101: 2158 | M101: 2145.4733 | N101: 2209.001
A102: Organic Growth (%) | B102: IS_ORGANIC_GROWTH_RATE | C102: IS950 | D102: SEG0000306569 Segment | E102: 3.7 | F102: 1.9 | G102: 5.8 | H102: 10.3 | I102: -28.7 | J102: 26.6 | K102: 11.7 | L102: -2.3 | M102: -0.84143623 | N102: 2.8164473
A103: Adult | B103: SALES_REV_TURN | C103: IS010 | D103: SEG0000306732 Segment | E103: 1232 | F103: 1231 | G103: 1292 | H103: 1364 | I103: 1357 | J103: 1436 | K103: 1481 | L103: 1448 | M103: 1462.5991 | N103: 1498.8843
A104: Organic Growth (%) | B104: IS_ORGANIC_GROWTH_RATE | C104: IS950 | D104: SEG0000306732 Segment | E104: -0.3 | F104: 3.2 | G104: 4.9 | H104: 5.6 | I104: -0.5 | J104: 5.8 | K104: 5.8 | L104: -1.4 | M104: 1.0202045 | N104: 2.3652185
A105: Diagnostics | B105: SALES_REV_TURN | C105: IS010 | D105: SEG0000306681 Segment | E105: 2717 | F105: 2887 | G105: 4774 | H105: 7011 | I105: 8531 | J105: 4329 | K105: 3830 | L105: 3552 | M105: 3724.7703 | N105: 3931.3981
A106: Organic Growth (%) | B106: IS_ORGANIC_GROWTH_RATE | C106: IS950 | D106: SEG0000306681 Segment | E106: 3.1 | F106: 6.3 | G106: 65.3 | H106: 49.3 | I106: 21.3 | J106: 1.3 | K106: 6.3 | L106: -7.7 | M106: 6.5967318 | N106: 6.1118498
A107: Core Laboratory | B107: IS_REV_INCLUDING_EX_CRT_ITEMS | C107: IC304 | D107: SEG0000306671 Segment | E107: 985 | F107: 1086 | G107: 1166 | H107: 1145 | I107: 1137 | J107: 1243 | K107: 1332 | L107: 1425 | M107: 1515.7923 | N107: 1611.6266
A108: Organic Growth (%) | B108: IS_ORGANIC_GROWTH_RATE | C108: IS950 | D108: SEG0000306671 Segment | E108: 7 | F108: 10.3 | G108: 7.3 | H108: -1.8 | I108: -0.7 | J108: 10.1 | K108: 7.5 | L108: 7 | M108: 6.5735996 | N108: 6.3977782
...

Sheet BSX
A1: BSX US Equity- Company Financial (Multiple Periods)
A2: BSX US Equity Periodicity:A Currency:USD Estimate Source:BST Actual Source:Bloomberg
A3: In Millions of USD | E3: 2018 A (Rep) | F3: 2019 A (Rep) | G3: 2020 A (Rep) | H3: 2021 A (Rep) | I3: 2022 A (Rep) | J3: 2023 A (Rep) | K3: 2024 A (Rep) | L3: 2025 A (Rep) | M3: 2026 A (Fwd) | N3: 2027 A (Fwd)
A4: 12 Months Ending | B4: Field Expression | C4: Calcrt Field | D4: Segment Id | E4: 43465 | F4: 43830 | G4: 44196 | H4: 44561 | I4: 44926 | J4: 45291 | K4: 45657 | L4: 46022 | M4: 46387 | N4: 46752
A5: Highlights
A6: Adjusted Diluted EPS | B6: IS_COMP_EPS_ADJUSTED_OLD | C6: IS900 | E6: 1.47 | F6: 1.58 | G6: 0.96 | H6: 1.63 | I6: 1.71 | J6: 2.05 | K6: 2.51 | L6: 3.06 | M6: 3.4640625 | N6: 3.9132258
A7: Revenue | B7: IS_COMP_SALES | C7: IS902 | E7: 9823 | F7: 10735 | G7: 9913 | H7: 11888 | I7: 12682 | J7: 14240 | K7: 16747 | L7: 20074 | M7: 22267.344 | N7: 24604.903
A8: Operational Growth (%) | B8: REVENUE_GROWTH_CC_1_YR | C8: M0025 | E8: 8 | F8: 11.1 | G8: -7.8 | H8: 18.7 | I8: 11.1 | J8: 13.1 | K8: 18.5 | L8: 19.2 | M8: 10.207622 | N8: 10.300023
A9: Organic Growth (%) | B9: IS_ORGANIC_GROWTH_RATE | C9: IS950 | E9: 7.2 | F9: 7.3 | G9: -11.3 | H9: 18.9 | I9: 8.7 | J9: 12.3 | K9: 16.4 | L9: 15.8 | M9: 9.9174905 | N9: 10.107342
A11: Segment Revenue
A12: Cardiovascular | B12: SALES_REV_TURN | C12: IS010 | D12: SEG0000267131 Segment | E12: 3777 | F12: 4207 | G12: 3876 | H12: 7242 | I12: 7830 | J12: 8819 | K12: 10754 | L12: 13250 | M12: 14860.227 | N12: 16587.256
A13: Organic Growth (%) | B13: IS_ORGANIC_GROWTH_RATE | C13: IS950 | D13: SEG0000267131 Segment | E13: 6 | F13: 9.3 | G13: -13.1 | H13: 23.9 | I13: 10.1 | J13: 12.9 | K13: 21.9 | L13: 20.8 | M13: 11.909247 | N13: 11.857659
A14: MedSurg | B14: SALES_REV_TURN | C14: IS010 | D14: SEG0000267042 Segment | E14: 3006 | F14: 3307 | G14: 3066 | H14: 4633 | I14: 4911 | J14: 5422 | K14: 5993 | L14: 6825 | M14: 7385.1979 | N14: 7963.1352
A15: Organic Growth (%) | B15: IS_ORGANIC_GROWTH_RATE | C15: IS950 | D15: SEG0000267042 Segment | E15: 8.2 | F15: 8.8 | G15: -6.7 | H15: 19 | I15: 7.7 | J15: 10 | K15: 7.5 | L15: 6.7 | M15: 7.4359268 | N15: 7.3514253
A17: Adjusted Gross Margin (%) | B17: IS_COMP_GROSS_MARGIN_PERCENTAGE | C17: IM092 | E17: 71.373308 | F17: 72.37075 | G17: 67.134066 | H17: 68.783647 | I17: 70.454187 | J17: 70.73736 | K17: 70.317072 | L17: 69.014646 | M17: 70.533501 | N17: 70.713997
A18: Adjusted Operating Margin (%) | B18: CB_IS_ADJ_OPERATING_MARGIN | C18: IM731 | E18: 25.5 | F18: 26.1 | G18: 19.3 | H18: 25.3 | I18: 25.6 | J18: 26.3 | K18: 27 | L18: 28 | M18: 28.452403 | N18: 28.989559
A19: Adjusted Net Income | B19: IS_COMP_NET_INCOME_ADJUST_OLD | C19: IS903 | E19: 2060 | F19: 2234 | G19: 1378 | H19: 2336 | I19: 2459 | J19: 2999 | K19: 3725 | L19: 4574 | M19: 5189.7241 | N19: 5868.1613
A21: Net Debt | B21: HEADLINE_NET_DEBT | C21: F1708 | E21: 6910 | F21: 9791 | G21: 7409 | H21: 7140 | I21: 8007 | J21: 8237 | K21: 10332 | L21: 9471 | M21: 5980.625 | N21: 1968.625
A22: Free Cash Flow | B22: HEADLINE_FCF | C22: F1709 | E22: -5 | F22: 1375 | G22: 1132 | H22: 1316 | I22: 938 | J22: 1792 | K22: 2648 | L22: 3659 | M22: 4076.3913 | N22: 4700.5308
A24: Company Operating Metrics
A26: Company-Level Industry Statistics
A27: Total Revenue Organic Growth (%) | B27: IS_ORGANIC_GROWTH_RATE | C27: IS950 | E27: 7.2 | F27: 7.3 | G27: -11.3 | H27: 18.9 | I27: 8.7 | J27: 12.3 | K27: 16.4 | L27: 15.8 | M27: 9.9174905 | N27: 10.107342
A28: Cardiovascular Organic Growth (%) | B28: IS_ORGANIC_GROWTH_RATE | C28: IS950 | D28: SEG0000267131 Segment | E28: 6 | F28: 9.3 | G28: -13.1 | H28: 23.9 | I28: 10.1 | J28: 12.9 | K28: 21.9 | L28: 20.8 | M28: 11.909247 | N28: 11.857659
A29: MedSurg Organic Growth (%) | B29: IS_ORGANIC_GROWTH_RATE | C29: IS950 | D29: SEG0000267042 Segment | E29: 8.2 | F29: 8.8 | G29: -6.7 | H29: 19 | I29: 7.7 | J29: 10 | K29: 7.5 | L29: 6.7 | M29: 7.4359268 | N29: 7.3514253
A31: Business Breakdown
A32: Medical Devices
A33: Revenue | B33: SALES_REV_TURN | C33: IS010 | D33: SEG0000346235 Segment | E33: 9824 | F33: 10654 | G33: 9694 | H33: 11875 | I33: 12741 | J33: 14241 | K33: 16747 | L33: 20075 | M33: 22235.674 | N33: 24545.802
A34: MedSurg | B34: SALES_REV_TURN | C34: IS010 | D34: SEG0000267042 Segment | E34: 3006 | F34: 3307 | G34: 3066 | H34: 4633 | I34: 4911 | J34: 5422 | K34: 5993 | L34: 6825 | M34: 7385.1979 | N34: 7963.1352
A35: YoY Organic Growth (%) | B35: IS_ORGANIC_GROWTH_RATE | C35: IS950 | D35: SEG0000267042 Segment | E35: 8.2 | F35: 8.8 | G35: -6.7 | H35: 19 | I35: 7.7 | J35: 10 | K35: 7.5 | L35: 6.7 | M35: 7.4359268 | N35: 7.3514253
A36: Endoscopy | B36: SALES_REV_TURN | C36: IS010 | D36: SEG0000267031 Segment | E36: 1761 | F36: 1894 | G36: 1780 | H36: 2141 | I36: 2221 | J36: 2481 | K36: 2687 | L36: 2917 | M36: 3135.6008 | N36: 3375.0235
A37: YoY Organic Growth (%) | B37: IS_ORGANIC_GROWTH_RATE | C37: IS950 | D37: SEG0000267031 Segment | E37: 8.3 | F37: 9.2 | G37: -6.3 | H37: 18.9 | I37: 8.1 | J37: 11.1 | K37: 8 | L37: 7.7 | M37: 6.3128771 | N37: 7.5422355
A38: Urology | B38: SALES_REV_TURN | C38: IS010 | D38: SEG0000266935 Segment | E38: 1245 | F38: 1413 | G38: 1286 | H38: 1583 | I38: 1773 | J38: 1964 | K38: 2200 | L38: 2709 | M38: 2921.4252 | N38: 3144.4124
A39: YoY Organic Growth (%) | B39: IS_ORGANIC_GROWTH_RATE | C39: IS950 | D39: SEG0000266935 Segment | E39: 8.1 | F39: 8.4 | G39: -7.3 | H39: 19.2 | I39: 14.9 | J39: 11.1 | K39: 9.3 | L39: 4.7 | M39: 6.9297166 | N39: 6.9144728
A40: Neuromodulation | B40: SALES_REV_TURN | C40: IS010 | D40: SEG0000267106 Segment | E40: 779 | F40: 873 | G40: 761 | H40: 909 | I40: 917 | J40: 976 | K40: 1106 | L40: 1199 | M40: 1317.1292 | N40: 1423.4384
A41: YoY Organic Growth (%) | B41: IS_ORGANIC_GROWTH_RATE | C41: IS950 | D41: SEG0000267106 Segment | E41: 22.5 | F41: 6.8 | G41: -15.7 | H41: 18.6 | I41: 3.5 | J41: 5.3 | K41: 2.7 | L41: 8 | M41: 7.937659 | N41: 7.2902967
A42: Cardiovascular | B42: SALES_REV_TURN | C42: IS010 | D42: SEG0000267131 Segment | E42: 3777 | F42: 4207 | G42: 3876 | H42: 7242 | I42: 7830 | J42: 8819 | K42: 10754 | L42: 13250 | M42: 14860.227 | N42: 16587.256
A43: YoY Organic Growth (%) | B43: IS_ORGANIC_GROWTH_RATE | C43: IS950 | D43: SEG0000267131 Segment | E43: 6 | F43: 9.3 | G43: -13.1 | H43: 23.9 | I43: 10.1 | J43: 12.9 | K43: 21.9 | L43: 20.8 | M43: 11.909247 | N43: 11.857659
A44: Interventional Cardiology & Vascular Therapies | B44: SALES_REV_TURN | C44: IS010 | D44: SEG1984404819 Segment | J44: 3791 | K44: 4199 | L44: 4639 | M44: 5035.7321 | N44: 5441.1199
A45: YoY Organic Growth (%) | B45: IS_ORGANIC_GROWTH_RATE | C45: IS950 | D45: SEG1984404819 Segment | L45: 9.9 | M45: 6.4 | N45: 5.9
A46: Watchman | B46: SALES_REV_TURN | C46: IS010 | D46: SEG0000674830 Segment | H46: 829 | I46: 1018 | J46: 1274 | K46: 1516 | L46: 1958 | M46: 2379.2218 | N46: 2876.0039
A47: YoY Organic Growth (%) | B47: IS_ORGANIC_GROWTH_RATE | C47: IS950 | D47: SEG0000674830 Segment | I47: 24 | J47: 25.4 | K47: 19.2 | L47: 28.9 | M47: 21.594948 | N47: 21.080414
A48: Electrophysiology | B48: SALES_REV_TURN | C48: IS010 | D48: SEG0000267000 Segment | E48: 311 | F48: 328 | G48: 287 | H48: 365 | I48: 585 | J48: 800 | K48: 1904 | L48: 3325 | M48: 3932.2977 | N48: 4589.3876
A49: YoY Organic Growth (%) | B49: IS_ORGANIC_GROWTH_RATE | C49: IS950 | D49: SEG0000267000 Segment | E49: 10.9 | F49: 7.5 | G49: -13.5 | H49: 23.5 | I49: 68.9 | J49: 32.7 | K49: 139.5 | L49: 73.3 | M49: 17.457074 | N49: 16.238644
A50: Cardiac Rhythm Management | B50: SALES_REV_TURN | C50: IS010 | D50: SEG0000266913 Segment | E50: 1951 | F50: 1939 | G50: 1704 | H50: 2019 | I50: 2100 | J50: 2218 | K50: 2279 | L50: 2332 | M50: 2399.3689 | N50: 2467.4345
A51: YoY Organic Growth (%) | B51: IS_ORGANIC_GROWTH_RATE | C51: IS950 | D51: SEG0000266913 Segment | E51: 2.1 | F51: 1.2 | G51: -12.4 | H51: 7.7 | I51: 8.3 | J51: 5.9 | K51: 3.2 | L51: 1.4 | M51: 2.6539265 | N51: 3.1422996
A52: Interventional Oncology & Embolization | B52: SALES_REV_TURN | C52: IS010 | D52: SEG7317820745 Segment | J52: 736 | K52: 856 | L52: 996 | M52: 1113.4771 | N52: 1226.8618
A53: YoY Organic Growth (%) | B53: IS_ORGANIC_GROWTH_RATE | C53: IS950 | D53: SEG7317820745 Segment | L53: 15.9 | M53: 8.0320959 | N53: 8.7988098
A55: Operational Growth (%)
A56: MedSurg | B56: REVENUE_GROWTH_CC_1_YR | C56: M0025 | D56: SEG0000267042 Segment | E56: 9.3 | F56: 11.5 | G56: -7.5 | H56: 20.2 | I56: 9.5 | J56: 10.8 | K56: 11.1 | L56: 13.3 | M56: 7.9263009 | N56: 7.6476211
A57: Endoscopy | B57: REVENUE_GROWTH_CC_1_YR | C57: M0025 | D57: SEG0000267031 Segment | E57: 8.3 | F57: 9.2 | G57: -6.3 | H57: 18.9 | I57: 8.1 | J57: 12.3 | K57: 8.9 | L57: 7.8 | M57: 7.0326901 | N57: 7.6247346
A58: Urology | B58: REVENUE_GROWTH_CC_1_YR | C58: M0025 | D58: SEG0000266935 Segment | E58: 10.6 | F58: 14.7 | G58: -9 | H58: 22.1 | I58: 14.9 | J58: 11.1 | K58: 12.5 | L58: 22.7 | M58: 7.5485286 | N58: 7.2290332
A59: Neuromodulation | B59: REVENUE_GROWTH_CC_1_YR | C59: M0025 | D59: SEG0000267106 Segment | E59: 22.5 | F59: 13.1 | G59: -13 | H59: 18.6 | I59: 3.5 | J59: 6.7 | K59: 13.7 | L59: 8 | M59: 10.043533 | N59: 7.601124
A60: Cardiovascular | B60: REVENUE_GROWTH_CC_1_YR | C60: M0025 | D60: SEG0000267131 Segment | E60: 7.4 | F60: 13.5 | G60: -7.9 | H60: 23.9 | I60: 13.1 | J60: 13.7 | K60: 23 | L60: 22.5 | M60: 11.893901 | N60: 11.753718
A61: Interventional Cardiology & Vascular Therapies | B61: REVENUE_GROWTH_CC_1_YR | C61: M0025 | D61: SEG1984404819 Segment | L61: 9.9 | M61: 7.8093807 | N61: 7.9929766
A62: Watchman | B62: REVENUE_GROWTH_CC_1_YR | C62: M0025 | D62: SEG0000674830 Segment | I62: 24 | J62: 25.4 | K62: 19.2 | L62: 28.9 | M62: 21.755242 | N62: 21.22564
A63: Electrophysiology | B63: REVENUE_GROWTH_CC_1_YR | C63: M0025 | D63: SEG0000267000 Segment | E63: 10.9 | F63: 7.5 | G63: -13.5 | H63: 25.8 | I63: 68.9 | J63: 37.3 | K63: 139.5 | L63: 73.3 | M63: 16.605654 | N63: 14.84559
A64: Cardiac Rhythm Management | B64: REVENUE_GROWTH_CC_1_YR | C64: M0025 | D64: SEG0000266913 Segment | E64: 2.1 | F64: 1.2 | G64: -12.4 | H64: 17.1 | I64: 8.3 | J64: 5.9 | K64: 3.2 | L64: 1.4 | M64: 2.7738168 | N64: 2.9344057
A65: Interventional Oncology & Embolization | B65: REVENUE_GROWTH_CC_1_YR | C65: M0025 | D65: SEG7317820745 Segment | L65: 15.9 | M65: 13.012216 | N65: 10.024147
A67: Prior Disclosure
A68: Rhythm & Neuro | B68: SALES_REV_TURN | C68: IS010 | D68: SEG0000266912 Segment | E68: 3041 | F68: 3140 | G68: 2752 | H68: 3293
A69: Specialty Pharmaceuticals | B69: SALES_REV_TURN | C69: IS010 | D69: SEG0000335568 Segment | F69: 81 | G69: 219 | H69: 13 | M69: 0 | N69: 0
A70: Interventional Cardiology | B70: SALES_REV_TURN | C70: IS010 | D70: SEG0000266984 Segment | E70: 2590 | F70: 2815 | G70: 2298 | H70: 2209 | I70: 2229 | J70: 2417 | K70: 2644 | M70: 3357.3516 | N70: 3621.8001
A71: YoY Organic Growth (%) | B71: IS_ORGANIC_GROWTH_RATE | C71: IS950 | D71: SEG0000266984 Segment | E71: 4.5 | F71: 10 | G71: -18.2 | H71: 30.7 | I71: 7.5 | J71: 10.4 | K71: 11.4 | M71: 6.4377622 | N71: 7.331622
A72: Cardiology | B72: SALES_REV_TURN | C72: IS010 | D72: SEG0000752875 Segment | H72: 5422 | I72: 5932 | J72: 6709 | K72: 8344 | L72: 13250 | M72: 12535.85 | N72: 14092.169
A73: YoY Organic Growth (%) | B73: IS_ORGANIC_GROWTH_RATE | C73: IS950 | D73: SEG0000752875 Segment | I73: 10.4 | J73: 13.6 | K73: 25.4 | M73: 15.472174 | N73: 12.617252
A74: Peripheral Interventions | B74: SALES_REV_TURN | C74: IS010 | D74: SEG0000267082 Segment | E74: 1187 | F74: 1392 | G74: 1577 | H74: 1820 | I74: 1898 | J74: 2110 | K74: 2410 | M74: 2738.5103 | N74: 2982.7135
A75: YoY Organic Growth (%) | B75: IS_ORGANIC_GROWTH_RATE | C75: IS950 | D75: SEG0000267082 Segment | E75: 9.2 | F75: 7.8 | G75: -2.5 | H75: 14.2 | I75: 9.1 | J75: 10.9 | K75: 10.9
A77: Regional Breakdown
A78: United States
A79: Revenue | B79: SALES_REV_TURN | C79: IS010 | D79: SEG0000267039 Segment | E79: 5538 | F79: 6097 | G79: 5508 | H79: 6901 | I79: 7632 | J79: 8425 | K79: 10210 | L79: 12864 | M79: 14262.03 | N79: 15860.264
A80: Endoscopy | B80: SALES_REV_TURN | C80: IS010 | D80: SEG0000266920 Segment | E80: 980 | F80: 1080 | G80: 1000 | H80: 1222 | I80: 1341 | J80: 1511 | K80: 1651 | L80: 1802 | M80: 1932.1829 | N80: 2090.0368
A81: Urology | B81: SALES_REV_TURN | C81: IS010 | D81: SEG0000266953 Segment | E81: 864 | F81: 1005 | G81: 918 | H81: 1120 | I81: 1257 | J81: 1369 | K81: 1557 | L81: 2000 | M81: 2162.3933 | N81: 2346.0697
A82: Neuromodulation | B82: SALES_REV_TURN | C82: IS010 | D82: SEG0000267050 Segment | E82: 624 | F82: 695 | G82: 610 | H82: 713 | I82: 715 | J82: 736 | K82: 847 | L82: 914 | M82: 1019.8267 | N82: 1107.2884
A83: Interventional Cardiology & Vascular Therapies | B83: SALES_REV_TURN | C83: IS010 | D83: SEG9762210123 Segment | J83: 1436 | K83: 1607 | L83: 2007 | M83: 2290.9843 | N83: 2552.5088
A84: Watchman | B84: SALES_REV_TURN | C84: IS010 | D84: SEG0000674832 Segment | H84: 729 | I84: 915 | J84: 1155 | K84: 1371 | L84: 1791 | M84: 2174.4859 | N84: 2646.8994
A85: Cardiac Rhythm Management | B85: SALES_REV_TURN | C85: IS010 | D85: SEG0000266954 Segment | E85: 1159 | F85: 1135 | G85: 992 | H85: 1214 | I85: 1337 | J85: 1405 | K85: 1403 | L85: 1425 | M85: 1481.5002 | N85: 1532.7098
A86: Electrophysiology | B86: SALES_REV_TURN | C86: IS010 | D86: SEG0000266957 Segment | E86: 150 | F86: 148 | G86: 118 | H86: 128 | I86: 275 | J86: 370 | K86: 1256 | L86: 2311 | M86: 2612.0028 | N86: 2983.0255
A87: Interventional Oncology & Embolization | B87: SALES_REV_TURN | C87: IS010 | D87: SEG2206723404 Segment | J87: 442 | K87: 518 | L87: 615 | M87: 691.2584 | N87: 762.25403
A89: International
A90: Revenue | B90: SALES_REV_TURN | C90: IS010 | D90: SEG0000267062 Segment | E90: 4286 | F90: 4557 | G90: 4185 | H90: 4974 | I90: 5111 | J90: 5816 | K90: 6538 | L90: 7209 | M90: 7907.4138 | N90: 8603.6062
A91: Endoscopy | B91: SALES_REV_TURN | C91: IS010 | D91: SEG0000266927 Segment | E91: 781 | F91: 814 | G91: 780 | H91: 919 | I91: 880 | J91: 970 | K91: 1036 | L91: 1115 | M91: 1208.8705 | N91: 1292.7225
A92: Urology | B92: SALES_REV_TURN | C92: IS010 | D92: SEG0000267095 Segment | E92: 381 | F92: 408 | G92: 368 | H92: 463 | I92: 516 | J92: 595 | K92: 643 | L92: 709 | M92: 768.94837 | N92: 825.00952
A93: Neuromodulation | B93: SALES_REV_TURN | C93: IS010 | D93: SEG0000267035 Segment | E93: 155 | F93: 178 | G93: 151 | H93: 196 | I93: 202 | J93: 240 | K93: 259 | L93: 285 | M93: 308.58968 | N93: 331.07991
A94: Interventional Cardiology & Vascular Therapies | B94: SALES_REV_TURN | C94: IS010 | D94: SEG8540015434 Segment | J94: 2355 | K94: 2592 | L94: 2632
A95: Watchman | B95: SALES_REV_TURN | C95: IS010 | D95: SEG0000674831 Segment | H95: 100 | I95: 103 | J95: 119 | K95: 145 | L95: 167 | M95: 199.92947 | N95: 237.12143
A96: Cardiac Rhythm Management | B96: SALES_REV_TURN | C96: IS010 | D96: SEG0000266932 Segment | E96: 792 | F96: 804 | G96: 712 | H96: 805 | I96: 763 | J96: 813 | K96: 876 | L96: 907 | M96: 945.88612 | N96: 974.72653
A97: Electrophysiology | B97: SALES_REV_TURN | C97: IS010 | D97: SEG0000267022 Segment | E97: 161 | F97: 180 | G97: 169 | H97: 237 | I97: 310 | J97: 430 | K97: 648 | L97: 1014 | M97: 1285.32 | N97: 1542.7843
A98: Interventional Oncology & Embolization | B98: SALES_REV_TURN | C98: IS010 | D98: SEG9984528708 Segment | J98: 294 | K98: 338 | L98: 381 | M98: 426.66208 | N98: 462.91579
A100: Income Statement (Adjusted)
A101: Revenue | B101: IS_COMP_SALES | C101: IS902 | E101: 9823 | F101: 10735 | G101: 9913 | H101: 11888 | I101: 12682 | J101: 14240 | K101: 16747 | L101: 20074 | M101: 22267.344 | N101: 24604.903
A103: Cost of Revenue | B103: IS_ADJUSTED_COGS_AS_REPORTED | C103: IM057 | E103: 2724 | F103: 2966 | G103: 3258 | H103: 3535 | I103: 3747 | J103: 4167 | K103: 4972 | L103: 5899 | M103: 6532.5364 | N103: 7173.1898
A105: Gross Profit | B105: IS_ADJ_GROSS_PROFIT_AS_REPORTED | C105: IS923 | E105: 7099 | F105: 7769 | G105: 6655 | H105: 8353 | I105: 8935 | J105: 10073 | K105: 11776 | L105: 14175 | M105: 15740.267 | N105: 17439.891
A106: Gross Margin (%) | B106: IS_COMP_GROSS_MARGIN_PERCENTAGE | C106: IM092 | E106: 71.373308 | F106: 72.37075 | G106: 67.134066 | H106: 68.783647 | I106: 70.454187 | J106: 70.73736 | K106: 70.317072 | L106: 69.014646 | M106: 70.533501 | N106: 70.713997
A108: Total Operating Expenses | B108: CB_IS_ADJUSTED_OPEX | C108: IM744 | E108: 4526 | F108: 4970 | G108: 4738 | H108: 0 | I108: 5694 | J108: 6335 | K108: 7246 | L108: 8563 | M108: 9358.0528 | N108: 10242.581
A109: Selling, General & Administrative | B109: IS_ADJ_SG_AND_A_AS_REPORTED | C109: IS926 | E109: 3474 | F109: 3766 | G109: 3646 | H109: 4149 | I109: 4387 | J109: 4945 | K109: 5686 | L109: 6602 | M109: 7223.689 | N109: 7932.2277
A110: As % of Revenue | B110: ADJ_SG_AND_A_TO_SALES | C110: RX613 | E110: 35.365978 | F110: 35.081509 | G110: 36.779986 | H110: 34.90074 | I110: 34.592336 | J110: 34.726124 | K110: 33.95235 | L110: 32.888313 | M110: 32.581014 | N110: 32.268516
A111: Research & Development | B111: IS_ADJ_R_AND_D_AS_REPORTED | C111: IS925 | E111: 1052 | F111: 1138 | G111: 1046 | H111: 1145 | I111: 1260 | J111: 1344 | K111: 1527 | L111: 1914 | M111: 2099.0847 | N111: 2307.6904
A112: As % of Revenue | B112: ADJ_R_AND_D_TO_SALES | C112: RX612 | E112: 10.709559 | F112: 10.600838 | G112: 10.551801 | H112: 9.6315612 | I112: 9.9353414 | J112: 9.4382022 | K112: 9.118051 | L112: 9.5347215 | M112: 9.4485495 | N112: 9.4132531
A113: Royalty | B113: CB_IS_ROYALTIES_EXP | C113: IC331 | E113: 71 | F113: 65 | G113: 45 | H113: 49 | I113: 47 | J113: 46 | K113: 33 | L113: 46 | M113: 40.635616 | N113: 42.179893
A114: Intangible Asset Impairment Charges | B114: CB_IS_IMPAIRMENT_INTANGIBLE_ASSETS | C114: IL487 | E114: 35 | F114: 105 | G114: 460 | H114: 370 | I114: 132 | J114: 58 | K114: 386 | L114: 46 | M114: 0 | N114: 0
...

Sheet EDW
A1: EW US Equity- Company Financial (Multiple Periods)
A2: EW US Equity Periodicity:A Currency:USD Estimate Source:BST Actual Source:Bloomberg
A3: In Millions of USD | E3: 2018 A (Rep) | F3: 2019 A (Rep) | G3: 2020 A (Rep) | H3: 2021 A (Rep) | I3: 2022 A (Rep) | J3: 2023 A (Rep) | K3: 2024 A (Rep) | L3: 2025 A (Rep) | M3: 2026 A (Fwd) | N3: 2027 A (Fwd)
A4: 12 Months Ending | B4: Field Expression | C4: Calcrt Field | D4: Segment Id | E4: 43465 | F4: 43830 | G4: 44196 | H4: 44561 | I4: 44926 | J4: 45291 | K4: 45657 | L4: 46022 | M4: 46387 | N4: 46752
A5: Highlights
A6: Adjusted Diluted EPS | B6: IS_COMP_EPS_ADJUSTED_OLD | C6: IS900 | E6: 1.5666667 | F6: 1.8566667 | G6: 1.86 | H6: 2.22 | I6: 2.48 | J6: 2.51 | K6: 2.43 | L6: 2.56 | M6: 2.962 | N6: 3.3203448
A7: Revenue | B7: IS_COMP_SALES | C7: IS902 | E7: 3813.3 | F7: 4348 | G7: 4386.3 | H7: 5232.5 | I7: 5382.4 | J7: 6004.8 | K7: 5439.5 | L7: 6067.6 | M7: 6677.1333 | N7: 7328.2333
A9: Organic Growth (%) | B9: IS_ORGANIC_GROWTH_RATE | C9: IS950 | E9: 10 | F9: 15.3 | G9: 0.6 | H9: 17.8 | I9: 7.7 | J9: 12.1 | K9: 8.9 | L9: 10.7 | M9: 9.4872493 | N9: 9.7081572
A11: Segment Revenue
A12: Transcatheter Aortic Valve Replacement | B12: SALES_REV_TURN | C12: IS010 | D12: SEG0000291598 Segment | E12: 2283.8 | F12: 2737.9 | G12: 2857.3 | H12: 3422.5 | I12: 3518.2 | J12: 3879.8 | K12: 4106.1 | L12: 4487.7 | M12: 4833.1669 | N12: 5175.0951
A13: Transcatheter Mitral & Tricuspid Therapies | B13: SALES_REV_TURN | C13: IS010 | D13: SEG0000291600 Segment | E13: 2.9 | F13: 28.2 | G13: 41.8 | H13: 86 | I13: 116.1 | J13: 197.6 | K13: 352.1 | L13: 550.6 | M13: 758.16057 | N13: 1016.3783
A14: Surgical Structural Heart | B14: SALES_REV_TURN | C14: IS010 | D14: SEG0000280744 Segment | E14: 761.6 | F14: 841.7 | G14: 761.8 | H14: 889.1 | I14: 893.1 | J14: 932.6 | K14: 981.3 | L14: 1029.3 | M14: 1079.0689 | N14: 1123.0594
A16: Divested Segment Revenue
A17: Critical Care | B17: SALES_REV_TURN | C17: IS010 | D17: SEG0000280745 Segment | E17: 674.5 | F17: 740.2 | G17: 725.4 | H17: 834.9 | I17: 855 | J17: 928.1 | M17: 281.89326 | N17: 298.80686
A19: Adjusted Gross Margin (%) | B19: IS_ADJ_GROSS_MARGIN_PCT_AR | C19: IM058 | E19: 75.1 | F19: 76.2 | G19: 75.5 | H19: 76.3 | I19: 80.1 | J19: 80.5 | K19: 79.5 | L19: 78.1 | M19: 78.444265 | N19: 78.62116
A20: Adjusted Operating Margin (%) | B20: ADJ_OPERATING_MARGIN | C20: RX609 | E20: 30.990115 | F20: 30.275989 | G20: 30.139297 | H20: 30.473005 | I20: 33.377304 | J20: 29.692615 | K20: 27.842633 | L20: 27.086492 | M20: 28.756033 | N20: 29.283617
A22: Long-Term Debt | B22: BS_LONG_TERM_BORROWINGS | C22: BM286 | E22: 593.8 | F22: 594.4 | G22: 595 | H22: 595.7 | I22: 596.3 | J22: 597 | K22: 597.7 | L22: 598.3 | M22: 597.85 | N22: 597.85
A23: Free Cash Flow | B23: CF_FREE_CASH_FLOW | C23: RR008 | E23: 688.1 | F23: 928.5 | G23: 647 | H23: 1406.3 | I23: 973.6 | J23: 642.8 | K23: 289.9 | L23: 1335 | M23: 1487.988 | N23: 1653.7376
A25: Company Operating Metrics
A27: Company-Level Industry Statistics
A28: Constant Currency Growth (%) | B28: IS_ORGANIC_GROWTH_RATE | C28: IS950 | E28: 10 | F28: 15.3 | G28: 0.6 | H28: 17.8 | I28: 7.7 | J28: 12.1 | K28: 8.9 | L28: 10.7 | M28: 9.4872493 | N28: 9.7081572
A29: Transcatheter Aortic Valve Replacement | B29: IS_ORGANIC_REV_GRWTH_N_GAAP_PCT | C29: IC390 | D29: SEG0000291598 Segment | F29: 21.2 | G29: 4.2 | H29: 18.4 | I29: 7.2 | J29: 10.6 | K29: 6.2 | L29: 8.6 | M29: 7.155794 | N29: 7.0103627
A30: Transcatheter Mitral & Tricuspid Therapy | B30: IS_ORGANIC_REV_GRWTH_N_GAAP_PCT | C30: IC390 | D30: SEG0000291600 Segment | G30: 46.2 | H30: 99.7 | I30: 47.6 | J30: 66.8 | K30: 76.9 | L30: 53.1 | M30: 37.457948 | N30: 34.137443
A31: Surgical Structural Heart | B31: IS_ORGANIC_REV_GRWTH_N_GAAP_PCT | C31: IC390 | D31: SEG0000280744 Segment | E31: 3.4 | F31: 1.5 | G31: -9.6 | H31: 14.8 | I31: 6 | J31: 12.7 | K31: 5.8 | L31: 4.3 | M31: 4.3107183 | N31: 4.3959008
A33: Sales Change Currencies
A34: Transcatheter Aortic Valve Replacement | B34: IS_SALES_CHANGE_CRNCY_IMPACT | C34: IM116 | D34: SEG0000291598 Segment | F34: -32.7 | G34: 5 | H34: 33.9 | I34: -140.2 | J34: -11.3 | K34: -13.6 | L34: 26.7 | M34: 27.055442 | N34: -1.6666667
A35: Transcatheter Mitral & Triscuspid Therapies | B35: IS_SALES_CHANGE_CRNCY_IMPACT | C35: IM116 | D35: SEG0000291600 Segment | F35: -0.1 | G35: 0.4 | H35: 1.3 | I35: -7.4 | J35: 2.4 | K35: 1.5 | L35: 5.8 | M35: 5.1613931 | N35: 0
A36: Surgical Structural Heart | B36: IS_SALES_CHANGE_CRNCY_IMPACT | C36: IM116 | D36: SEG0000280744 Segment | E36: 9.2 | F36: -14.5 | G36: 1 | H36: 13.1 | I36: -46.5 | J36: -6.4 | K36: -5.1 | L36: 5.9 | M36: 7.7047677 | N36: 0
A38: Sales Change Currencies
A39: International | B39: IS_SALES_CHANGE_CRNCY_IMPACT | C39: IM116 | D39: SEG0000280749 Segment | E39: 34.3 | F39: -56.4 | G39: 4.9 | H39: 57.3 | I39: -233.6 | J39: -25.6 | K39: -17.2 | L39: 38.4 | M39: 40.490258 | N39: -1.3924714
A40: Europe | B40: IS_SALES_CHANGE_CRNCY_IMPACT | C40: IM116 | D40: SEG0000280752 Segment | E40: 32.9 | F40: -44.8 | G40: 9.4 | H40: 48.9 | I40: -126.4 | J40: 23 | K40: 16 | L40: 44.6
A41: Japan | B41: IS_SALES_CHANGE_CRNCY_IMPACT | C41: IM116 | D41: SEG0000280748 Segment | E41: 4.3 | F41: 4.5 | G41: 8.1 | H41: -10.9 | I41: -81.8 | J41: -34 | K41: -26.3 | L41: 3.2
A42: Rest of World | B42: IS_SALES_CHANGE_CRNCY_IMPACT | C42: IM116 | D42: SEG0000280739 Segment | E42: -2.9 | F42: -16.1 | G42: -12.6 | H42: 19.3 | I42: -25.4 | J42: -14.6 | K42: -6.9 | L42: -9.4
A44: Business Breakdown
A45: Transcatheter Heart Valves
A46: Revenue | B46: SALES_REV_TURN | C46: IS010 | D46: SEG0000280733 Segment | E46: 2286.7 | F46: 2766.1 | G46: 2899.1 | H46: 3508.5 | I46: 3634.3 | J46: 4077.4 | K46: 4458.2 | L46: 5038.3 | M46: 5587.1735 | N46: 6211.0952
A47: Transcatheter Aortic Valve Replacement | B47: SALES_REV_TURN | C47: IS010 | D47: SEG0000291598 Segment | E47: 2283.8 | F47: 2737.9 | G47: 2857.3 | H47: 3422.5 | I47: 3518.2 | J47: 3879.8 | K47: 4106.1 | L47: 4487.7 | M47: 4833.1669 | N47: 5175.0951
A48: Transcatheter Mitral & Tricuspid Therapies | B48: SALES_REV_TURN | C48: IS010 | D48: SEG0000291600 Segment | E48: 2.9 | F48: 28.2 | G48: 41.8 | H48: 86 | I48: 116.1 | J48: 197.6 | K48: 352.1 | L48: 550.6 | M48: 758.16057 | N48: 1016.3783
A50: Surgical Structural Heart
A51: Revenue | B51: SALES_REV_TURN | C51: IS010 | D51: SEG0000280744 Segment | E51: 761.6 | F51: 841.7 | G51: 761.8 | H51: 889.1 | I51: 893.1 | J51: 932.6 | K51: 981.3 | L51: 1029.3 | M51: 1079.0689 | N51: 1123.0594
A53: Prior Disclosure
A54: Critical Care
A55: Revenue | B55: SALES_REV_TURN | C55: IS010 | D55: SEG0000280745 Segment | E55: 674.5 | F55: 740.2 | G55: 725.4 | H55: 834.9 | I55: 855 | J55: 928.1 | M55: 281.89326 | N55: 298.80686
A57: Regional Breakdown
A58: Revenue | B58: IS_COMP_SALES | C58: IS902 | E58: 3813.3 | F58: 4348 | G58: 4386.3 | H58: 5232.5 | I58: 5382.4 | J58: 6004.8 | K58: 5439.5 | L58: 6067.6 | M58: 6677.1333 | N58: 7328.2333
A59: United States | B59: SALES_REV_TURN | C59: IS010 | D59: SEG0000280734 Segment | E59: 2055.3 | F59: 2532.7 | G59: 2516.8 | H59: 2963.1 | I59: 3132.6 | J59: 2947.9 | K59: 3206 | L59: 3543.1 | M59: 3891.6969 | N59: 4243.5979
A60: International | B60: SALES_REV_TURN | C60: IS010 | D60: SEG0000280749 Segment | E60: 1667.5 | F60: 1815.3 | G60: 1869.5 | H60: 2269.4 | I60: 2249.8 | J60: 2062.1 | K60: 2233.5 | L60: 2524.5 | M60: 2777.9161 | N60: 3058.2446
A61: Europe | B61: SALES_REV_TURN | C61: IS010 | D61: SEG0000280752 Segment | E61: 885.1 | F61: 941.2 | G61: 973.6 | H61: 1190.3 | I61: 1174.8 | J61: 1180.2 | K61: 1321.7 | L61: 1517.5 | M61: 1579.3673 | N61: 1695.753
A62: Japan | B62: SALES_REV_TURN | C62: IS010 | D62: SEG0000280748 Segment | E62: 396.8 | F62: 444.7 | G62: 460.1 | H62: 528.9 | I62: 473.6 | J62: 350.8 | K62: 339.8 | L62: 354.7 | M62: 433.30746 | N62: 518.6225
A63: Rest of the World | B63: SALES_REV_TURN | C63: IS010 | D63: SEG0000280739 Segment | E63: 385.6 | F63: 429.4 | G63: 435.8 | H63: 550.2 | I63: 601.4 | J63: 531.1 | K63: 572 | L63: 652.3 | M63: 726.14078 | N63: 811.44973
A65: Income Statement (Adjusted)
A66: Total Revenue | B66: IS_COMP_SALES | C66: IS902 | E66: 3813.3 | F66: 4348 | G66: 4386.3 | H66: 5232.5 | I66: 5382.4 | J66: 6004.8 | K66: 5439.5 | L66: 6067.6 | M66: 6677.1333 | N66: 7328.2333
A68: Cost of Revenue | B68: IS_COGS_TO_FE_AND_PP_AND_G | C68: IS021 | E68: 939.4 | F68: 1114.4 | G68: 1080.6 | H68: 1248.9 | I68: 1080.4 | J68: 978.4 | K68: 1117.5 | L68: 1334.2 | M68: 1439.1929 | N68: 1566.0596
A69: As % of Revenue | B69: COGS_TO_NET_SALES | C69: RR279 | E69: 25.233695 | F69: 25.630175 | G69: 24.635798 | H69: 23.868132 | I69: 20.07283 | J69: 19.528942 | K69: 20.544168 | L69: 21.988925 | M69: 21.58799 | N69: 21.384244
A70: Gross Profit | B70: IS_ADJ_GROSS_PROFIT_AS_REPORTED | C70: IS923 | E70: 2863.79 | F70: 3313.18 | G70: 3311.6565 | H70: 3992.3975 | I70: 4311.3024 | J70: 4033.05 | K70: 4324.4025 | L70: 4738.7956 | M70: 5233.3802 | N70: 5754.5864
A71: Gross Margin (%) | B71: IS_ADJ_GROSS_MARGIN_PCT_AR | C71: IM058 | E71: 75.1 | F71: 76.2 | G71: 75.5 | H71: 76.3 | I71: 80.1 | J71: 80.5 | K71: 79.5 | L71: 78.1 | M71: 78.444265 | N71: 78.62116
A73: Selling, General & Administrative | B73: IS_ADJ_SG_AND_A_AS_REPORTED | C73: IS926 | E73: 1088.5 | F73: 1242.2 | G73: 1228.4 | H73: 1493.7 | I73: 1567.6 | J73: 1582.5 | K73: 1789.2 | L73: 2085.2 | M73: 2187.1604 | N73: 2366.596
A74: As % of Revenue | B74: SGA_AS_PCT_TOTAL_SALES | C74: F1010 | E74: 29.238745 | F74: 28.569457 | G74: 28.00538 | H74: 28.546584 | I74: 29.124554 | J74: 31.586826 | K74: 32.892729 | L74: 34.366141 | M74: 32.752651 | N74: 32.293093
A75: Research & Development | B75: IS_ADJ_R_AND_D_AS_REPORTED | C75: IS925 | E75: 624.3755 | F75: 752.7 | G75: 760.7 | H75: 903.1 | I75: 945.2 | J75: 962.9 | K75: 1053 | L75: 1079.2 | M75: 1144.1985 | N75: 1245.1911
A76: As % of Revenue | B76: RD_EXPEND_TO_NET_SALES | C76: RR295 | E76: 16.713227 | F76: 17.311408 | G76: 17.342635 | H76: 17.259436 | I76: 17.560939 | J76: 19.219561 | K76: 19.358397 | L76: 17.786275 | M76: 17.158521 | N76: 17.033273
A77: Merger & Acquisition | B77: CB_IS_MERGER_ACQUISITION_EXP | C77: IL482 | E77: -5.7 | F77: -6.1 | G77: 13.6 | H77: -124.1 | I77: -35.8 | J77: -26.2 | K77: 0 | L77: -12.5 | M77: 0 | N77: 0
A79: Operating Income | B79: IS_COMPARABLE_EBIT | C79: IM132 | E79: 1153.7 | F79: 1316.4 | G79: 1322 | H79: 1594.5 | I79: 1796.5 | J79: 1733.8 | K79: 1514.5 | L79: 1643.5 | M79: 1915.7241 | N79: 2152.5333
A80: Operating Margin (%) | B80: ADJ_OPERATING_MARGIN | C80: RX609 | E80: 30.990115 | F80: 30.275989 | G80: 30.139297 | H80: 30.473005 | I80: 33.377304 | J80: 29.692615 | K80: 27.842633 | L80: 27.086492 | M80: 28.756033 | N80: 29.283617
... A102: Diluted EPS | B102: IS_COMP_EPS_ADJUSTED_OLD | C102: IS900 | E102: 1.5666667 | F102: 1.8566667 | G102: 1.86 | H102: 2.22 | I102: 2.48 | J102: 2.51 | K102: 2.43 | L102: 2.56 | M102: 2.962 | N102: 3.3203448
A104: Dividend per Share | B104: IS_REGULAR_CASH_DIVIDEND_PER_SH | C104: IM303 | E104: 0 | F104: 0 | G104: 0 | H104: 0 | I104: 0 | J104: 0 | K104: 0 | L104: 0
A106: GAAP Results
A107: Total Revenue | B107: SALES_REV_TURN | C107: IS010 | E107: 3722.8 | F107: 4348 | G107: 4386.3 | H107: 5232.5 | I107: 5382.4 | J107: 5010 | K107: 5439.5 | L107: 6067.6
A108: Total Operating Expenses | B108: IS_OPERATING_EXPN | C108: IS032 | E108: 2035.2 | F108: 2086.8 | G108: 2408.1 | H108: 2293.3 | I108: 2553.5 | J108: 2722.7 | K108: 2943.3 | L108: 3469.2 | M108: 3323.9054 | N108: 3608.5808
A109: Operating Income | B109: IS_OPER_INC | C109: IS033 | E109: 748.2 | F109: 1146.8 | G109: 897.6 | H109: 1690.3 | I109: 1748.5 | J109: 1308.9 | K109: 1378.7 | L109: 1264.2 | M109: 1852.9848 | N109: 2092.7506
A110: Operating Margin (%) | B110: OPER_MARGIN | C110: RR026 | E110: 20.097776 | F110: 26.375345 | G110: 20.463717 | H110: 32.30387 | I110: 32.485508 | J110: 26.125749 | K110: 25.34608 | L110: 20.835256 | M110: 27.202916 | N110: 27.4
A111: Non-Operating (Income) Loss | B111: IS_NON_OPERATING_INC_LOSS_GAAP | C111: IM437 | E111: -13.2 | F111: -19.7 | G111: -19.1 | H111: -11.7 | I111: -18.9 | J111: -63.5 | K111: -169.4 | L111: -8.7 | M111: -160.2413 | N111: -155.56728
A112: Tax Rate (%) | B112: CB_IS_ETR_PCT | C112: IM790 | E112: 5.1 | F112: 10.3 | G112: 10.2 | H112: 11.7 | I112: 13.9 | J112: 11.1 | K112: 9.8 | L112: 17 | M112: 17.225 | N112: 16.25
A113: Income Tax Expense | B113: IS_INC_TAX_EXP | C113: IS038 | E113: 39.2 | F113: 119.6 | G113: 93.3 | H113: 198.9 | I113: 245.5 | J113: 152.4 | K113: 152.1 | L113: 216.9 | M113: 337.13684 | N113: 367.35158
A114: Net Income | B114: IS_COMP_NET_INCOME_GAAP | C114: IS904 | E114: 722.2 | F114: 1046.9 | G114: 823.4 | H114: 1503.1 | I114: 1521.9 | J114: 1399.4 | K114: 4169.7 | L114: 1069.4 | M114: 1688 | N114: 1817.4783
A115: Diluted EPS | B115: IS_COMP_EPS_GAAP | C115: IS901 | E115: 1.1266667 | F115: 1.6433333 | G115: 1.3 | H115: 2.38 | I115: 2.44 | J115: 2.3 | K115: 6.97 | L115: 1.83 | M115: 2.8147368 | N115: 3.1494444
A117: Company-Specific Adjustments
A118: Legal Settlement | B118: CB_IS_LEGAL_SETTLE_PRETAX_NONGAAP_RECON | C118: IM567 | E118: 214 | F118: 33.4 | G118: 405.4 | H118: 20.6 | I118: 15.8 | J118: 203.5 | K118: 40.4 | L118: 325.4 | M118: 42.666667 | N118: 34.333333
A119: Adjustments | B119: IS_ADJUSTMENT_FACE | C119: IM371 | E119: 324.5 | F119: 91.9 | G119: 419 | H119: -103.5 | I119: 40.7 | J119: 177.3 | K119: 101.4 | L119: 332 | M119: 60.127399 | N119: 71.268005
A121: Condensed Balance Sheet
A122: Assets
A123: Current Assets | B123: BS_CUR_ASSET_REPORT | C123: BS015 | E123: 2286.9 | F123: 2984 | G123: 3091 | H123: 3180.7 | I123: 3095.8 | J123: 4035.7 | K123: 6285.4 | L123: 6738.9 | M123: 7352.7696 | N123: 8580.3823
A124: Cash, Cash Equivalents & Short-Term Investments | B124: BS_CASH_CASH_EQUIVALENTS_AND_STI | C124: BM289 | E124: 956.5 | F124: 1516.9 | G124: 1402.6 | H124: 1466.8 | I124: 1215.3 | J124: 1632.8 | K124: 3975.9 | L124: 4226.3 | M124: 4998.0841 | N124: 6252.2977
A125: Cash & Cash Equivalents | B125: BS_CASH_NEAR_CASH_ITEM | C125: BS010 | E125: 714.1 | F125: 1179.1 | G125: 1183.2 | H125: 862.8 | I125: 769 | J125: 1132.3 | K125: 3045.2 | L125: 2938 | M125: 3541.6949 | N125: 4521.8274
A126: Accounts Receivable | B126: CB_BS_ACCOUNTS_RECEIVABLE | C126: BL309 | E126: 456.9 | F126: 543.6 | G126: 514.6 | H126: 582.2 | I126: 643 | J126: 771.5 | K126: 609.1 | L126: 659.6 | M126: 898.40357 | N126: 985.03837
A127: Inventories | B127: BS_INVENTORIES | C127: BS013 | E127: 607 | F127: 640.9 | G127: 802.3 | H127: 726.7 | I127: 875.5 | J127: 903.5 | K127: 1086.7 | L127: 1126.2 | M127: 1250.3032 | N127: 1356.1103
A128: Short-Term Investments | B128: BS_MKT_SEC_OTHER_ST_INVEST | C128: BS011 | E128: 242.4 | F128: 337.8 | G128: 219.4 | H128: 604 | I128: 446.3 | J128: 500.5 | K128: 930.7 | L128: 1288.3 | M128: 1091.9143 | N128: 1091.9143
A129: Prepaid Expenses & Other Current Assets | B129: OTHER_CURRENT_ASSETS_DETAILED | C129: F1201 | E129: 266.5 | F129: 282.6 | G129: 379.6 | H129: 405 | I129: 362 | J129: 727.9 | K129: 613.7 | L129: 726.8 | M129: 588.50481 | N129: 627.43728
A130: Prepaid Expenses | B130: BS_PREPAY | C130: BS119 | E130: 54.3 | F130: 59.1 | G130: 75.1 | H130: 85.2 | I130: 110 | J130: 128.8 | K130: 121 | L130: 135 | M130: 137.31618 | N130: 134.57103
A131: Other Current Assets | B131: CB_BS_OTHER_CURRENT_ASSETS | C131: BM783 | E131: 131.8 | F131: 168 | G131: 208.2 | H131: 237.1 | I131: 195.9 | J131: 224.9 | K131: 347.6 | L131: 339.3 | M131: 351.93333 | N131: 355.90646
A132: Non-Current Assets | B132: BS_TOTAL_NON_CURRENT_ASSETS | C132: BM321 | E132: 3036.8 | F132: 3504.1 | G132: 4146.1 | H132: 5321.9 | I132: 5196.7 | J132: 5327.5 | K132: 6769.9 | L132: 6958.3 | M132: 7089.5393 | N132: 7204.5783
A133: Property, Plant & Equipment | B133: CB_BS_PP_AND_E_NET | C133: BM788 | E133: 867.5 | F133: 1060.3 | G133: 1395.2 | H133: 1546.6 | I133: 1632.8 | J133: 1591 | K133: 1686 | L133: 1811.9 | M133: 1931.1041 | N133: 2069.4107
A134: Operating Lease Assets | B134: BS_OPER_LEA_RT_OF_USE_ASSETS | C134: BM659 | E134: 0 | F134: 80.1 | G134: 94.2 | H134: 92.1 | I134: 92.3 | J134: 84.4 | K134: 98.2 | L134: 102.7 | M134: 99.133333 | N134: 98.475
... A141: Total Assets | B141: BS_TOT_ASSET | C141: BS035 | E141: 5323.7 | F141: 6488.1 | G141: 7237.1 | H141: 8502.6 | I141: 8292.5 | J141: 9363.2 | K141: 13055.3 | L141: 13697.2 | M141: 14483.407 | N141: 15873.124
A143: Liabilities & Equity
A144: Current Liabilities | B144: BS_CUR_LIAB | C144: BS050 | E144: 876.6 | F144: 902.4 | G144: 893.9 | H144: 1032.3 | I144: 1022.4 | J144: 1195.4 | K144: 1505.2 | L144: 1813.7 | M144: 1469.3411 | N144: 1549.9056
A145: Accounts Payable | B145: BS_ACCT_PAYABLE | C145: BS036 | E145: 134 | F145: 180.4 | G145: 196.5 | H145: 204.5 | I145: 201.9 | J145: 186.6 | K145: 197.4 | L145: 227.5 | M145: 204.47678 | N145: 217.61131
A146: Accounts Payable & Accrued Liabilities | B146: CB_BS_ACCT_PYBL_ACC_EXPNSS | C146: BL248 | E146: 876.6 | F146: 696.5 | G146: 866.7 | H146: 802.3 | I146: 795 | J146: 856.4 | K146: 1282.4 | L146: 1561.7 | M146: 1280.8908 | N146: 1313.3565
A147: Other Current Liabilities | B147: BS_ST_PORTION_OF_LT_DEBT | C147: BS071 | E147: 0 | F147: 25.5 | G147: 27.2 | H147: 25.5 | I147: 25.5 | J147: 22.9 | K147: 23.4 | L147: 24.5 | M147: 23.314443 | N147: 23.750138
A148: Non-Current Liabilities | B148: BS_ADJ_TOTAL_LT_LIABILITIES | C148: BS814 | E148: 1306.7 | F148: 1437.4 | G148: 1768.9 | H148: 1634.4 | I148: 1463.4 | J148: 1448.4 | K148: 1487.2 | L148: 1545.9 | M148: 1490.4881 | N148: 1494.9937
A149: Long-Term Debt | B149: BS_LONG_TERM_BORROWINGS | C149: BM286 | E149: 593.8 | F149: 594.4 | G149: 595 | H149: 595.7 | I149: 596.3 | J149: 597 | K149: 597.7 | L149: 598.3 | M149: 597.85 | N149: 597.85
...
